{
  "generationux-styles": {
    "background": {
      "value": "#581C87",
      "type": "color",
      "description": "background"
    },
    "foreground": {
      "value": "#99F6E4",
      "type": "color",
      "description": "foreground"
    },
    "card": {
      "value": "#581C87",
      "type": "color",
      "description": "card"
    },
    "card-foreground": {
      "value": "#99F6E4",
      "type": "color",
      "description": "card-foreground"
    },
    "popover": {
      "value": "#581C87",
      "type": "color",
      "description": "popover"
    },
    "popover-foreground": {
      "value": "#99F6E4",
      "type": "color",
      "description": "popover-foreground"
    },
    "primary": {
      "value": "#99F6E4",
      "type": "color",
      "description": "primary"
    },
    "primary-foreground": {
      "value": "#581C87",
      "type": "color",
      "description": "primary-foreground"
    },
    "secondary": {
      "value": "#6b21a8",
      "type": "color",
      "description": "secondary"
    },
    "secondary-foreground": {
      "value": "#99F6E4",
      "type": "color",
      "description": "secondary-foreground"
    },
    "muted": {
      "value": "#6b21a8",
      "type": "color",
      "description": "muted"
    },
    "muted-foreground": {
      "value": "#99F6E4",
      "type": "color",
      "description": "muted-foreground"
    },
    "accent": {
      "value": "#6b21a8",
      "type": "color",
      "description": "accent"
    },
    "accent-foreground": {
      "value": "#99F6E4",
      "type": "color",
      "description": "accent-foreground"
    },
    "destructive": {
      "value": "linear-gradient(-75deg, #581C87 0%, #581C87 4%, #99F6E4 4%, #99F6E4 8%, #581C87 8%, #581C87 12%, #99F6E4 12%, #99F6E4 16%, #581C87 16%, #581C87 20%, #99F6E4 20%, #99F6E4 24%, #581C87 24%, #581C87 28%, #99F6E4 28%, #99F6E4 32%, #581C87 32%, #581C87 36%, #99F6E4 36%, #99F6E4 40%, #581C87 40%, #581C87 44%, #99F6E4 44%, #99F6E4 48%, #581C87 48%, #581C87 52%, #99F6E4 52%, #99F6E4 56%, #581C87 56%, #581C87 60%, #99F6E4 60%, #99F6E4 64%, #581C87 64%, #581C87 68%, #99F6E4 68%, #99F6E4 72%, #581C87 72%, #581C87 76%, #99F6E4 76%, #99F6E4 80%, #581C87 80%, #581C87 84%, #99F6E4 84%, #99F6E4 88%, #581C87 88%, #581C87 92%, #99F6E4 92%,#99F6E4 92%, #581C87 96%, #581C87 96%, #99F6E4 100%)",
      "type": "color",
      "description": "destructive"
    },
    "destructive-foreground": {
      "value": "#99F6E4",
      "type": "color",
      "description": "destructive-foreground"
    },
    "border": {
      "value": "#99F6E4",
      "type": "color",
      "description": "border"
    },
    "input": {
      "value": "#99F6E4",
      "type": "color",
      "description": "input"
    },
    "ring": {
      "value": "#99F6E4",
      "type": "color",
      "description": "ring"
    },
    "boxshadow": {
      "value": "#3b0764",
      "type": "color",
      "description": "boxshadow"
    },
    "candy_min45°": {
      "value": "linear-gradient(-45deg, #581C87 0%, #581C87 1%, #99F6E4 1%, #99F6E4 2%, #581C87 2%, #581C87 3%, #99F6E4 3%, #99F6E4 4%, #581C87 4%, #581C87 5%, #99F6E4 5%, #99F6E4 6%, #581C87 6%, #581C87 7%, #99F6E4 7%, #99F6E4 8%, #581C87 8%, #581C87 9%, #99F6E4 9%, #99F6E4 10%, #581C87 10%, #581C87 11%, #99F6E4 11%, #99F6E4 12%, #581C87 12%, #581C87 13%, #99F6E4 13%, #99F6E4 14%, #581C87 14%, #581C87 15%, #99F6E4 15%, #99F6E4 16%, #581C87 16%, #581C87 17%, #99F6E4 17%, #99F6E4 18%, #581C87 18%, #581C87 19%, #99F6E4 19%, #99F6E4 20%, #581C87 20%, #581C87 21%, #99F6E4 21%, #99F6E4 22%, #581C87 22%, #581C87 23%, #99F6E4 23%, #99F6E4 24%, #581C87 24%, #581C87 25%, #99F6E4 25%, #99F6E4 26%, #581C87 26%, #581C87 27%, #99F6E4 27%, #99F6E4 28%, #581C87 28%, #581C87 29%, #99F6E4 29%, #99F6E4 30%, #581C87 30%, #581C87 31%, #99F6E4 31%, #99F6E4 32%, #581C87 32%, #581C87 33%, #99F6E4 33%, #99F6E4 34%, #581C87 34%, #581C87 35%, #99F6E4 35%, #99F6E4 36%, #581C87 36%, #581C87 37%, #99F6E4 37%, #99F6E4 38%, #581C87 38%, #581C87 39%, #99F6E4 39%, #99F6E4 40%, #581C87 40%, #581C87 41%, #99F6E4 41%, #99F6E4 42%, #581C87 42%, #581C87 43%, #99F6E4 43%, #99F6E4 44%, #581C87 44%, #581C87 45%, #99F6E4 45%, #99F6E4 46%, #581C87 46%, #581C87 47%, #99F6E4 47%, #99F6E4 48%, #581C87 48%, #581C87 49%, #99F6E4 49%, #99F6E4 50%, #581C87 50%, #581C87 51%, #99F6E4 51%, #99F6E4 52%, #581C87 52%, #581C87 53%, #99F6E4 53%, #99F6E4 54%, #581C87 54%, #581C87 55%, #99F6E4 55%, #99F6E4 56%, #581C87 56%, #581C87 57%, #99F6E4 57%, #99F6E4 58%, #581C87 58%, #581C87 59%, #99F6E4 59%, #99F6E4 60%, #581C87 60%, #581C87 61%, #99F6E4 61%, #99F6E4 62%, #581C87 62%, #581C87 63%, #99F6E4 63%, #99F6E4 64%, #581C87 64%, #581C87 65%, #99F6E4 65%, #99F6E4 66%, #581C87 66%, #581C87 67%, #99F6E4 67%, #99F6E4 68%, #581C87 68%, #581C87 69%, #99F6E4 69%, #99F6E4 70%, #581C87 70%, #581C87 71%, #99F6E4 71%, #99F6E4 72%, #581C87 72%, #581C87 73%, #99F6E4 73%, #99F6E4 74%, #581C87 74%, #581C87 75%, #99F6E4 75%, #99F6E4 76%, #581C87 76%, #581C87 77%, #99F6E4 77%, #99F6E4 78%, #581C87 78%, #581C87 79%, #99F6E4 79%, #99F6E4 80%, #581C87 80%, #581C87 81%, #99F6E4 81%, #99F6E4 82%, #581C87 82%, #581C87 83%, #99F6E4 83%, #99F6E4 84%, #581C87 84%, #581C87 85%, #99F6E4 85%, #99F6E4 86%, #581C87 86%, #581C87 87%, #99F6E4 87%, #99F6E4 88%, #581C87 88%, #581C87 89%, #99F6E4 89%, #99F6E4 90%, #581C87 90%, #581C87 91%, #99F6E4 91%, #99F6E4 92%, #581C87 92%, #581C87 93%, #99F6E4 93%, #99F6E4 94%, #581C87 94%, #581C87 95%, #99F6E4 95%, #99F6E4 96%, #581C87 96%, #581C87 97%, #99F6E4 97%, #99F6E4 98%, #581C87 98%, #581C87 99%, #99F6E4 99%, #99F6E4 100%)",
      "type": "color",
      "description": "candy_min45°"
    },
    "candy_45°": {
      "value": "linear-gradient(45deg, #581C87 0%, #581C87 1%, #99F6E4 1%, #99F6E4 2%, #581C87 2%, #581C87 3%, #99F6E4 3%, #99F6E4 4%, #581C87 4%, #581C87 5%, #99F6E4 5%, #99F6E4 6%, #581C87 6%, #581C87 7%, #99F6E4 7%, #99F6E4 8%, #581C87 8%, #581C87 9%, #99F6E4 9%, #99F6E4 10%, #581C87 10%, #581C87 11%, #99F6E4 11%, #99F6E4 12%, #581C87 12%, #581C87 13%, #99F6E4 13%, #99F6E4 14%, #581C87 14%, #581C87 15%, #99F6E4 15%, #99F6E4 16%, #581C87 16%, #581C87 17%, #99F6E4 17%, #99F6E4 18%, #581C87 18%, #581C87 19%, #99F6E4 19%, #99F6E4 20%, #581C87 20%, #581C87 21%, #99F6E4 21%, #99F6E4 22%, #581C87 22%, #581C87 23%, #99F6E4 23%, #99F6E4 24%, #581C87 24%, #581C87 25%, #99F6E4 25%, #99F6E4 26%, #581C87 26%, #581C87 27%, #99F6E4 27%, #99F6E4 28%, #581C87 28%, #581C87 29%, #99F6E4 29%, #99F6E4 30%, #581C87 30%, #581C87 31%, #99F6E4 31%, #99F6E4 32%, #581C87 32%, #581C87 33%, #99F6E4 33%, #99F6E4 34%, #581C87 34%, #581C87 35%, #99F6E4 35%, #99F6E4 36%, #581C87 36%, #581C87 37%, #99F6E4 37%, #99F6E4 38%, #581C87 38%, #581C87 39%, #99F6E4 39%, #99F6E4 40%, #581C87 40%, #581C87 41%, #99F6E4 41%, #99F6E4 42%, #581C87 42%, #581C87 43%, #99F6E4 43%, #99F6E4 44%, #581C87 44%, #581C87 45%, #99F6E4 45%, #99F6E4 46%, #581C87 46%, #581C87 47%, #99F6E4 47%, #99F6E4 48%, #581C87 48%, #581C87 49%, #99F6E4 49%, #99F6E4 50%, #581C87 50%, #581C87 51%, #99F6E4 51%, #99F6E4 52%, #581C87 52%, #581C87 53%, #99F6E4 53%, #99F6E4 54%, #581C87 54%, #581C87 55%, #99F6E4 55%, #99F6E4 56%, #581C87 56%, #581C87 57%, #99F6E4 57%, #99F6E4 58%, #581C87 58%, #581C87 59%, #99F6E4 59%, #99F6E4 60%, #581C87 60%, #581C87 61%, #99F6E4 61%, #99F6E4 62%, #581C87 62%, #581C87 63%, #99F6E4 63%, #99F6E4 64%, #581C87 64%, #581C87 65%, #99F6E4 65%, #99F6E4 66%, #581C87 66%, #581C87 67%, #99F6E4 67%, #99F6E4 68%, #581C87 68%, #581C87 69%, #99F6E4 69%, #99F6E4 70%, #581C87 70%, #581C87 71%, #99F6E4 71%, #99F6E4 72%, #581C87 72%, #581C87 73%, #99F6E4 73%, #99F6E4 74%, #581C87 74%, #581C87 75%, #99F6E4 75%, #99F6E4 76%, #581C87 76%, #581C87 77%, #99F6E4 77%, #99F6E4 78%, #581C87 78%, #581C87 79%, #99F6E4 79%, #99F6E4 80%, #581C87 80%, #581C87 81%, #99F6E4 81%, #99F6E4 82%, #581C87 82%, #581C87 83%, #99F6E4 83%, #99F6E4 84%, #581C87 84%, #581C87 85%, #99F6E4 85%, #99F6E4 86%, #581C87 86%, #581C87 87%, #99F6E4 87%, #99F6E4 88%, #581C87 88%, #581C87 89%, #99F6E4 89%, #99F6E4 90%, #581C87 90%, #581C87 91%, #99F6E4 91%, #99F6E4 92%, #581C87 92%, #581C87 93%, #99F6E4 93%, #99F6E4 94%, #581C87 94%, #581C87 95%, #99F6E4 95%, #99F6E4 96%, #581C87 96%, #581C87 97%, #99F6E4 97%, #99F6E4 98%, #581C87 98%, #581C87 99%, #99F6E4 99%, #99F6E4 100%)",
      "type": "color",
      "description": "candy_45°"
    },
    "candy_min60°": {
      "value": "linear-gradient(-60deg, #581C87 0%, #581C87 1%, #99F6E4 1%, #99F6E4 2%, #581C87 2%, #581C87 3%, #99F6E4 3%, #99F6E4 4%, #581C87 4%, #581C87 5%, #99F6E4 5%, #99F6E4 6%, #581C87 6%, #581C87 7%, #99F6E4 7%, #99F6E4 8%, #581C87 8%, #581C87 9%, #99F6E4 9%, #99F6E4 10%, #581C87 10%, #581C87 11%, #99F6E4 11%, #99F6E4 12%, #581C87 12%, #581C87 13%, #99F6E4 13%, #99F6E4 14%, #581C87 14%, #581C87 15%, #99F6E4 15%, #99F6E4 16%, #581C87 16%, #581C87 17%, #99F6E4 17%, #99F6E4 18%, #581C87 18%, #581C87 19%, #99F6E4 19%, #99F6E4 20%, #581C87 20%, #581C87 21%, #99F6E4 21%, #99F6E4 22%, #581C87 22%, #581C87 23%, #99F6E4 23%, #99F6E4 24%, #581C87 24%, #581C87 25%, #99F6E4 25%, #99F6E4 26%, #581C87 26%, #581C87 27%, #99F6E4 27%, #99F6E4 28%, #581C87 28%, #581C87 29%, #99F6E4 29%, #99F6E4 30%, #581C87 30%, #581C87 31%, #99F6E4 31%, #99F6E4 32%, #581C87 32%, #581C87 33%, #99F6E4 33%, #99F6E4 34%, #581C87 34%, #581C87 35%, #99F6E4 35%, #99F6E4 36%, #581C87 36%, #581C87 37%, #99F6E4 37%, #99F6E4 38%, #581C87 38%, #581C87 39%, #99F6E4 39%, #99F6E4 40%, #581C87 40%, #581C87 41%, #99F6E4 41%, #99F6E4 42%, #581C87 42%, #581C87 43%, #99F6E4 43%, #99F6E4 44%, #581C87 44%, #581C87 45%, #99F6E4 45%, #99F6E4 46%, #581C87 46%, #581C87 47%, #99F6E4 47%, #99F6E4 48%, #581C87 48%, #581C87 49%, #99F6E4 49%, #99F6E4 50%, #581C87 50%, #581C87 51%, #99F6E4 51%, #99F6E4 52%, #581C87 52%, #581C87 53%, #99F6E4 53%, #99F6E4 54%, #581C87 54%, #581C87 55%, #99F6E4 55%, #99F6E4 56%, #581C87 56%, #581C87 57%, #99F6E4 57%, #99F6E4 58%, #581C87 58%, #581C87 59%, #99F6E4 59%, #99F6E4 60%, #581C87 60%, #581C87 61%, #99F6E4 61%, #99F6E4 62%, #581C87 62%, #581C87 63%, #99F6E4 63%, #99F6E4 64%, #581C87 64%, #581C87 65%, #99F6E4 65%, #99F6E4 66%, #581C87 66%, #581C87 67%, #99F6E4 67%, #99F6E4 68%, #581C87 68%, #581C87 69%, #99F6E4 69%, #99F6E4 70%, #581C87 70%, #581C87 71%, #99F6E4 71%, #99F6E4 72%, #581C87 72%, #581C87 73%, #99F6E4 73%, #99F6E4 74%, #581C87 74%, #581C87 75%, #99F6E4 75%, #99F6E4 76%, #581C87 76%, #581C87 77%, #99F6E4 77%, #99F6E4 78%, #581C87 78%, #581C87 79%, #99F6E4 79%, #99F6E4 80%, #581C87 80%, #581C87 81%, #99F6E4 81%, #99F6E4 82%, #581C87 82%, #581C87 83%, #99F6E4 83%, #99F6E4 84%, #581C87 84%, #581C87 85%, #99F6E4 85%, #99F6E4 86%, #581C87 86%, #581C87 87%, #99F6E4 87%, #99F6E4 88%, #581C87 88%, #581C87 89%, #99F6E4 89%, #99F6E4 90%, #581C87 90%, #581C87 91%, #99F6E4 91%, #99F6E4 92%, #581C87 92%, #581C87 93%, #99F6E4 93%, #99F6E4 94%, #581C87 94%, #581C87 95%, #99F6E4 95%, #99F6E4 96%, #581C87 96%, #581C87 97%, #99F6E4 97%, #99F6E4 98%, #581C87 98%, #581C87 99%, #99F6E4 99%, #99F6E4 100%)",
      "type": "color",
      "description": "candy_min60°"
    },
    "candy_60°": {
      "value": "linear-gradient(60deg, #581C87 0%, #581C87 1%, #99F6E4 1%, #99F6E4 2%, #581C87 2%, #581C87 3%, #99F6E4 3%, #99F6E4 4%, #581C87 4%, #581C87 5%, #99F6E4 5%, #99F6E4 6%, #581C87 6%, #581C87 7%, #99F6E4 7%, #99F6E4 8%, #581C87 8%, #581C87 9%, #99F6E4 9%, #99F6E4 10%, #581C87 10%, #581C87 11%, #99F6E4 11%, #99F6E4 12%, #581C87 12%, #581C87 13%, #99F6E4 13%, #99F6E4 14%, #581C87 14%, #581C87 15%, #99F6E4 15%, #99F6E4 16%, #581C87 16%, #581C87 17%, #99F6E4 17%, #99F6E4 18%, #581C87 18%, #581C87 19%, #99F6E4 19%, #99F6E4 20%, #581C87 20%, #581C87 21%, #99F6E4 21%, #99F6E4 22%, #581C87 22%, #581C87 23%, #99F6E4 23%, #99F6E4 24%, #581C87 24%, #581C87 25%, #99F6E4 25%, #99F6E4 26%, #581C87 26%, #581C87 27%, #99F6E4 27%, #99F6E4 28%, #581C87 28%, #581C87 29%, #99F6E4 29%, #99F6E4 30%, #581C87 30%, #581C87 31%, #99F6E4 31%, #99F6E4 32%, #581C87 32%, #581C87 33%, #99F6E4 33%, #99F6E4 34%, #581C87 34%, #581C87 35%, #99F6E4 35%, #99F6E4 36%, #581C87 36%, #581C87 37%, #99F6E4 37%, #99F6E4 38%, #581C87 38%, #581C87 39%, #99F6E4 39%, #99F6E4 40%, #581C87 40%, #581C87 41%, #99F6E4 41%, #99F6E4 42%, #581C87 42%, #581C87 43%, #99F6E4 43%, #99F6E4 44%, #581C87 44%, #581C87 45%, #99F6E4 45%, #99F6E4 46%, #581C87 46%, #581C87 47%, #99F6E4 47%, #99F6E4 48%, #581C87 48%, #581C87 49%, #99F6E4 49%, #99F6E4 50%, #581C87 50%, #581C87 51%, #99F6E4 51%, #99F6E4 52%, #581C87 52%, #581C87 53%, #99F6E4 53%, #99F6E4 54%, #581C87 54%, #581C87 55%, #99F6E4 55%, #99F6E4 56%, #581C87 56%, #581C87 57%, #99F6E4 57%, #99F6E4 58%, #581C87 58%, #581C87 59%, #99F6E4 59%, #99F6E4 60%, #581C87 60%, #581C87 61%, #99F6E4 61%, #99F6E4 62%, #581C87 62%, #581C87 63%, #99F6E4 63%, #99F6E4 64%, #581C87 64%, #581C87 65%, #99F6E4 65%, #99F6E4 66%, #581C87 66%, #581C87 67%, #99F6E4 67%, #99F6E4 68%, #581C87 68%, #581C87 69%, #99F6E4 69%, #99F6E4 70%, #581C87 70%, #581C87 71%, #99F6E4 71%, #99F6E4 72%, #581C87 72%, #581C87 73%, #99F6E4 73%, #99F6E4 74%, #581C87 74%, #581C87 75%, #99F6E4 75%, #99F6E4 76%, #581C87 76%, #581C87 77%, #99F6E4 77%, #99F6E4 78%, #581C87 78%, #581C87 79%, #99F6E4 79%, #99F6E4 80%, #581C87 80%, #581C87 81%, #99F6E4 81%, #99F6E4 82%, #581C87 82%, #581C87 83%, #99F6E4 83%, #99F6E4 84%, #581C87 84%, #581C87 85%, #99F6E4 85%, #99F6E4 86%, #581C87 86%, #581C87 87%, #99F6E4 87%, #99F6E4 88%, #581C87 88%, #581C87 89%, #99F6E4 89%, #99F6E4 90%, #581C87 90%, #581C87 91%, #99F6E4 91%, #99F6E4 92%, #581C87 92%, #581C87 93%, #99F6E4 93%, #99F6E4 94%, #581C87 94%, #581C87 95%, #99F6E4 95%, #99F6E4 96%, #581C87 96%, #581C87 97%, #99F6E4 97%, #99F6E4 98%, #581C87 98%, #581C87 99%, #99F6E4 99%, #99F6E4 100%)",
      "type": "color",
      "description": "candy_60°"
    },
    "candy_min75°": {
      "value": "linear-gradient(-75deg, #581C87 0%, #581C87 1%, #99F6E4 1%, #99F6E4 2%, #581C87 2%, #581C87 3%, #99F6E4 3%, #99F6E4 4%, #581C87 4%, #581C87 5%, #99F6E4 5%, #99F6E4 6%, #581C87 6%, #581C87 7%, #99F6E4 7%, #99F6E4 8%, #581C87 8%, #581C87 9%, #99F6E4 9%, #99F6E4 10%, #581C87 10%, #581C87 11%, #99F6E4 11%, #99F6E4 12%, #581C87 12%, #581C87 13%, #99F6E4 13%, #99F6E4 14%, #581C87 14%, #581C87 15%, #99F6E4 15%, #99F6E4 16%, #581C87 16%, #581C87 17%, #99F6E4 17%, #99F6E4 18%, #581C87 18%, #581C87 19%, #99F6E4 19%, #99F6E4 20%, #581C87 20%, #581C87 21%, #99F6E4 21%, #99F6E4 22%, #581C87 22%, #581C87 23%, #99F6E4 23%, #99F6E4 24%, #581C87 24%, #581C87 25%, #99F6E4 25%, #99F6E4 26%, #581C87 26%, #581C87 27%, #99F6E4 27%, #99F6E4 28%, #581C87 28%, #581C87 29%, #99F6E4 29%, #99F6E4 30%, #581C87 30%, #581C87 31%, #99F6E4 31%, #99F6E4 32%, #581C87 32%, #581C87 33%, #99F6E4 33%, #99F6E4 34%, #581C87 34%, #581C87 35%, #99F6E4 35%, #99F6E4 36%, #581C87 36%, #581C87 37%, #99F6E4 37%, #99F6E4 38%, #581C87 38%, #581C87 39%, #99F6E4 39%, #99F6E4 40%, #581C87 40%, #581C87 41%, #99F6E4 41%, #99F6E4 42%, #581C87 42%, #581C87 43%, #99F6E4 43%, #99F6E4 44%, #581C87 44%, #581C87 45%, #99F6E4 45%, #99F6E4 46%, #581C87 46%, #581C87 47%, #99F6E4 47%, #99F6E4 48%, #581C87 48%, #581C87 49%, #99F6E4 49%, #99F6E4 50%, #581C87 50%, #581C87 51%, #99F6E4 51%, #99F6E4 52%, #581C87 52%, #581C87 53%, #99F6E4 53%, #99F6E4 54%, #581C87 54%, #581C87 55%, #99F6E4 55%, #99F6E4 56%, #581C87 56%, #581C87 57%, #99F6E4 57%, #99F6E4 58%, #581C87 58%, #581C87 59%, #99F6E4 59%, #99F6E4 60%, #581C87 60%, #581C87 61%, #99F6E4 61%, #99F6E4 62%, #581C87 62%, #581C87 63%, #99F6E4 63%, #99F6E4 64%, #581C87 64%, #581C87 65%, #99F6E4 65%, #99F6E4 66%, #581C87 66%, #581C87 67%, #99F6E4 67%, #99F6E4 68%, #581C87 68%, #581C87 69%, #99F6E4 69%, #99F6E4 70%, #581C87 70%, #581C87 71%, #99F6E4 71%, #99F6E4 72%, #581C87 72%, #581C87 73%, #99F6E4 73%, #99F6E4 74%, #581C87 74%, #581C87 75%, #99F6E4 75%, #99F6E4 76%, #581C87 76%, #581C87 77%, #99F6E4 77%, #99F6E4 78%, #581C87 78%, #581C87 79%, #99F6E4 79%, #99F6E4 80%, #581C87 80%, #581C87 81%, #99F6E4 81%, #99F6E4 82%, #581C87 82%, #581C87 83%, #99F6E4 83%, #99F6E4 84%, #581C87 84%, #581C87 85%, #99F6E4 85%, #99F6E4 86%, #581C87 86%, #581C87 87%, #99F6E4 87%, #99F6E4 88%, #581C87 88%, #581C87 89%, #99F6E4 89%, #99F6E4 90%, #581C87 90%, #581C87 91%, #99F6E4 91%, #99F6E4 92%, #581C87 92%, #581C87 93%, #99F6E4 93%, #99F6E4 94%, #581C87 94%, #581C87 95%, #99F6E4 95%, #99F6E4 96%, #581C87 96%, #581C87 97%, #99F6E4 97%, #99F6E4 98%, #581C87 98%, #581C87 99%, #99F6E4 99%, #99F6E4 100%)",
      "type": "color",
      "description": "candy_min75°"
    },
    "candy_75°": {
      "value": "linear-gradient(75deg, #581C87 0%, #581C87 1%, #99F6E4 1%, #99F6E4 2%, #581C87 2%, #581C87 3%, #99F6E4 3%, #99F6E4 4%, #581C87 4%, #581C87 5%, #99F6E4 5%, #99F6E4 6%, #581C87 6%, #581C87 7%, #99F6E4 7%, #99F6E4 8%, #581C87 8%, #581C87 9%, #99F6E4 9%, #99F6E4 10%, #581C87 10%, #581C87 11%, #99F6E4 11%, #99F6E4 12%, #581C87 12%, #581C87 13%, #99F6E4 13%, #99F6E4 14%, #581C87 14%, #581C87 15%, #99F6E4 15%, #99F6E4 16%, #581C87 16%, #581C87 17%, #99F6E4 17%, #99F6E4 18%, #581C87 18%, #581C87 19%, #99F6E4 19%, #99F6E4 20%, #581C87 20%, #581C87 21%, #99F6E4 21%, #99F6E4 22%, #581C87 22%, #581C87 23%, #99F6E4 23%, #99F6E4 24%, #581C87 24%, #581C87 25%, #99F6E4 25%, #99F6E4 26%, #581C87 26%, #581C87 27%, #99F6E4 27%, #99F6E4 28%, #581C87 28%, #581C87 29%, #99F6E4 29%, #99F6E4 30%, #581C87 30%, #581C87 31%, #99F6E4 31%, #99F6E4 32%, #581C87 32%, #581C87 33%, #99F6E4 33%, #99F6E4 34%, #581C87 34%, #581C87 35%, #99F6E4 35%, #99F6E4 36%, #581C87 36%, #581C87 37%, #99F6E4 37%, #99F6E4 38%, #581C87 38%, #581C87 39%, #99F6E4 39%, #99F6E4 40%, #581C87 40%, #581C87 41%, #99F6E4 41%, #99F6E4 42%, #581C87 42%, #581C87 43%, #99F6E4 43%, #99F6E4 44%, #581C87 44%, #581C87 45%, #99F6E4 45%, #99F6E4 46%, #581C87 46%, #581C87 47%, #99F6E4 47%, #99F6E4 48%, #581C87 48%, #581C87 49%, #99F6E4 49%, #99F6E4 50%, #581C87 50%, #581C87 51%, #99F6E4 51%, #99F6E4 52%, #581C87 52%, #581C87 53%, #99F6E4 53%, #99F6E4 54%, #581C87 54%, #581C87 55%, #99F6E4 55%, #99F6E4 56%, #581C87 56%, #581C87 57%, #99F6E4 57%, #99F6E4 58%, #581C87 58%, #581C87 59%, #99F6E4 59%, #99F6E4 60%, #581C87 60%, #581C87 61%, #99F6E4 61%, #99F6E4 62%, #581C87 62%, #581C87 63%, #99F6E4 63%, #99F6E4 64%, #581C87 64%, #581C87 65%, #99F6E4 65%, #99F6E4 66%, #581C87 66%, #581C87 67%, #99F6E4 67%, #99F6E4 68%, #581C87 68%, #581C87 69%, #99F6E4 69%, #99F6E4 70%, #581C87 70%, #581C87 71%, #99F6E4 71%, #99F6E4 72%, #581C87 72%, #581C87 73%, #99F6E4 73%, #99F6E4 74%, #581C87 74%, #581C87 75%, #99F6E4 75%, #99F6E4 76%, #581C87 76%, #581C87 77%, #99F6E4 77%, #99F6E4 78%, #581C87 78%, #581C87 79%, #99F6E4 79%, #99F6E4 80%, #581C87 80%, #581C87 81%, #99F6E4 81%, #99F6E4 82%, #581C87 82%, #581C87 83%, #99F6E4 83%, #99F6E4 84%, #581C87 84%, #581C87 85%, #99F6E4 85%, #99F6E4 86%, #581C87 86%, #581C87 87%, #99F6E4 87%, #99F6E4 88%, #581C87 88%, #581C87 89%, #99F6E4 89%, #99F6E4 90%, #581C87 90%, #581C87 91%, #99F6E4 91%, #99F6E4 92%, #581C87 92%, #581C87 93%, #99F6E4 93%, #99F6E4 94%, #581C87 94%, #581C87 95%, #99F6E4 95%, #99F6E4 96%, #581C87 96%, #581C87 97%, #99F6E4 97%, #99F6E4 98%, #581C87 98%, #581C87 99%, #99F6E4 99%, #99F6E4 100%)",
      "type": "color",
      "description": "candy_75°"
    },
    "candy_0°": {
      "value": "linear-gradient(0deg, #581C87 0%, #581C87 1%, #99F6E4 1%, #99F6E4 2%, #581C87 2%, #581C87 3%, #99F6E4 3%, #99F6E4 4%, #581C87 4%, #581C87 5%, #99F6E4 5%, #99F6E4 6%, #581C87 6%, #581C87 7%, #99F6E4 7%, #99F6E4 8%, #581C87 8%, #581C87 9%, #99F6E4 9%, #99F6E4 10%, #581C87 10%, #581C87 11%, #99F6E4 11%, #99F6E4 12%, #581C87 12%, #581C87 13%, #99F6E4 13%, #99F6E4 14%, #581C87 14%, #581C87 15%, #99F6E4 15%, #99F6E4 16%, #581C87 16%, #581C87 17%, #99F6E4 17%, #99F6E4 18%, #581C87 18%, #581C87 19%, #99F6E4 19%, #99F6E4 20%, #581C87 20%, #581C87 21%, #99F6E4 21%, #99F6E4 22%, #581C87 22%, #581C87 23%, #99F6E4 23%, #99F6E4 24%, #581C87 24%, #581C87 25%, #99F6E4 25%, #99F6E4 26%, #581C87 26%, #581C87 27%, #99F6E4 27%, #99F6E4 28%, #581C87 28%, #581C87 29%, #99F6E4 29%, #99F6E4 30%, #581C87 30%, #581C87 31%, #99F6E4 31%, #99F6E4 32%, #581C87 32%, #581C87 33%, #99F6E4 33%, #99F6E4 34%, #581C87 34%, #581C87 35%, #99F6E4 35%, #99F6E4 36%, #581C87 36%, #581C87 37%, #99F6E4 37%, #99F6E4 38%, #581C87 38%, #581C87 39%, #99F6E4 39%, #99F6E4 40%, #581C87 40%, #581C87 41%, #99F6E4 41%, #99F6E4 42%, #581C87 42%, #581C87 43%, #99F6E4 43%, #99F6E4 44%, #581C87 44%, #581C87 45%, #99F6E4 45%, #99F6E4 46%, #581C87 46%, #581C87 47%, #99F6E4 47%, #99F6E4 48%, #581C87 48%, #581C87 49%, #99F6E4 49%, #99F6E4 50%, #581C87 50%, #581C87 51%, #99F6E4 51%, #99F6E4 52%, #581C87 52%, #581C87 53%, #99F6E4 53%, #99F6E4 54%, #581C87 54%, #581C87 55%, #99F6E4 55%, #99F6E4 56%, #581C87 56%, #581C87 57%, #99F6E4 57%, #99F6E4 58%, #581C87 58%, #581C87 59%, #99F6E4 59%, #99F6E4 60%, #581C87 60%, #581C87 61%, #99F6E4 61%, #99F6E4 62%, #581C87 62%, #581C87 63%, #99F6E4 63%, #99F6E4 64%, #581C87 64%, #581C87 65%, #99F6E4 65%, #99F6E4 66%, #581C87 66%, #581C87 67%, #99F6E4 67%, #99F6E4 68%, #581C87 68%, #581C87 69%, #99F6E4 69%, #99F6E4 70%, #581C87 70%, #581C87 71%, #99F6E4 71%, #99F6E4 72%, #581C87 72%, #581C87 73%, #99F6E4 73%, #99F6E4 74%, #581C87 74%, #581C87 75%, #99F6E4 75%, #99F6E4 76%, #581C87 76%, #581C87 77%, #99F6E4 77%, #99F6E4 78%, #581C87 78%, #581C87 79%, #99F6E4 79%, #99F6E4 80%, #581C87 80%, #581C87 81%, #99F6E4 81%, #99F6E4 82%, #581C87 82%, #581C87 83%, #99F6E4 83%, #99F6E4 84%, #581C87 84%, #581C87 85%, #99F6E4 85%, #99F6E4 86%, #581C87 86%, #581C87 87%, #99F6E4 87%, #99F6E4 88%, #581C87 88%, #581C87 89%, #99F6E4 89%, #99F6E4 90%, #581C87 90%, #581C87 91%, #99F6E4 91%, #99F6E4 92%, #581C87 92%, #581C87 93%, #99F6E4 93%, #99F6E4 94%, #581C87 94%, #581C87 95%, #99F6E4 95%, #99F6E4 96%, #581C87 96%, #581C87 97%, #99F6E4 97%, #99F6E4 98%, #581C87 98%, #581C87 99%, #99F6E4 99%, #99F6E4 100%)",
      "type": "color",
      "description": "candy_0°"
    },
    "candy_90°": {
      "value": "linear-gradient(90deg, #581C87 0%, #581C87 1%, #99F6E4 1%, #99F6E4 2%, #581C87 2%, #581C87 3%, #99F6E4 3%, #99F6E4 4%, #581C87 4%, #581C87 5%, #99F6E4 5%, #99F6E4 6%, #581C87 6%, #581C87 7%, #99F6E4 7%, #99F6E4 8%, #581C87 8%, #581C87 9%, #99F6E4 9%, #99F6E4 10%, #581C87 10%, #581C87 11%, #99F6E4 11%, #99F6E4 12%, #581C87 12%, #581C87 13%, #99F6E4 13%, #99F6E4 14%, #581C87 14%, #581C87 15%, #99F6E4 15%, #99F6E4 16%, #581C87 16%, #581C87 17%, #99F6E4 17%, #99F6E4 18%, #581C87 18%, #581C87 19%, #99F6E4 19%, #99F6E4 20%, #581C87 20%, #581C87 21%, #99F6E4 21%, #99F6E4 22%, #581C87 22%, #581C87 23%, #99F6E4 23%, #99F6E4 24%, #581C87 24%, #581C87 25%, #99F6E4 25%, #99F6E4 26%, #581C87 26%, #581C87 27%, #99F6E4 27%, #99F6E4 28%, #581C87 28%, #581C87 29%, #99F6E4 29%, #99F6E4 30%, #581C87 30%, #581C87 31%, #99F6E4 31%, #99F6E4 32%, #581C87 32%, #581C87 33%, #99F6E4 33%, #99F6E4 34%, #581C87 34%, #581C87 35%, #99F6E4 35%, #99F6E4 36%, #581C87 36%, #581C87 37%, #99F6E4 37%, #99F6E4 38%, #581C87 38%, #581C87 39%, #99F6E4 39%, #99F6E4 40%, #581C87 40%, #581C87 41%, #99F6E4 41%, #99F6E4 42%, #581C87 42%, #581C87 43%, #99F6E4 43%, #99F6E4 44%, #581C87 44%, #581C87 45%, #99F6E4 45%, #99F6E4 46%, #581C87 46%, #581C87 47%, #99F6E4 47%, #99F6E4 48%, #581C87 48%, #581C87 49%, #99F6E4 49%, #99F6E4 50%, #581C87 50%, #581C87 51%, #99F6E4 51%, #99F6E4 52%, #581C87 52%, #581C87 53%, #99F6E4 53%, #99F6E4 54%, #581C87 54%, #581C87 55%, #99F6E4 55%, #99F6E4 56%, #581C87 56%, #581C87 57%, #99F6E4 57%, #99F6E4 58%, #581C87 58%, #581C87 59%, #99F6E4 59%, #99F6E4 60%, #581C87 60%, #581C87 61%, #99F6E4 61%, #99F6E4 62%, #581C87 62%, #581C87 63%, #99F6E4 63%, #99F6E4 64%, #581C87 64%, #581C87 65%, #99F6E4 65%, #99F6E4 66%, #581C87 66%, #581C87 67%, #99F6E4 67%, #99F6E4 68%, #581C87 68%, #581C87 69%, #99F6E4 69%, #99F6E4 70%, #581C87 70%, #581C87 71%, #99F6E4 71%, #99F6E4 72%, #581C87 72%, #581C87 73%, #99F6E4 73%, #99F6E4 74%, #581C87 74%, #581C87 75%, #99F6E4 75%, #99F6E4 76%, #581C87 76%, #581C87 77%, #99F6E4 77%, #99F6E4 78%, #581C87 78%, #581C87 79%, #99F6E4 79%, #99F6E4 80%, #581C87 80%, #581C87 81%, #99F6E4 81%, #99F6E4 82%, #581C87 82%, #581C87 83%, #99F6E4 83%, #99F6E4 84%, #581C87 84%, #581C87 85%, #99F6E4 85%, #99F6E4 86%, #581C87 86%, #581C87 87%, #99F6E4 87%, #99F6E4 88%, #581C87 88%, #581C87 89%, #99F6E4 89%, #99F6E4 90%, #581C87 90%, #581C87 91%, #99F6E4 91%, #99F6E4 92%, #581C87 92%, #581C87 93%, #99F6E4 93%, #99F6E4 94%, #581C87 94%, #581C87 95%, #99F6E4 95%, #99F6E4 96%, #581C87 96%, #581C87 97%, #99F6E4 97%, #99F6E4 98%, #581C87 98%, #581C87 99%, #99F6E4 99%, #99F6E4 100%)",
      "type": "color",
      "description": "candy_90°"
    },
    "stripe_min45°": {
      "value": "linear-gradient(-45deg, #581C87 0%, #581C87 1%, #99F6E4 1%, #99F6E4 5%, #581C87 5%, #581C87 6%, #99F6E4 6%, #99F6E4 10%, #581C87 10%, #581C87 11%, #99F6E4 11%, #99F6E4 15%, #581C87 15%, #581C87 16%, #99F6E4 16%, #99F6E4 20%, #581C87 20%, #581C87 21%, #99F6E4 21%, #99F6E4 25%, #581C87 25%, #581C87 26%, #99F6E4 26%, #99F6E4 30%, #581C87 30%, #581C87 31%, #99F6E4 31%, #99F6E4 35%, #581C87 35%, #581C87 36%, #99F6E4 36%, #99F6E4 40%, #581C87 40%, #581C87 41%, #99F6E4 41%, #99F6E4 45%, #581C87 45%, #581C87 46%, #99F6E4 46%, #99F6E4 50%, #581C87 50%, #581C87 51%, #99F6E4 51%, #99F6E4 55%, #581C87 55%, #581C87 56%, #99F6E4 56%, #99F6E4 60%, #581C87 60%, #581C87 61%, #99F6E4 61%, #99F6E4 65%, #581C87 65%, #581C87 66%, #99F6E4 66%, #99F6E4 70%, #581C87 70%, #581C87 71%, #99F6E4 71%, #99F6E4 75%, #581C87 75%, #581C87 76%, #99F6E4 76%, #99F6E4 80%, #581C87 80%, #581C87 81%, #99F6E4 81%, #99F6E4 85%, #581C87 85%, #581C87 86%, #99F6E4 86%, #99F6E4 90%, #581C87 90%, #581C87 91%, #99F6E4 91%, #99F6E4 95%, #581C87 95%, #581C87 96%, #99F6E4 96%, #99F6E4 100%)",
      "type": "color",
      "description": "stripe_min45°"
    },
    "stripe_45°": {
      "value": "linear-gradient(45deg, #581C87 0%, #581C87 1%, #99F6E4 1%, #99F6E4 5%, #581C87 5%, #581C87 6%, #99F6E4 6%, #99F6E4 10%, #581C87 10%, #581C87 11%, #99F6E4 11%, #99F6E4 15%, #581C87 15%, #581C87 16%, #99F6E4 16%, #99F6E4 20%, #581C87 20%, #581C87 21%, #99F6E4 21%, #99F6E4 25%, #581C87 25%, #581C87 26%, #99F6E4 26%, #99F6E4 30%, #581C87 30%, #581C87 31%, #99F6E4 31%, #99F6E4 35%, #581C87 35%, #581C87 36%, #99F6E4 36%, #99F6E4 40%, #581C87 40%, #581C87 41%, #99F6E4 41%, #99F6E4 45%, #581C87 45%, #581C87 46%, #99F6E4 46%, #99F6E4 50%, #581C87 50%, #581C87 51%, #99F6E4 51%, #99F6E4 55%, #581C87 55%, #581C87 56%, #99F6E4 56%, #99F6E4 60%, #581C87 60%, #581C87 61%, #99F6E4 61%, #99F6E4 65%, #581C87 65%, #581C87 66%, #99F6E4 66%, #99F6E4 70%, #581C87 70%, #581C87 71%, #99F6E4 71%, #99F6E4 75%, #581C87 75%, #581C87 76%, #99F6E4 76%, #99F6E4 80%, #581C87 80%, #581C87 81%, #99F6E4 81%, #99F6E4 85%, #581C87 85%, #581C87 86%, #99F6E4 86%, #99F6E4 90%, #581C87 90%, #581C87 91%, #99F6E4 91%, #99F6E4 95%, #581C87 95%, #581C87 96%, #99F6E4 96%, #99F6E4 100%)",
      "type": "color",
      "description": "stripe_45°"
    },
    "stripe_min60°": {
      "value": "linear-gradient(-60deg, #581C87 0%, #581C87 1%, #99F6E4 1%, #99F6E4 5%, #581C87 5%, #581C87 6%, #99F6E4 6%, #99F6E4 10%, #581C87 10%, #581C87 11%, #99F6E4 11%, #99F6E4 15%, #581C87 15%, #581C87 16%, #99F6E4 16%, #99F6E4 20%, #581C87 20%, #581C87 21%, #99F6E4 21%, #99F6E4 25%, #581C87 25%, #581C87 26%, #99F6E4 26%, #99F6E4 30%, #581C87 30%, #581C87 31%, #99F6E4 31%, #99F6E4 35%, #581C87 35%, #581C87 36%, #99F6E4 36%, #99F6E4 40%, #581C87 40%, #581C87 41%, #99F6E4 41%, #99F6E4 45%, #581C87 45%, #581C87 46%, #99F6E4 46%, #99F6E4 50%, #581C87 50%, #581C87 51%, #99F6E4 51%, #99F6E4 55%, #581C87 55%, #581C87 56%, #99F6E4 56%, #99F6E4 60%, #581C87 60%, #581C87 61%, #99F6E4 61%, #99F6E4 65%, #581C87 65%, #581C87 66%, #99F6E4 66%, #99F6E4 70%, #581C87 70%, #581C87 71%, #99F6E4 71%, #99F6E4 75%, #581C87 75%, #581C87 76%, #99F6E4 76%, #99F6E4 80%, #581C87 80%, #581C87 81%, #99F6E4 81%, #99F6E4 85%, #581C87 85%, #581C87 86%, #99F6E4 86%, #99F6E4 90%, #581C87 90%, #581C87 91%, #99F6E4 91%, #99F6E4 95%, #581C87 95%, #581C87 96%, #99F6E4 96%, #99F6E4 100%)",
      "type": "color",
      "description": "stripe_min60°"
    },
    "stripe_60°": {
      "value": "linear-gradient(60deg, #581C87 0%, #581C87 1%, #99F6E4 1%, #99F6E4 5%, #581C87 5%, #581C87 6%, #99F6E4 6%, #99F6E4 10%, #581C87 10%, #581C87 11%, #99F6E4 11%, #99F6E4 15%, #581C87 15%, #581C87 16%, #99F6E4 16%, #99F6E4 20%, #581C87 20%, #581C87 21%, #99F6E4 21%, #99F6E4 25%, #581C87 25%, #581C87 26%, #99F6E4 26%, #99F6E4 30%, #581C87 30%, #581C87 31%, #99F6E4 31%, #99F6E4 35%, #581C87 35%, #581C87 36%, #99F6E4 36%, #99F6E4 40%, #581C87 40%, #581C87 41%, #99F6E4 41%, #99F6E4 45%, #581C87 45%, #581C87 46%, #99F6E4 46%, #99F6E4 50%, #581C87 50%, #581C87 51%, #99F6E4 51%, #99F6E4 55%, #581C87 55%, #581C87 56%, #99F6E4 56%, #99F6E4 60%, #581C87 60%, #581C87 61%, #99F6E4 61%, #99F6E4 65%, #581C87 65%, #581C87 66%, #99F6E4 66%, #99F6E4 70%, #581C87 70%, #581C87 71%, #99F6E4 71%, #99F6E4 75%, #581C87 75%, #581C87 76%, #99F6E4 76%, #99F6E4 80%, #581C87 80%, #581C87 81%, #99F6E4 81%, #99F6E4 85%, #581C87 85%, #581C87 86%, #99F6E4 86%, #99F6E4 90%, #581C87 90%, #581C87 91%, #99F6E4 91%, #99F6E4 95%, #581C87 95%, #581C87 96%, #99F6E4 96%, #99F6E4 100%)",
      "type": "color",
      "description": "stripe_60°"
    },
    "stripe_min75°": {
      "value": "linear-gradient(-75deg, #581C87 0%, #581C87 1%, #99F6E4 1%, #99F6E4 5%, #581C87 5%, #581C87 6%, #99F6E4 6%, #99F6E4 10%, #581C87 10%, #581C87 11%, #99F6E4 11%, #99F6E4 15%, #581C87 15%, #581C87 16%, #99F6E4 16%, #99F6E4 20%, #581C87 20%, #581C87 21%, #99F6E4 21%, #99F6E4 25%, #581C87 25%, #581C87 26%, #99F6E4 26%, #99F6E4 30%, #581C87 30%, #581C87 31%, #99F6E4 31%, #99F6E4 35%, #581C87 35%, #581C87 36%, #99F6E4 36%, #99F6E4 40%, #581C87 40%, #581C87 41%, #99F6E4 41%, #99F6E4 45%, #581C87 45%, #581C87 46%, #99F6E4 46%, #99F6E4 50%, #581C87 50%, #581C87 51%, #99F6E4 51%, #99F6E4 55%, #581C87 55%, #581C87 56%, #99F6E4 56%, #99F6E4 60%, #581C87 60%, #581C87 61%, #99F6E4 61%, #99F6E4 65%, #581C87 65%, #581C87 66%, #99F6E4 66%, #99F6E4 70%, #581C87 70%, #581C87 71%, #99F6E4 71%, #99F6E4 75%, #581C87 75%, #581C87 76%, #99F6E4 76%, #99F6E4 80%, #581C87 80%, #581C87 81%, #99F6E4 81%, #99F6E4 85%, #581C87 85%, #581C87 86%, #99F6E4 86%, #99F6E4 90%, #581C87 90%, #581C87 91%, #99F6E4 91%, #99F6E4 95%, #581C87 95%, #581C87 96%, #99F6E4 96%, #99F6E4 100%)",
      "type": "color",
      "description": "stripe_min75°"
    },
    "stripe_75°": {
      "value": "linear-gradient(75deg, #581C87 0%, #581C87 1%, #99F6E4 1%, #99F6E4 5%, #581C87 5%, #581C87 6%, #99F6E4 6%, #99F6E4 10%, #581C87 10%, #581C87 11%, #99F6E4 11%, #99F6E4 15%, #581C87 15%, #581C87 16%, #99F6E4 16%, #99F6E4 20%, #581C87 20%, #581C87 21%, #99F6E4 21%, #99F6E4 25%, #581C87 25%, #581C87 26%, #99F6E4 26%, #99F6E4 30%, #581C87 30%, #581C87 31%, #99F6E4 31%, #99F6E4 35%, #581C87 35%, #581C87 36%, #99F6E4 36%, #99F6E4 40%, #581C87 40%, #581C87 41%, #99F6E4 41%, #99F6E4 45%, #581C87 45%, #581C87 46%, #99F6E4 46%, #99F6E4 50%, #581C87 50%, #581C87 51%, #99F6E4 51%, #99F6E4 55%, #581C87 55%, #581C87 56%, #99F6E4 56%, #99F6E4 60%, #581C87 60%, #581C87 61%, #99F6E4 61%, #99F6E4 65%, #581C87 65%, #581C87 66%, #99F6E4 66%, #99F6E4 70%, #581C87 70%, #581C87 71%, #99F6E4 71%, #99F6E4 75%, #581C87 75%, #581C87 76%, #99F6E4 76%, #99F6E4 80%, #581C87 80%, #581C87 81%, #99F6E4 81%, #99F6E4 85%, #581C87 85%, #581C87 86%, #99F6E4 86%, #99F6E4 90%, #581C87 90%, #581C87 91%, #99F6E4 91%, #99F6E4 95%, #581C87 95%, #581C87 96%, #99F6E4 96%, #99F6E4 100%)",
      "type": "color",
      "description": "stripe_75°"
    },
    "stripe_0°": {
      "value": "linear-gradient(0deg, #581C87 0%, #581C87 1%, #99F6E4 1%, #99F6E4 5%, #581C87 5%, #581C87 6%, #99F6E4 6%, #99F6E4 10%, #581C87 10%, #581C87 11%, #99F6E4 11%, #99F6E4 15%, #581C87 15%, #581C87 16%, #99F6E4 16%, #99F6E4 20%, #581C87 20%, #581C87 21%, #99F6E4 21%, #99F6E4 25%, #581C87 25%, #581C87 26%, #99F6E4 26%, #99F6E4 30%, #581C87 30%, #581C87 31%, #99F6E4 31%, #99F6E4 35%, #581C87 35%, #581C87 36%, #99F6E4 36%, #99F6E4 40%, #581C87 40%, #581C87 41%, #99F6E4 41%, #99F6E4 45%, #581C87 45%, #581C87 46%, #99F6E4 46%, #99F6E4 50%, #581C87 50%, #581C87 51%, #99F6E4 51%, #99F6E4 55%, #581C87 55%, #581C87 56%, #99F6E4 56%, #99F6E4 60%, #581C87 60%, #581C87 61%, #99F6E4 61%, #99F6E4 65%, #581C87 65%, #581C87 66%, #99F6E4 66%, #99F6E4 70%, #581C87 70%, #581C87 71%, #99F6E4 71%, #99F6E4 75%, #581C87 75%, #581C87 76%, #99F6E4 76%, #99F6E4 80%, #581C87 80%, #581C87 81%, #99F6E4 81%, #99F6E4 85%, #581C87 85%, #581C87 86%, #99F6E4 86%, #99F6E4 90%, #581C87 90%, #581C87 91%, #99F6E4 91%, #99F6E4 95%, #581C87 95%, #581C87 96%, #99F6E4 96%, #99F6E4 100%)",
      "type": "color",
      "description": "stripe_0°"
    },
    "stripe_90°": {
      "value": "linear-gradient(-90deg, #581C87 0%, #581C87 1%, #99F6E4 1%, #99F6E4 5%, #581C87 5%, #581C87 6%, #99F6E4 6%, #99F6E4 10%, #581C87 10%, #581C87 11%, #99F6E4 11%, #99F6E4 15%, #581C87 15%, #581C87 16%, #99F6E4 16%, #99F6E4 20%, #581C87 20%, #581C87 21%, #99F6E4 21%, #99F6E4 25%, #581C87 25%, #581C87 26%, #99F6E4 26%, #99F6E4 30%, #581C87 30%, #581C87 31%, #99F6E4 31%, #99F6E4 35%, #581C87 35%, #581C87 36%, #99F6E4 36%, #99F6E4 40%, #581C87 40%, #581C87 41%, #99F6E4 41%, #99F6E4 45%, #581C87 45%, #581C87 46%, #99F6E4 46%, #99F6E4 50%, #581C87 50%, #581C87 51%, #99F6E4 51%, #99F6E4 55%, #581C87 55%, #581C87 56%, #99F6E4 56%, #99F6E4 60%, #581C87 60%, #581C87 61%, #99F6E4 61%, #99F6E4 65%, #581C87 65%, #581C87 66%, #99F6E4 66%, #99F6E4 70%, #581C87 70%, #581C87 71%, #99F6E4 71%, #99F6E4 75%, #581C87 75%, #581C87 76%, #99F6E4 76%, #99F6E4 80%, #581C87 80%, #581C87 81%, #99F6E4 81%, #99F6E4 85%, #581C87 85%, #581C87 86%, #99F6E4 86%, #99F6E4 90%, #581C87 90%, #581C87 91%, #99F6E4 91%, #99F6E4 95%, #581C87 95%, #581C87 96%, #99F6E4 96%, #99F6E4 100%)",
      "type": "color",
      "description": "stripe_90°"
    }
  }
}