{
  "generationux-styles": {
    "background": {
      "value": "#6ee7b7",
      "type": "color",
      "description": "background"
    },
    "foreground": {
      "value": "#6366f1",
      "type": "color",
      "description": "foreground"
    },
    "card": {
      "value": "#6ee7b7",
      "type": "color",
      "description": "card"
    },
    "card-foreground": {
      "value": "#4f46e5",
      "type": "color",
      "description": "card-foreground"
    },
    "popover": {
      "value": "#6ee7b7",
      "type": "color",
      "description": "popover"
    },
    "popover-foreground": {
      "value": "#4f46e5",
      "type": "color",
      "description": "popover-foreground"
    },
    "primary": {
      "value": "#6366f1",
      "type": "color",
      "description": "primary"
    },
    "primary-foreground": {
      "value": "#6ee7b7",
      "type": "color",
      "description": "primary-foreground"
    },
    "secondary": {
      "value": "#34d399",
      "type": "color",
      "description": "secondary"
    },
    "secondary-foreground": {
      "value": "#4f46e5",
      "type": "color",
      "description": "secondary-foreground"
    },
    "muted": {
      "value": "#34d399",
      "type": "color",
      "description": "muted"
    },
    "muted-foreground": {
      "value": "#4f46e5",
      "type": "color",
      "description": "muted-foreground"
    },
    "accent": {
      "value": "#34d399",
      "type": "color",
      "description": "accent"
    },
    "accent-foreground": {
      "value": "#4f46e5",
      "type": "color",
      "description": "accent-foreground"
    },
    "destructive": {
      "value": "linear-gradient(-75deg, #6ee7b7 0%, #6ee7b7 4%, #6366f1 4%, #6366f1 8%, #6ee7b7 8%, #6ee7b7 12%, #6366f1 12%, #6366f1 16%, #6ee7b7 16%, #6ee7b7 20%, #6366f1 20%, #6366f1 24%, #6ee7b7 24%, #6ee7b7 28%, #6366f1 28%, #6366f1 32%, #6ee7b7 32%, #6ee7b7 36%, #6366f1 36%, #6366f1 40%, #6ee7b7 40%, #6ee7b7 44%, #6366f1 44%, #6366f1 48%, #6ee7b7 48%, #6ee7b7 52%, #6366f1 52%, #6366f1 56%, #6ee7b7 56%, #6ee7b7 60%, #6366f1 60%, #6366f1 64%, #6ee7b7 64%, #6ee7b7 68%, #6366f1 68%, #6366f1 72%, #6ee7b7 72%, #6ee7b7 76%, #6366f1 76%, #6366f1 80%, #6ee7b7 80%, #6ee7b7 84%, #6366f1 84%, #6366f1 88%, #6ee7b7 88%, #6ee7b7 92%, #6366f1 92%,#6366f1 92%, #6ee7b7 96%, #6ee7b7 96%, #6366f1 100%)",
      "type": "color",
      "description": "destructive"
    },
    "destructive-foreground": {
      "value": "#4f46e5",
      "type": "color",
      "description": "destructive-foreground"
    },
    "border": {
      "value": "#4f46e5",
      "type": "color",
      "description": "border"
    },
    "input": {
      "value": "#4f46e5",
      "type": "color",
      "description": "input"
    },
    "ring": {
      "value": "#4f46e5",
      "type": "color",
      "description": "ring"
    },
    "boxshadow": {
      "value": "#4f46e5",
      "type": "color",
      "description": "boxshadow"
    },
    "candy_min45°✨": {
      "value": "linear-gradient(-45deg, #6ee7b7 0%, #6ee7b7 1%, #6366f1 1%, #6366f1 2%, #6ee7b7 2%, #6ee7b7 3%, #6366f1 3%, #6366f1 4%, #6ee7b7 4%, #6ee7b7 5%, #6366f1 5%, #6366f1 6%, #6ee7b7 6%, #6ee7b7 7%, #6366f1 7%, #6366f1 8%, #6ee7b7 8%, #6ee7b7 9%, #6366f1 9%, #6366f1 10%, #6ee7b7 10%, #6ee7b7 11%, #6366f1 11%, #6366f1 12%, #6ee7b7 12%, #6ee7b7 13%, #6366f1 13%, #6366f1 14%, #6ee7b7 14%, #6ee7b7 15%, #6366f1 15%, #6366f1 16%, #6ee7b7 16%, #6ee7b7 17%, #6366f1 17%, #6366f1 18%, #6ee7b7 18%, #6ee7b7 19%, #6366f1 19%, #6366f1 20%, #6ee7b7 20%, #6ee7b7 21%, #6366f1 21%, #6366f1 22%, #6ee7b7 22%, #6ee7b7 23%, #6366f1 23%, #6366f1 24%, #6ee7b7 24%, #6ee7b7 25%, #6366f1 25%, #6366f1 26%, #6ee7b7 26%, #6ee7b7 27%, #6366f1 27%, #6366f1 28%, #6ee7b7 28%, #6ee7b7 29%, #6366f1 29%, #6366f1 30%, #6ee7b7 30%, #6ee7b7 31%, #6366f1 31%, #6366f1 32%, #6ee7b7 32%, #6ee7b7 33%, #6366f1 33%, #6366f1 34%, #6ee7b7 34%, #6ee7b7 35%, #6366f1 35%, #6366f1 36%, #6ee7b7 36%, #6ee7b7 37%, #6366f1 37%, #6366f1 38%, #6ee7b7 38%, #6ee7b7 39%, #6366f1 39%, #6366f1 40%, #6ee7b7 40%, #6ee7b7 41%, #6366f1 41%, #6366f1 42%, #6ee7b7 42%, #6ee7b7 43%, #6366f1 43%, #6366f1 44%, #6ee7b7 44%, #6ee7b7 45%, #6366f1 45%, #6366f1 46%, #6ee7b7 46%, #6ee7b7 47%, #6366f1 47%, #6366f1 48%, #6ee7b7 48%, #6ee7b7 49%, #6366f1 49%, #6366f1 50%, #6ee7b7 50%, #6ee7b7 51%, #6366f1 51%, #6366f1 52%, #6ee7b7 52%, #6ee7b7 53%, #6366f1 53%, #6366f1 54%, #6ee7b7 54%, #6ee7b7 55%, #6366f1 55%, #6366f1 56%, #6ee7b7 56%, #6ee7b7 57%, #6366f1 57%, #6366f1 58%, #6ee7b7 58%, #6ee7b7 59%, #6366f1 59%, #6366f1 60%, #6ee7b7 60%, #6ee7b7 61%, #6366f1 61%, #6366f1 62%, #6ee7b7 62%, #6ee7b7 63%, #6366f1 63%, #6366f1 64%, #6ee7b7 64%, #6ee7b7 65%, #6366f1 65%, #6366f1 66%, #6ee7b7 66%, #6ee7b7 67%, #6366f1 67%, #6366f1 68%, #6ee7b7 68%, #6ee7b7 69%, #6366f1 69%, #6366f1 70%, #6ee7b7 70%, #6ee7b7 71%, #6366f1 71%, #6366f1 72%, #6ee7b7 72%, #6ee7b7 73%, #6366f1 73%, #6366f1 74%, #6ee7b7 74%, #6ee7b7 75%, #6366f1 75%, #6366f1 76%, #6ee7b7 76%, #6ee7b7 77%, #6366f1 77%, #6366f1 78%, #6ee7b7 78%, #6ee7b7 79%, #6366f1 79%, #6366f1 80%, #6ee7b7 80%, #6ee7b7 81%, #6366f1 81%, #6366f1 82%, #6ee7b7 82%, #6ee7b7 83%, #6366f1 83%, #6366f1 84%, #6ee7b7 84%, #6ee7b7 85%, #6366f1 85%, #6366f1 86%, #6ee7b7 86%, #6ee7b7 87%, #6366f1 87%, #6366f1 88%, #6ee7b7 88%, #6ee7b7 89%, #6366f1 89%, #6366f1 90%, #6ee7b7 90%, #6ee7b7 91%, #6366f1 91%, #6366f1 92%, #6ee7b7 92%, #6ee7b7 93%, #6366f1 93%, #6366f1 94%, #6ee7b7 94%, #6ee7b7 95%, #6366f1 95%, #6366f1 96%, #6ee7b7 96%, #6ee7b7 97%, #6366f1 97%, #6366f1 98%, #6ee7b7 98%, #6ee7b7 99%, #6366f1 99%, #6366f1 100%)",
      "type": "color",
      "description": "candy_min45°✨"
    },
    "candy_45°✨": {
      "value": "linear-gradient(45deg, #6ee7b7 0%, #6ee7b7 1%, #6366f1 1%, #6366f1 2%, #6ee7b7 2%, #6ee7b7 3%, #6366f1 3%, #6366f1 4%, #6ee7b7 4%, #6ee7b7 5%, #6366f1 5%, #6366f1 6%, #6ee7b7 6%, #6ee7b7 7%, #6366f1 7%, #6366f1 8%, #6ee7b7 8%, #6ee7b7 9%, #6366f1 9%, #6366f1 10%, #6ee7b7 10%, #6ee7b7 11%, #6366f1 11%, #6366f1 12%, #6ee7b7 12%, #6ee7b7 13%, #6366f1 13%, #6366f1 14%, #6ee7b7 14%, #6ee7b7 15%, #6366f1 15%, #6366f1 16%, #6ee7b7 16%, #6ee7b7 17%, #6366f1 17%, #6366f1 18%, #6ee7b7 18%, #6ee7b7 19%, #6366f1 19%, #6366f1 20%, #6ee7b7 20%, #6ee7b7 21%, #6366f1 21%, #6366f1 22%, #6ee7b7 22%, #6ee7b7 23%, #6366f1 23%, #6366f1 24%, #6ee7b7 24%, #6ee7b7 25%, #6366f1 25%, #6366f1 26%, #6ee7b7 26%, #6ee7b7 27%, #6366f1 27%, #6366f1 28%, #6ee7b7 28%, #6ee7b7 29%, #6366f1 29%, #6366f1 30%, #6ee7b7 30%, #6ee7b7 31%, #6366f1 31%, #6366f1 32%, #6ee7b7 32%, #6ee7b7 33%, #6366f1 33%, #6366f1 34%, #6ee7b7 34%, #6ee7b7 35%, #6366f1 35%, #6366f1 36%, #6ee7b7 36%, #6ee7b7 37%, #6366f1 37%, #6366f1 38%, #6ee7b7 38%, #6ee7b7 39%, #6366f1 39%, #6366f1 40%, #6ee7b7 40%, #6ee7b7 41%, #6366f1 41%, #6366f1 42%, #6ee7b7 42%, #6ee7b7 43%, #6366f1 43%, #6366f1 44%, #6ee7b7 44%, #6ee7b7 45%, #6366f1 45%, #6366f1 46%, #6ee7b7 46%, #6ee7b7 47%, #6366f1 47%, #6366f1 48%, #6ee7b7 48%, #6ee7b7 49%, #6366f1 49%, #6366f1 50%, #6ee7b7 50%, #6ee7b7 51%, #6366f1 51%, #6366f1 52%, #6ee7b7 52%, #6ee7b7 53%, #6366f1 53%, #6366f1 54%, #6ee7b7 54%, #6ee7b7 55%, #6366f1 55%, #6366f1 56%, #6ee7b7 56%, #6ee7b7 57%, #6366f1 57%, #6366f1 58%, #6ee7b7 58%, #6ee7b7 59%, #6366f1 59%, #6366f1 60%, #6ee7b7 60%, #6ee7b7 61%, #6366f1 61%, #6366f1 62%, #6ee7b7 62%, #6ee7b7 63%, #6366f1 63%, #6366f1 64%, #6ee7b7 64%, #6ee7b7 65%, #6366f1 65%, #6366f1 66%, #6ee7b7 66%, #6ee7b7 67%, #6366f1 67%, #6366f1 68%, #6ee7b7 68%, #6ee7b7 69%, #6366f1 69%, #6366f1 70%, #6ee7b7 70%, #6ee7b7 71%, #6366f1 71%, #6366f1 72%, #6ee7b7 72%, #6ee7b7 73%, #6366f1 73%, #6366f1 74%, #6ee7b7 74%, #6ee7b7 75%, #6366f1 75%, #6366f1 76%, #6ee7b7 76%, #6ee7b7 77%, #6366f1 77%, #6366f1 78%, #6ee7b7 78%, #6ee7b7 79%, #6366f1 79%, #6366f1 80%, #6ee7b7 80%, #6ee7b7 81%, #6366f1 81%, #6366f1 82%, #6ee7b7 82%, #6ee7b7 83%, #6366f1 83%, #6366f1 84%, #6ee7b7 84%, #6ee7b7 85%, #6366f1 85%, #6366f1 86%, #6ee7b7 86%, #6ee7b7 87%, #6366f1 87%, #6366f1 88%, #6ee7b7 88%, #6ee7b7 89%, #6366f1 89%, #6366f1 90%, #6ee7b7 90%, #6ee7b7 91%, #6366f1 91%, #6366f1 92%, #6ee7b7 92%, #6ee7b7 93%, #6366f1 93%, #6366f1 94%, #6ee7b7 94%, #6ee7b7 95%, #6366f1 95%, #6366f1 96%, #6ee7b7 96%, #6ee7b7 97%, #6366f1 97%, #6366f1 98%, #6ee7b7 98%, #6ee7b7 99%, #6366f1 99%, #6366f1 100%)",
      "type": "color",
      "description": "candy_45°✨"
    },
    "candy_min60°✨": {
      "value": "linear-gradient(-60deg, #6ee7b7 0%, #6ee7b7 1%, #6366f1 1%, #6366f1 2%, #6ee7b7 2%, #6ee7b7 3%, #6366f1 3%, #6366f1 4%, #6ee7b7 4%, #6ee7b7 5%, #6366f1 5%, #6366f1 6%, #6ee7b7 6%, #6ee7b7 7%, #6366f1 7%, #6366f1 8%, #6ee7b7 8%, #6ee7b7 9%, #6366f1 9%, #6366f1 10%, #6ee7b7 10%, #6ee7b7 11%, #6366f1 11%, #6366f1 12%, #6ee7b7 12%, #6ee7b7 13%, #6366f1 13%, #6366f1 14%, #6ee7b7 14%, #6ee7b7 15%, #6366f1 15%, #6366f1 16%, #6ee7b7 16%, #6ee7b7 17%, #6366f1 17%, #6366f1 18%, #6ee7b7 18%, #6ee7b7 19%, #6366f1 19%, #6366f1 20%, #6ee7b7 20%, #6ee7b7 21%, #6366f1 21%, #6366f1 22%, #6ee7b7 22%, #6ee7b7 23%, #6366f1 23%, #6366f1 24%, #6ee7b7 24%, #6ee7b7 25%, #6366f1 25%, #6366f1 26%, #6ee7b7 26%, #6ee7b7 27%, #6366f1 27%, #6366f1 28%, #6ee7b7 28%, #6ee7b7 29%, #6366f1 29%, #6366f1 30%, #6ee7b7 30%, #6ee7b7 31%, #6366f1 31%, #6366f1 32%, #6ee7b7 32%, #6ee7b7 33%, #6366f1 33%, #6366f1 34%, #6ee7b7 34%, #6ee7b7 35%, #6366f1 35%, #6366f1 36%, #6ee7b7 36%, #6ee7b7 37%, #6366f1 37%, #6366f1 38%, #6ee7b7 38%, #6ee7b7 39%, #6366f1 39%, #6366f1 40%, #6ee7b7 40%, #6ee7b7 41%, #6366f1 41%, #6366f1 42%, #6ee7b7 42%, #6ee7b7 43%, #6366f1 43%, #6366f1 44%, #6ee7b7 44%, #6ee7b7 45%, #6366f1 45%, #6366f1 46%, #6ee7b7 46%, #6ee7b7 47%, #6366f1 47%, #6366f1 48%, #6ee7b7 48%, #6ee7b7 49%, #6366f1 49%, #6366f1 50%, #6ee7b7 50%, #6ee7b7 51%, #6366f1 51%, #6366f1 52%, #6ee7b7 52%, #6ee7b7 53%, #6366f1 53%, #6366f1 54%, #6ee7b7 54%, #6ee7b7 55%, #6366f1 55%, #6366f1 56%, #6ee7b7 56%, #6ee7b7 57%, #6366f1 57%, #6366f1 58%, #6ee7b7 58%, #6ee7b7 59%, #6366f1 59%, #6366f1 60%, #6ee7b7 60%, #6ee7b7 61%, #6366f1 61%, #6366f1 62%, #6ee7b7 62%, #6ee7b7 63%, #6366f1 63%, #6366f1 64%, #6ee7b7 64%, #6ee7b7 65%, #6366f1 65%, #6366f1 66%, #6ee7b7 66%, #6ee7b7 67%, #6366f1 67%, #6366f1 68%, #6ee7b7 68%, #6ee7b7 69%, #6366f1 69%, #6366f1 70%, #6ee7b7 70%, #6ee7b7 71%, #6366f1 71%, #6366f1 72%, #6ee7b7 72%, #6ee7b7 73%, #6366f1 73%, #6366f1 74%, #6ee7b7 74%, #6ee7b7 75%, #6366f1 75%, #6366f1 76%, #6ee7b7 76%, #6ee7b7 77%, #6366f1 77%, #6366f1 78%, #6ee7b7 78%, #6ee7b7 79%, #6366f1 79%, #6366f1 80%, #6ee7b7 80%, #6ee7b7 81%, #6366f1 81%, #6366f1 82%, #6ee7b7 82%, #6ee7b7 83%, #6366f1 83%, #6366f1 84%, #6ee7b7 84%, #6ee7b7 85%, #6366f1 85%, #6366f1 86%, #6ee7b7 86%, #6ee7b7 87%, #6366f1 87%, #6366f1 88%, #6ee7b7 88%, #6ee7b7 89%, #6366f1 89%, #6366f1 90%, #6ee7b7 90%, #6ee7b7 91%, #6366f1 91%, #6366f1 92%, #6ee7b7 92%, #6ee7b7 93%, #6366f1 93%, #6366f1 94%, #6ee7b7 94%, #6ee7b7 95%, #6366f1 95%, #6366f1 96%, #6ee7b7 96%, #6ee7b7 97%, #6366f1 97%, #6366f1 98%, #6ee7b7 98%, #6ee7b7 99%, #6366f1 99%, #6366f1 100%)",
      "type": "color",
      "description": "candy_min60°✨"
    },
    "candy_60°✨": {
      "value": "linear-gradient(60deg, #6ee7b7 0%, #6ee7b7 1%, #6366f1 1%, #6366f1 2%, #6ee7b7 2%, #6ee7b7 3%, #6366f1 3%, #6366f1 4%, #6ee7b7 4%, #6ee7b7 5%, #6366f1 5%, #6366f1 6%, #6ee7b7 6%, #6ee7b7 7%, #6366f1 7%, #6366f1 8%, #6ee7b7 8%, #6ee7b7 9%, #6366f1 9%, #6366f1 10%, #6ee7b7 10%, #6ee7b7 11%, #6366f1 11%, #6366f1 12%, #6ee7b7 12%, #6ee7b7 13%, #6366f1 13%, #6366f1 14%, #6ee7b7 14%, #6ee7b7 15%, #6366f1 15%, #6366f1 16%, #6ee7b7 16%, #6ee7b7 17%, #6366f1 17%, #6366f1 18%, #6ee7b7 18%, #6ee7b7 19%, #6366f1 19%, #6366f1 20%, #6ee7b7 20%, #6ee7b7 21%, #6366f1 21%, #6366f1 22%, #6ee7b7 22%, #6ee7b7 23%, #6366f1 23%, #6366f1 24%, #6ee7b7 24%, #6ee7b7 25%, #6366f1 25%, #6366f1 26%, #6ee7b7 26%, #6ee7b7 27%, #6366f1 27%, #6366f1 28%, #6ee7b7 28%, #6ee7b7 29%, #6366f1 29%, #6366f1 30%, #6ee7b7 30%, #6ee7b7 31%, #6366f1 31%, #6366f1 32%, #6ee7b7 32%, #6ee7b7 33%, #6366f1 33%, #6366f1 34%, #6ee7b7 34%, #6ee7b7 35%, #6366f1 35%, #6366f1 36%, #6ee7b7 36%, #6ee7b7 37%, #6366f1 37%, #6366f1 38%, #6ee7b7 38%, #6ee7b7 39%, #6366f1 39%, #6366f1 40%, #6ee7b7 40%, #6ee7b7 41%, #6366f1 41%, #6366f1 42%, #6ee7b7 42%, #6ee7b7 43%, #6366f1 43%, #6366f1 44%, #6ee7b7 44%, #6ee7b7 45%, #6366f1 45%, #6366f1 46%, #6ee7b7 46%, #6ee7b7 47%, #6366f1 47%, #6366f1 48%, #6ee7b7 48%, #6ee7b7 49%, #6366f1 49%, #6366f1 50%, #6ee7b7 50%, #6ee7b7 51%, #6366f1 51%, #6366f1 52%, #6ee7b7 52%, #6ee7b7 53%, #6366f1 53%, #6366f1 54%, #6ee7b7 54%, #6ee7b7 55%, #6366f1 55%, #6366f1 56%, #6ee7b7 56%, #6ee7b7 57%, #6366f1 57%, #6366f1 58%, #6ee7b7 58%, #6ee7b7 59%, #6366f1 59%, #6366f1 60%, #6ee7b7 60%, #6ee7b7 61%, #6366f1 61%, #6366f1 62%, #6ee7b7 62%, #6ee7b7 63%, #6366f1 63%, #6366f1 64%, #6ee7b7 64%, #6ee7b7 65%, #6366f1 65%, #6366f1 66%, #6ee7b7 66%, #6ee7b7 67%, #6366f1 67%, #6366f1 68%, #6ee7b7 68%, #6ee7b7 69%, #6366f1 69%, #6366f1 70%, #6ee7b7 70%, #6ee7b7 71%, #6366f1 71%, #6366f1 72%, #6ee7b7 72%, #6ee7b7 73%, #6366f1 73%, #6366f1 74%, #6ee7b7 74%, #6ee7b7 75%, #6366f1 75%, #6366f1 76%, #6ee7b7 76%, #6ee7b7 77%, #6366f1 77%, #6366f1 78%, #6ee7b7 78%, #6ee7b7 79%, #6366f1 79%, #6366f1 80%, #6ee7b7 80%, #6ee7b7 81%, #6366f1 81%, #6366f1 82%, #6ee7b7 82%, #6ee7b7 83%, #6366f1 83%, #6366f1 84%, #6ee7b7 84%, #6ee7b7 85%, #6366f1 85%, #6366f1 86%, #6ee7b7 86%, #6ee7b7 87%, #6366f1 87%, #6366f1 88%, #6ee7b7 88%, #6ee7b7 89%, #6366f1 89%, #6366f1 90%, #6ee7b7 90%, #6ee7b7 91%, #6366f1 91%, #6366f1 92%, #6ee7b7 92%, #6ee7b7 93%, #6366f1 93%, #6366f1 94%, #6ee7b7 94%, #6ee7b7 95%, #6366f1 95%, #6366f1 96%, #6ee7b7 96%, #6ee7b7 97%, #6366f1 97%, #6366f1 98%, #6ee7b7 98%, #6ee7b7 99%, #6366f1 99%, #6366f1 100%)",
      "type": "color",
      "description": "candy_60°✨"
    },
    "candy_min75°✨": {
      "value": "linear-gradient(-75deg, #6ee7b7 0%, #6ee7b7 1%, #6366f1 1%, #6366f1 2%, #6ee7b7 2%, #6ee7b7 3%, #6366f1 3%, #6366f1 4%, #6ee7b7 4%, #6ee7b7 5%, #6366f1 5%, #6366f1 6%, #6ee7b7 6%, #6ee7b7 7%, #6366f1 7%, #6366f1 8%, #6ee7b7 8%, #6ee7b7 9%, #6366f1 9%, #6366f1 10%, #6ee7b7 10%, #6ee7b7 11%, #6366f1 11%, #6366f1 12%, #6ee7b7 12%, #6ee7b7 13%, #6366f1 13%, #6366f1 14%, #6ee7b7 14%, #6ee7b7 15%, #6366f1 15%, #6366f1 16%, #6ee7b7 16%, #6ee7b7 17%, #6366f1 17%, #6366f1 18%, #6ee7b7 18%, #6ee7b7 19%, #6366f1 19%, #6366f1 20%, #6ee7b7 20%, #6ee7b7 21%, #6366f1 21%, #6366f1 22%, #6ee7b7 22%, #6ee7b7 23%, #6366f1 23%, #6366f1 24%, #6ee7b7 24%, #6ee7b7 25%, #6366f1 25%, #6366f1 26%, #6ee7b7 26%, #6ee7b7 27%, #6366f1 27%, #6366f1 28%, #6ee7b7 28%, #6ee7b7 29%, #6366f1 29%, #6366f1 30%, #6ee7b7 30%, #6ee7b7 31%, #6366f1 31%, #6366f1 32%, #6ee7b7 32%, #6ee7b7 33%, #6366f1 33%, #6366f1 34%, #6ee7b7 34%, #6ee7b7 35%, #6366f1 35%, #6366f1 36%, #6ee7b7 36%, #6ee7b7 37%, #6366f1 37%, #6366f1 38%, #6ee7b7 38%, #6ee7b7 39%, #6366f1 39%, #6366f1 40%, #6ee7b7 40%, #6ee7b7 41%, #6366f1 41%, #6366f1 42%, #6ee7b7 42%, #6ee7b7 43%, #6366f1 43%, #6366f1 44%, #6ee7b7 44%, #6ee7b7 45%, #6366f1 45%, #6366f1 46%, #6ee7b7 46%, #6ee7b7 47%, #6366f1 47%, #6366f1 48%, #6ee7b7 48%, #6ee7b7 49%, #6366f1 49%, #6366f1 50%, #6ee7b7 50%, #6ee7b7 51%, #6366f1 51%, #6366f1 52%, #6ee7b7 52%, #6ee7b7 53%, #6366f1 53%, #6366f1 54%, #6ee7b7 54%, #6ee7b7 55%, #6366f1 55%, #6366f1 56%, #6ee7b7 56%, #6ee7b7 57%, #6366f1 57%, #6366f1 58%, #6ee7b7 58%, #6ee7b7 59%, #6366f1 59%, #6366f1 60%, #6ee7b7 60%, #6ee7b7 61%, #6366f1 61%, #6366f1 62%, #6ee7b7 62%, #6ee7b7 63%, #6366f1 63%, #6366f1 64%, #6ee7b7 64%, #6ee7b7 65%, #6366f1 65%, #6366f1 66%, #6ee7b7 66%, #6ee7b7 67%, #6366f1 67%, #6366f1 68%, #6ee7b7 68%, #6ee7b7 69%, #6366f1 69%, #6366f1 70%, #6ee7b7 70%, #6ee7b7 71%, #6366f1 71%, #6366f1 72%, #6ee7b7 72%, #6ee7b7 73%, #6366f1 73%, #6366f1 74%, #6ee7b7 74%, #6ee7b7 75%, #6366f1 75%, #6366f1 76%, #6ee7b7 76%, #6ee7b7 77%, #6366f1 77%, #6366f1 78%, #6ee7b7 78%, #6ee7b7 79%, #6366f1 79%, #6366f1 80%, #6ee7b7 80%, #6ee7b7 81%, #6366f1 81%, #6366f1 82%, #6ee7b7 82%, #6ee7b7 83%, #6366f1 83%, #6366f1 84%, #6ee7b7 84%, #6ee7b7 85%, #6366f1 85%, #6366f1 86%, #6ee7b7 86%, #6ee7b7 87%, #6366f1 87%, #6366f1 88%, #6ee7b7 88%, #6ee7b7 89%, #6366f1 89%, #6366f1 90%, #6ee7b7 90%, #6ee7b7 91%, #6366f1 91%, #6366f1 92%, #6ee7b7 92%, #6ee7b7 93%, #6366f1 93%, #6366f1 94%, #6ee7b7 94%, #6ee7b7 95%, #6366f1 95%, #6366f1 96%, #6ee7b7 96%, #6ee7b7 97%, #6366f1 97%, #6366f1 98%, #6ee7b7 98%, #6ee7b7 99%, #6366f1 99%, #6366f1 100%)",
      "type": "color",
      "description": "candy_min75°✨"
    },
    "candy_75°✨": {
      "value": "linear-gradient(75deg, #6ee7b7 0%, #6ee7b7 1%, #6366f1 1%, #6366f1 2%, #6ee7b7 2%, #6ee7b7 3%, #6366f1 3%, #6366f1 4%, #6ee7b7 4%, #6ee7b7 5%, #6366f1 5%, #6366f1 6%, #6ee7b7 6%, #6ee7b7 7%, #6366f1 7%, #6366f1 8%, #6ee7b7 8%, #6ee7b7 9%, #6366f1 9%, #6366f1 10%, #6ee7b7 10%, #6ee7b7 11%, #6366f1 11%, #6366f1 12%, #6ee7b7 12%, #6ee7b7 13%, #6366f1 13%, #6366f1 14%, #6ee7b7 14%, #6ee7b7 15%, #6366f1 15%, #6366f1 16%, #6ee7b7 16%, #6ee7b7 17%, #6366f1 17%, #6366f1 18%, #6ee7b7 18%, #6ee7b7 19%, #6366f1 19%, #6366f1 20%, #6ee7b7 20%, #6ee7b7 21%, #6366f1 21%, #6366f1 22%, #6ee7b7 22%, #6ee7b7 23%, #6366f1 23%, #6366f1 24%, #6ee7b7 24%, #6ee7b7 25%, #6366f1 25%, #6366f1 26%, #6ee7b7 26%, #6ee7b7 27%, #6366f1 27%, #6366f1 28%, #6ee7b7 28%, #6ee7b7 29%, #6366f1 29%, #6366f1 30%, #6ee7b7 30%, #6ee7b7 31%, #6366f1 31%, #6366f1 32%, #6ee7b7 32%, #6ee7b7 33%, #6366f1 33%, #6366f1 34%, #6ee7b7 34%, #6ee7b7 35%, #6366f1 35%, #6366f1 36%, #6ee7b7 36%, #6ee7b7 37%, #6366f1 37%, #6366f1 38%, #6ee7b7 38%, #6ee7b7 39%, #6366f1 39%, #6366f1 40%, #6ee7b7 40%, #6ee7b7 41%, #6366f1 41%, #6366f1 42%, #6ee7b7 42%, #6ee7b7 43%, #6366f1 43%, #6366f1 44%, #6ee7b7 44%, #6ee7b7 45%, #6366f1 45%, #6366f1 46%, #6ee7b7 46%, #6ee7b7 47%, #6366f1 47%, #6366f1 48%, #6ee7b7 48%, #6ee7b7 49%, #6366f1 49%, #6366f1 50%, #6ee7b7 50%, #6ee7b7 51%, #6366f1 51%, #6366f1 52%, #6ee7b7 52%, #6ee7b7 53%, #6366f1 53%, #6366f1 54%, #6ee7b7 54%, #6ee7b7 55%, #6366f1 55%, #6366f1 56%, #6ee7b7 56%, #6ee7b7 57%, #6366f1 57%, #6366f1 58%, #6ee7b7 58%, #6ee7b7 59%, #6366f1 59%, #6366f1 60%, #6ee7b7 60%, #6ee7b7 61%, #6366f1 61%, #6366f1 62%, #6ee7b7 62%, #6ee7b7 63%, #6366f1 63%, #6366f1 64%, #6ee7b7 64%, #6ee7b7 65%, #6366f1 65%, #6366f1 66%, #6ee7b7 66%, #6ee7b7 67%, #6366f1 67%, #6366f1 68%, #6ee7b7 68%, #6ee7b7 69%, #6366f1 69%, #6366f1 70%, #6ee7b7 70%, #6ee7b7 71%, #6366f1 71%, #6366f1 72%, #6ee7b7 72%, #6ee7b7 73%, #6366f1 73%, #6366f1 74%, #6ee7b7 74%, #6ee7b7 75%, #6366f1 75%, #6366f1 76%, #6ee7b7 76%, #6ee7b7 77%, #6366f1 77%, #6366f1 78%, #6ee7b7 78%, #6ee7b7 79%, #6366f1 79%, #6366f1 80%, #6ee7b7 80%, #6ee7b7 81%, #6366f1 81%, #6366f1 82%, #6ee7b7 82%, #6ee7b7 83%, #6366f1 83%, #6366f1 84%, #6ee7b7 84%, #6ee7b7 85%, #6366f1 85%, #6366f1 86%, #6ee7b7 86%, #6ee7b7 87%, #6366f1 87%, #6366f1 88%, #6ee7b7 88%, #6ee7b7 89%, #6366f1 89%, #6366f1 90%, #6ee7b7 90%, #6ee7b7 91%, #6366f1 91%, #6366f1 92%, #6ee7b7 92%, #6ee7b7 93%, #6366f1 93%, #6366f1 94%, #6ee7b7 94%, #6ee7b7 95%, #6366f1 95%, #6366f1 96%, #6ee7b7 96%, #6ee7b7 97%, #6366f1 97%, #6366f1 98%, #6ee7b7 98%, #6ee7b7 99%, #6366f1 99%, #6366f1 100%)",
      "type": "color",
      "description": "candy_75°✨"
    },
    "candy_0°✨": {
      "value": "linear-gradient(0deg, #6ee7b7 0%, #6ee7b7 1%, #6366f1 1%, #6366f1 2%, #6ee7b7 2%, #6ee7b7 3%, #6366f1 3%, #6366f1 4%, #6ee7b7 4%, #6ee7b7 5%, #6366f1 5%, #6366f1 6%, #6ee7b7 6%, #6ee7b7 7%, #6366f1 7%, #6366f1 8%, #6ee7b7 8%, #6ee7b7 9%, #6366f1 9%, #6366f1 10%, #6ee7b7 10%, #6ee7b7 11%, #6366f1 11%, #6366f1 12%, #6ee7b7 12%, #6ee7b7 13%, #6366f1 13%, #6366f1 14%, #6ee7b7 14%, #6ee7b7 15%, #6366f1 15%, #6366f1 16%, #6ee7b7 16%, #6ee7b7 17%, #6366f1 17%, #6366f1 18%, #6ee7b7 18%, #6ee7b7 19%, #6366f1 19%, #6366f1 20%, #6ee7b7 20%, #6ee7b7 21%, #6366f1 21%, #6366f1 22%, #6ee7b7 22%, #6ee7b7 23%, #6366f1 23%, #6366f1 24%, #6ee7b7 24%, #6ee7b7 25%, #6366f1 25%, #6366f1 26%, #6ee7b7 26%, #6ee7b7 27%, #6366f1 27%, #6366f1 28%, #6ee7b7 28%, #6ee7b7 29%, #6366f1 29%, #6366f1 30%, #6ee7b7 30%, #6ee7b7 31%, #6366f1 31%, #6366f1 32%, #6ee7b7 32%, #6ee7b7 33%, #6366f1 33%, #6366f1 34%, #6ee7b7 34%, #6ee7b7 35%, #6366f1 35%, #6366f1 36%, #6ee7b7 36%, #6ee7b7 37%, #6366f1 37%, #6366f1 38%, #6ee7b7 38%, #6ee7b7 39%, #6366f1 39%, #6366f1 40%, #6ee7b7 40%, #6ee7b7 41%, #6366f1 41%, #6366f1 42%, #6ee7b7 42%, #6ee7b7 43%, #6366f1 43%, #6366f1 44%, #6ee7b7 44%, #6ee7b7 45%, #6366f1 45%, #6366f1 46%, #6ee7b7 46%, #6ee7b7 47%, #6366f1 47%, #6366f1 48%, #6ee7b7 48%, #6ee7b7 49%, #6366f1 49%, #6366f1 50%, #6ee7b7 50%, #6ee7b7 51%, #6366f1 51%, #6366f1 52%, #6ee7b7 52%, #6ee7b7 53%, #6366f1 53%, #6366f1 54%, #6ee7b7 54%, #6ee7b7 55%, #6366f1 55%, #6366f1 56%, #6ee7b7 56%, #6ee7b7 57%, #6366f1 57%, #6366f1 58%, #6ee7b7 58%, #6ee7b7 59%, #6366f1 59%, #6366f1 60%, #6ee7b7 60%, #6ee7b7 61%, #6366f1 61%, #6366f1 62%, #6ee7b7 62%, #6ee7b7 63%, #6366f1 63%, #6366f1 64%, #6ee7b7 64%, #6ee7b7 65%, #6366f1 65%, #6366f1 66%, #6ee7b7 66%, #6ee7b7 67%, #6366f1 67%, #6366f1 68%, #6ee7b7 68%, #6ee7b7 69%, #6366f1 69%, #6366f1 70%, #6ee7b7 70%, #6ee7b7 71%, #6366f1 71%, #6366f1 72%, #6ee7b7 72%, #6ee7b7 73%, #6366f1 73%, #6366f1 74%, #6ee7b7 74%, #6ee7b7 75%, #6366f1 75%, #6366f1 76%, #6ee7b7 76%, #6ee7b7 77%, #6366f1 77%, #6366f1 78%, #6ee7b7 78%, #6ee7b7 79%, #6366f1 79%, #6366f1 80%, #6ee7b7 80%, #6ee7b7 81%, #6366f1 81%, #6366f1 82%, #6ee7b7 82%, #6ee7b7 83%, #6366f1 83%, #6366f1 84%, #6ee7b7 84%, #6ee7b7 85%, #6366f1 85%, #6366f1 86%, #6ee7b7 86%, #6ee7b7 87%, #6366f1 87%, #6366f1 88%, #6ee7b7 88%, #6ee7b7 89%, #6366f1 89%, #6366f1 90%, #6ee7b7 90%, #6ee7b7 91%, #6366f1 91%, #6366f1 92%, #6ee7b7 92%, #6ee7b7 93%, #6366f1 93%, #6366f1 94%, #6ee7b7 94%, #6ee7b7 95%, #6366f1 95%, #6366f1 96%, #6ee7b7 96%, #6ee7b7 97%, #6366f1 97%, #6366f1 98%, #6ee7b7 98%, #6ee7b7 99%, #6366f1 99%, #6366f1 100%)",
      "type": "color",
      "description": "candy_0°✨"
    },
    "candy_90°✨": {
      "value": "linear-gradient(90deg, #6ee7b7 0%, #6ee7b7 1%, #6366f1 1%, #6366f1 2%, #6ee7b7 2%, #6ee7b7 3%, #6366f1 3%, #6366f1 4%, #6ee7b7 4%, #6ee7b7 5%, #6366f1 5%, #6366f1 6%, #6ee7b7 6%, #6ee7b7 7%, #6366f1 7%, #6366f1 8%, #6ee7b7 8%, #6ee7b7 9%, #6366f1 9%, #6366f1 10%, #6ee7b7 10%, #6ee7b7 11%, #6366f1 11%, #6366f1 12%, #6ee7b7 12%, #6ee7b7 13%, #6366f1 13%, #6366f1 14%, #6ee7b7 14%, #6ee7b7 15%, #6366f1 15%, #6366f1 16%, #6ee7b7 16%, #6ee7b7 17%, #6366f1 17%, #6366f1 18%, #6ee7b7 18%, #6ee7b7 19%, #6366f1 19%, #6366f1 20%, #6ee7b7 20%, #6ee7b7 21%, #6366f1 21%, #6366f1 22%, #6ee7b7 22%, #6ee7b7 23%, #6366f1 23%, #6366f1 24%, #6ee7b7 24%, #6ee7b7 25%, #6366f1 25%, #6366f1 26%, #6ee7b7 26%, #6ee7b7 27%, #6366f1 27%, #6366f1 28%, #6ee7b7 28%, #6ee7b7 29%, #6366f1 29%, #6366f1 30%, #6ee7b7 30%, #6ee7b7 31%, #6366f1 31%, #6366f1 32%, #6ee7b7 32%, #6ee7b7 33%, #6366f1 33%, #6366f1 34%, #6ee7b7 34%, #6ee7b7 35%, #6366f1 35%, #6366f1 36%, #6ee7b7 36%, #6ee7b7 37%, #6366f1 37%, #6366f1 38%, #6ee7b7 38%, #6ee7b7 39%, #6366f1 39%, #6366f1 40%, #6ee7b7 40%, #6ee7b7 41%, #6366f1 41%, #6366f1 42%, #6ee7b7 42%, #6ee7b7 43%, #6366f1 43%, #6366f1 44%, #6ee7b7 44%, #6ee7b7 45%, #6366f1 45%, #6366f1 46%, #6ee7b7 46%, #6ee7b7 47%, #6366f1 47%, #6366f1 48%, #6ee7b7 48%, #6ee7b7 49%, #6366f1 49%, #6366f1 50%, #6ee7b7 50%, #6ee7b7 51%, #6366f1 51%, #6366f1 52%, #6ee7b7 52%, #6ee7b7 53%, #6366f1 53%, #6366f1 54%, #6ee7b7 54%, #6ee7b7 55%, #6366f1 55%, #6366f1 56%, #6ee7b7 56%, #6ee7b7 57%, #6366f1 57%, #6366f1 58%, #6ee7b7 58%, #6ee7b7 59%, #6366f1 59%, #6366f1 60%, #6ee7b7 60%, #6ee7b7 61%, #6366f1 61%, #6366f1 62%, #6ee7b7 62%, #6ee7b7 63%, #6366f1 63%, #6366f1 64%, #6ee7b7 64%, #6ee7b7 65%, #6366f1 65%, #6366f1 66%, #6ee7b7 66%, #6ee7b7 67%, #6366f1 67%, #6366f1 68%, #6ee7b7 68%, #6ee7b7 69%, #6366f1 69%, #6366f1 70%, #6ee7b7 70%, #6ee7b7 71%, #6366f1 71%, #6366f1 72%, #6ee7b7 72%, #6ee7b7 73%, #6366f1 73%, #6366f1 74%, #6ee7b7 74%, #6ee7b7 75%, #6366f1 75%, #6366f1 76%, #6ee7b7 76%, #6ee7b7 77%, #6366f1 77%, #6366f1 78%, #6ee7b7 78%, #6ee7b7 79%, #6366f1 79%, #6366f1 80%, #6ee7b7 80%, #6ee7b7 81%, #6366f1 81%, #6366f1 82%, #6ee7b7 82%, #6ee7b7 83%, #6366f1 83%, #6366f1 84%, #6ee7b7 84%, #6ee7b7 85%, #6366f1 85%, #6366f1 86%, #6ee7b7 86%, #6ee7b7 87%, #6366f1 87%, #6366f1 88%, #6ee7b7 88%, #6ee7b7 89%, #6366f1 89%, #6366f1 90%, #6ee7b7 90%, #6ee7b7 91%, #6366f1 91%, #6366f1 92%, #6ee7b7 92%, #6ee7b7 93%, #6366f1 93%, #6366f1 94%, #6ee7b7 94%, #6ee7b7 95%, #6366f1 95%, #6366f1 96%, #6ee7b7 96%, #6ee7b7 97%, #6366f1 97%, #6366f1 98%, #6ee7b7 98%, #6ee7b7 99%, #6366f1 99%, #6366f1 100%)",
      "type": "color",
      "description": "candy_90°✨"
    },
    "stripe_min45°✨": {
      "value": "linear-gradient(-45deg, #6ee7b7 0%, #6ee7b7 1%, #6366f1 1%, #6366f1 5%, #6ee7b7 5%, #6ee7b7 6%, #6366f1 6%, #6366f1 10%, #6ee7b7 10%, #6ee7b7 11%, #6366f1 11%, #6366f1 15%, #6ee7b7 15%, #6ee7b7 16%, #6366f1 16%, #6366f1 20%, #6ee7b7 20%, #6ee7b7 21%, #6366f1 21%, #6366f1 25%, #6ee7b7 25%, #6ee7b7 26%, #6366f1 26%, #6366f1 30%, #6ee7b7 30%, #6ee7b7 31%, #6366f1 31%, #6366f1 35%, #6ee7b7 35%, #6ee7b7 36%, #6366f1 36%, #6366f1 40%, #6ee7b7 40%, #6ee7b7 41%, #6366f1 41%, #6366f1 45%, #6ee7b7 45%, #6ee7b7 46%, #6366f1 46%, #6366f1 50%, #6ee7b7 50%, #6ee7b7 51%, #6366f1 51%, #6366f1 55%, #6ee7b7 55%, #6ee7b7 56%, #6366f1 56%, #6366f1 60%, #6ee7b7 60%, #6ee7b7 61%, #6366f1 61%, #6366f1 65%, #6ee7b7 65%, #6ee7b7 66%, #6366f1 66%, #6366f1 70%, #6ee7b7 70%, #6ee7b7 71%, #6366f1 71%, #6366f1 75%, #6ee7b7 75%, #6ee7b7 76%, #6366f1 76%, #6366f1 80%, #6ee7b7 80%, #6ee7b7 81%, #6366f1 81%, #6366f1 85%, #6ee7b7 85%, #6ee7b7 86%, #6366f1 86%, #6366f1 90%, #6ee7b7 90%, #6ee7b7 91%, #6366f1 91%, #6366f1 95%, #6ee7b7 95%, #6ee7b7 96%, #6366f1 96%, #6366f1 100%)",
      "type": "color",
      "description": "stripe_min45°✨"
    },
    "stripe_45°✨": {
      "value": "linear-gradient(45deg, #6ee7b7 0%, #6ee7b7 1%, #6366f1 1%, #6366f1 5%, #6ee7b7 5%, #6ee7b7 6%, #6366f1 6%, #6366f1 10%, #6ee7b7 10%, #6ee7b7 11%, #6366f1 11%, #6366f1 15%, #6ee7b7 15%, #6ee7b7 16%, #6366f1 16%, #6366f1 20%, #6ee7b7 20%, #6ee7b7 21%, #6366f1 21%, #6366f1 25%, #6ee7b7 25%, #6ee7b7 26%, #6366f1 26%, #6366f1 30%, #6ee7b7 30%, #6ee7b7 31%, #6366f1 31%, #6366f1 35%, #6ee7b7 35%, #6ee7b7 36%, #6366f1 36%, #6366f1 40%, #6ee7b7 40%, #6ee7b7 41%, #6366f1 41%, #6366f1 45%, #6ee7b7 45%, #6ee7b7 46%, #6366f1 46%, #6366f1 50%, #6ee7b7 50%, #6ee7b7 51%, #6366f1 51%, #6366f1 55%, #6ee7b7 55%, #6ee7b7 56%, #6366f1 56%, #6366f1 60%, #6ee7b7 60%, #6ee7b7 61%, #6366f1 61%, #6366f1 65%, #6ee7b7 65%, #6ee7b7 66%, #6366f1 66%, #6366f1 70%, #6ee7b7 70%, #6ee7b7 71%, #6366f1 71%, #6366f1 75%, #6ee7b7 75%, #6ee7b7 76%, #6366f1 76%, #6366f1 80%, #6ee7b7 80%, #6ee7b7 81%, #6366f1 81%, #6366f1 85%, #6ee7b7 85%, #6ee7b7 86%, #6366f1 86%, #6366f1 90%, #6ee7b7 90%, #6ee7b7 91%, #6366f1 91%, #6366f1 95%, #6ee7b7 95%, #6ee7b7 96%, #6366f1 96%, #6366f1 100%)",
      "type": "color",
      "description": "stripe_45°✨"
    },
    "stripe_min60°✨": {
      "value": "linear-gradient(-60deg, #6ee7b7 0%, #6ee7b7 1%, #6366f1 1%, #6366f1 5%, #6ee7b7 5%, #6ee7b7 6%, #6366f1 6%, #6366f1 10%, #6ee7b7 10%, #6ee7b7 11%, #6366f1 11%, #6366f1 15%, #6ee7b7 15%, #6ee7b7 16%, #6366f1 16%, #6366f1 20%, #6ee7b7 20%, #6ee7b7 21%, #6366f1 21%, #6366f1 25%, #6ee7b7 25%, #6ee7b7 26%, #6366f1 26%, #6366f1 30%, #6ee7b7 30%, #6ee7b7 31%, #6366f1 31%, #6366f1 35%, #6ee7b7 35%, #6ee7b7 36%, #6366f1 36%, #6366f1 40%, #6ee7b7 40%, #6ee7b7 41%, #6366f1 41%, #6366f1 45%, #6ee7b7 45%, #6ee7b7 46%, #6366f1 46%, #6366f1 50%, #6ee7b7 50%, #6ee7b7 51%, #6366f1 51%, #6366f1 55%, #6ee7b7 55%, #6ee7b7 56%, #6366f1 56%, #6366f1 60%, #6ee7b7 60%, #6ee7b7 61%, #6366f1 61%, #6366f1 65%, #6ee7b7 65%, #6ee7b7 66%, #6366f1 66%, #6366f1 70%, #6ee7b7 70%, #6ee7b7 71%, #6366f1 71%, #6366f1 75%, #6ee7b7 75%, #6ee7b7 76%, #6366f1 76%, #6366f1 80%, #6ee7b7 80%, #6ee7b7 81%, #6366f1 81%, #6366f1 85%, #6ee7b7 85%, #6ee7b7 86%, #6366f1 86%, #6366f1 90%, #6ee7b7 90%, #6ee7b7 91%, #6366f1 91%, #6366f1 95%, #6ee7b7 95%, #6ee7b7 96%, #6366f1 96%, #6366f1 100%)",
      "type": "color",
      "description": "stripe_min60°✨"
    },
    "stripe_60°✨": {
      "value": "linear-gradient(60deg, #6ee7b7 0%, #6ee7b7 1%, #6366f1 1%, #6366f1 5%, #6ee7b7 5%, #6ee7b7 6%, #6366f1 6%, #6366f1 10%, #6ee7b7 10%, #6ee7b7 11%, #6366f1 11%, #6366f1 15%, #6ee7b7 15%, #6ee7b7 16%, #6366f1 16%, #6366f1 20%, #6ee7b7 20%, #6ee7b7 21%, #6366f1 21%, #6366f1 25%, #6ee7b7 25%, #6ee7b7 26%, #6366f1 26%, #6366f1 30%, #6ee7b7 30%, #6ee7b7 31%, #6366f1 31%, #6366f1 35%, #6ee7b7 35%, #6ee7b7 36%, #6366f1 36%, #6366f1 40%, #6ee7b7 40%, #6ee7b7 41%, #6366f1 41%, #6366f1 45%, #6ee7b7 45%, #6ee7b7 46%, #6366f1 46%, #6366f1 50%, #6ee7b7 50%, #6ee7b7 51%, #6366f1 51%, #6366f1 55%, #6ee7b7 55%, #6ee7b7 56%, #6366f1 56%, #6366f1 60%, #6ee7b7 60%, #6ee7b7 61%, #6366f1 61%, #6366f1 65%, #6ee7b7 65%, #6ee7b7 66%, #6366f1 66%, #6366f1 70%, #6ee7b7 70%, #6ee7b7 71%, #6366f1 71%, #6366f1 75%, #6ee7b7 75%, #6ee7b7 76%, #6366f1 76%, #6366f1 80%, #6ee7b7 80%, #6ee7b7 81%, #6366f1 81%, #6366f1 85%, #6ee7b7 85%, #6ee7b7 86%, #6366f1 86%, #6366f1 90%, #6ee7b7 90%, #6ee7b7 91%, #6366f1 91%, #6366f1 95%, #6ee7b7 95%, #6ee7b7 96%, #6366f1 96%, #6366f1 100%)",
      "type": "color",
      "description": "stripe_60°✨"
    },
    "stripe_min75°✨": {
      "value": "linear-gradient(-75deg, #6ee7b7 0%, #6ee7b7 1%, #6366f1 1%, #6366f1 5%, #6ee7b7 5%, #6ee7b7 6%, #6366f1 6%, #6366f1 10%, #6ee7b7 10%, #6ee7b7 11%, #6366f1 11%, #6366f1 15%, #6ee7b7 15%, #6ee7b7 16%, #6366f1 16%, #6366f1 20%, #6ee7b7 20%, #6ee7b7 21%, #6366f1 21%, #6366f1 25%, #6ee7b7 25%, #6ee7b7 26%, #6366f1 26%, #6366f1 30%, #6ee7b7 30%, #6ee7b7 31%, #6366f1 31%, #6366f1 35%, #6ee7b7 35%, #6ee7b7 36%, #6366f1 36%, #6366f1 40%, #6ee7b7 40%, #6ee7b7 41%, #6366f1 41%, #6366f1 45%, #6ee7b7 45%, #6ee7b7 46%, #6366f1 46%, #6366f1 50%, #6ee7b7 50%, #6ee7b7 51%, #6366f1 51%, #6366f1 55%, #6ee7b7 55%, #6ee7b7 56%, #6366f1 56%, #6366f1 60%, #6ee7b7 60%, #6ee7b7 61%, #6366f1 61%, #6366f1 65%, #6ee7b7 65%, #6ee7b7 66%, #6366f1 66%, #6366f1 70%, #6ee7b7 70%, #6ee7b7 71%, #6366f1 71%, #6366f1 75%, #6ee7b7 75%, #6ee7b7 76%, #6366f1 76%, #6366f1 80%, #6ee7b7 80%, #6ee7b7 81%, #6366f1 81%, #6366f1 85%, #6ee7b7 85%, #6ee7b7 86%, #6366f1 86%, #6366f1 90%, #6ee7b7 90%, #6ee7b7 91%, #6366f1 91%, #6366f1 95%, #6ee7b7 95%, #6ee7b7 96%, #6366f1 96%, #6366f1 100%)",
      "type": "color",
      "description": "stripe_min75°✨"
    },
    "stripe_75°✨": {
      "value": "linear-gradient(75deg, #6ee7b7 0%, #6ee7b7 1%, #6366f1 1%, #6366f1 5%, #6ee7b7 5%, #6ee7b7 6%, #6366f1 6%, #6366f1 10%, #6ee7b7 10%, #6ee7b7 11%, #6366f1 11%, #6366f1 15%, #6ee7b7 15%, #6ee7b7 16%, #6366f1 16%, #6366f1 20%, #6ee7b7 20%, #6ee7b7 21%, #6366f1 21%, #6366f1 25%, #6ee7b7 25%, #6ee7b7 26%, #6366f1 26%, #6366f1 30%, #6ee7b7 30%, #6ee7b7 31%, #6366f1 31%, #6366f1 35%, #6ee7b7 35%, #6ee7b7 36%, #6366f1 36%, #6366f1 40%, #6ee7b7 40%, #6ee7b7 41%, #6366f1 41%, #6366f1 45%, #6ee7b7 45%, #6ee7b7 46%, #6366f1 46%, #6366f1 50%, #6ee7b7 50%, #6ee7b7 51%, #6366f1 51%, #6366f1 55%, #6ee7b7 55%, #6ee7b7 56%, #6366f1 56%, #6366f1 60%, #6ee7b7 60%, #6ee7b7 61%, #6366f1 61%, #6366f1 65%, #6ee7b7 65%, #6ee7b7 66%, #6366f1 66%, #6366f1 70%, #6ee7b7 70%, #6ee7b7 71%, #6366f1 71%, #6366f1 75%, #6ee7b7 75%, #6ee7b7 76%, #6366f1 76%, #6366f1 80%, #6ee7b7 80%, #6ee7b7 81%, #6366f1 81%, #6366f1 85%, #6ee7b7 85%, #6ee7b7 86%, #6366f1 86%, #6366f1 90%, #6ee7b7 90%, #6ee7b7 91%, #6366f1 91%, #6366f1 95%, #6ee7b7 95%, #6ee7b7 96%, #6366f1 96%, #6366f1 100%)",
      "type": "color",
      "description": "stripe_75°✨"
    },
    "stripe_0°✨": {
      "value": "linear-gradient(0deg, #6ee7b7 0%, #6ee7b7 1%, #6366f1 1%, #6366f1 5%, #6ee7b7 5%, #6ee7b7 6%, #6366f1 6%, #6366f1 10%, #6ee7b7 10%, #6ee7b7 11%, #6366f1 11%, #6366f1 15%, #6ee7b7 15%, #6ee7b7 16%, #6366f1 16%, #6366f1 20%, #6ee7b7 20%, #6ee7b7 21%, #6366f1 21%, #6366f1 25%, #6ee7b7 25%, #6ee7b7 26%, #6366f1 26%, #6366f1 30%, #6ee7b7 30%, #6ee7b7 31%, #6366f1 31%, #6366f1 35%, #6ee7b7 35%, #6ee7b7 36%, #6366f1 36%, #6366f1 40%, #6ee7b7 40%, #6ee7b7 41%, #6366f1 41%, #6366f1 45%, #6ee7b7 45%, #6ee7b7 46%, #6366f1 46%, #6366f1 50%, #6ee7b7 50%, #6ee7b7 51%, #6366f1 51%, #6366f1 55%, #6ee7b7 55%, #6ee7b7 56%, #6366f1 56%, #6366f1 60%, #6ee7b7 60%, #6ee7b7 61%, #6366f1 61%, #6366f1 65%, #6ee7b7 65%, #6ee7b7 66%, #6366f1 66%, #6366f1 70%, #6ee7b7 70%, #6ee7b7 71%, #6366f1 71%, #6366f1 75%, #6ee7b7 75%, #6ee7b7 76%, #6366f1 76%, #6366f1 80%, #6ee7b7 80%, #6ee7b7 81%, #6366f1 81%, #6366f1 85%, #6ee7b7 85%, #6ee7b7 86%, #6366f1 86%, #6366f1 90%, #6ee7b7 90%, #6ee7b7 91%, #6366f1 91%, #6366f1 95%, #6ee7b7 95%, #6ee7b7 96%, #6366f1 96%, #6366f1 100%)",
      "type": "color",
      "description": "stripe_0°✨"
    },
    "stripe_90°✨": {
      "value": "linear-gradient(-90deg, #6ee7b7 0%, #6ee7b7 1%, #6366f1 1%, #6366f1 5%, #6ee7b7 5%, #6ee7b7 6%, #6366f1 6%, #6366f1 10%, #6ee7b7 10%, #6ee7b7 11%, #6366f1 11%, #6366f1 15%, #6ee7b7 15%, #6ee7b7 16%, #6366f1 16%, #6366f1 20%, #6ee7b7 20%, #6ee7b7 21%, #6366f1 21%, #6366f1 25%, #6ee7b7 25%, #6ee7b7 26%, #6366f1 26%, #6366f1 30%, #6ee7b7 30%, #6ee7b7 31%, #6366f1 31%, #6366f1 35%, #6ee7b7 35%, #6ee7b7 36%, #6366f1 36%, #6366f1 40%, #6ee7b7 40%, #6ee7b7 41%, #6366f1 41%, #6366f1 45%, #6ee7b7 45%, #6ee7b7 46%, #6366f1 46%, #6366f1 50%, #6ee7b7 50%, #6ee7b7 51%, #6366f1 51%, #6366f1 55%, #6ee7b7 55%, #6ee7b7 56%, #6366f1 56%, #6366f1 60%, #6ee7b7 60%, #6ee7b7 61%, #6366f1 61%, #6366f1 65%, #6ee7b7 65%, #6ee7b7 66%, #6366f1 66%, #6366f1 70%, #6ee7b7 70%, #6ee7b7 71%, #6366f1 71%, #6366f1 75%, #6ee7b7 75%, #6ee7b7 76%, #6366f1 76%, #6366f1 80%, #6ee7b7 80%, #6ee7b7 81%, #6366f1 81%, #6366f1 85%, #6ee7b7 85%, #6ee7b7 86%, #6366f1 86%, #6366f1 90%, #6ee7b7 90%, #6ee7b7 91%, #6366f1 91%, #6366f1 95%, #6ee7b7 95%, #6ee7b7 96%, #6366f1 96%, #6366f1 100%)",
      "type": "color",
      "description": "stripe_90°✨"
    }
  }
}