{
  "generationux-styles": {
    "background": {
      "value": "#f0abfc",
      "type": "color",
      "description": "background"
    },
    "foreground": {
      "value": "#818cf8",
      "type": "color",
      "description": "foreground"
    },
    "card": {
      "value": "#f0abfc",
      "type": "color",
      "description": "card"
    },
    "card-foreground": {
      "value": "#6366f1",
      "type": "color",
      "description": "card-foreground"
    },
    "popover": {
      "value": "#f0abfc",
      "type": "color",
      "description": "popover"
    },
    "popover-foreground": {
      "value": "#6366f1",
      "type": "color",
      "description": "popover-foreground"
    },
    "primary": {
      "value": "#818cf8",
      "type": "color",
      "description": "primary"
    },
    "primary-foreground": {
      "value": "#f0abfc",
      "type": "color",
      "description": "primary-foreground"
    },
    "secondary": {
      "value": "#e879f9",
      "type": "color",
      "description": "secondary"
    },
    "secondary-foreground": {
      "value": "#6366f1",
      "type": "color",
      "description": "secondary-foreground"
    },
    "muted": {
      "value": "#e879f9",
      "type": "color",
      "description": "muted"
    },
    "muted-foreground": {
      "value": "#6366f1",
      "type": "color",
      "description": "muted-foreground"
    },
    "accent": {
      "value": "#e879f9",
      "type": "color",
      "description": "accent"
    },
    "accent-foreground": {
      "value": "#6366f1",
      "type": "color",
      "description": "accent-foreground"
    },
    "destructive": {
      "value": "linear-gradient(-75deg, #f0abfc 0%, #f0abfc 4%, #818cf8 4%, #818cf8 8%, #f0abfc 8%, #f0abfc 12%, #818cf8 12%, #818cf8 16%, #f0abfc 16%, #f0abfc 20%, #818cf8 20%, #818cf8 24%, #f0abfc 24%, #f0abfc 28%, #818cf8 28%, #818cf8 32%, #f0abfc 32%, #f0abfc 36%, #818cf8 36%, #818cf8 40%, #f0abfc 40%, #f0abfc 44%, #818cf8 44%, #818cf8 48%, #f0abfc 48%, #f0abfc 52%, #818cf8 52%, #818cf8 56%, #f0abfc 56%, #f0abfc 60%, #818cf8 60%, #818cf8 64%, #f0abfc 64%, #f0abfc 68%, #818cf8 68%, #818cf8 72%, #f0abfc 72%, #f0abfc 76%, #818cf8 76%, #818cf8 80%, #f0abfc 80%, #f0abfc 84%, #818cf8 84%, #818cf8 88%, #f0abfc 88%, #f0abfc 92%, #818cf8 92%,#818cf8 92%, #f0abfc 96%, #f0abfc 96%, #818cf8 100%)",
      "type": "color",
      "description": "destructive"
    },
    "destructive-foreground": {
      "value": "#6366f1",
      "type": "color",
      "description": "destructive-foreground"
    },
    "border": {
      "value": "#6366f1",
      "type": "color",
      "description": "border"
    },
    "input": {
      "value": "#6366f1",
      "type": "color",
      "description": "input"
    },
    "ring": {
      "value": "#6366f1",
      "type": "color",
      "description": "ring"
    },
    "boxshadow": {
      "value": "#6366f1",
      "type": "color",
      "description": "boxshadow"
    },
    "candy_min45°": {
      "value": "linear-gradient(-45deg, #f0abfc 0%, #f0abfc 1%, #818cf8 1%, #818cf8 2%, #f0abfc 2%, #f0abfc 3%, #818cf8 3%, #818cf8 4%, #f0abfc 4%, #f0abfc 5%, #818cf8 5%, #818cf8 6%, #f0abfc 6%, #f0abfc 7%, #818cf8 7%, #818cf8 8%, #f0abfc 8%, #f0abfc 9%, #818cf8 9%, #818cf8 10%, #f0abfc 10%, #f0abfc 11%, #818cf8 11%, #818cf8 12%, #f0abfc 12%, #f0abfc 13%, #818cf8 13%, #818cf8 14%, #f0abfc 14%, #f0abfc 15%, #818cf8 15%, #818cf8 16%, #f0abfc 16%, #f0abfc 17%, #818cf8 17%, #818cf8 18%, #f0abfc 18%, #f0abfc 19%, #818cf8 19%, #818cf8 20%, #f0abfc 20%, #f0abfc 21%, #818cf8 21%, #818cf8 22%, #f0abfc 22%, #f0abfc 23%, #818cf8 23%, #818cf8 24%, #f0abfc 24%, #f0abfc 25%, #818cf8 25%, #818cf8 26%, #f0abfc 26%, #f0abfc 27%, #818cf8 27%, #818cf8 28%, #f0abfc 28%, #f0abfc 29%, #818cf8 29%, #818cf8 30%, #f0abfc 30%, #f0abfc 31%, #818cf8 31%, #818cf8 32%, #f0abfc 32%, #f0abfc 33%, #818cf8 33%, #818cf8 34%, #f0abfc 34%, #f0abfc 35%, #818cf8 35%, #818cf8 36%, #f0abfc 36%, #f0abfc 37%, #818cf8 37%, #818cf8 38%, #f0abfc 38%, #f0abfc 39%, #818cf8 39%, #818cf8 40%, #f0abfc 40%, #f0abfc 41%, #818cf8 41%, #818cf8 42%, #f0abfc 42%, #f0abfc 43%, #818cf8 43%, #818cf8 44%, #f0abfc 44%, #f0abfc 45%, #818cf8 45%, #818cf8 46%, #f0abfc 46%, #f0abfc 47%, #818cf8 47%, #818cf8 48%, #f0abfc 48%, #f0abfc 49%, #818cf8 49%, #818cf8 50%, #f0abfc 50%, #f0abfc 51%, #818cf8 51%, #818cf8 52%, #f0abfc 52%, #f0abfc 53%, #818cf8 53%, #818cf8 54%, #f0abfc 54%, #f0abfc 55%, #818cf8 55%, #818cf8 56%, #f0abfc 56%, #f0abfc 57%, #818cf8 57%, #818cf8 58%, #f0abfc 58%, #f0abfc 59%, #818cf8 59%, #818cf8 60%, #f0abfc 60%, #f0abfc 61%, #818cf8 61%, #818cf8 62%, #f0abfc 62%, #f0abfc 63%, #818cf8 63%, #818cf8 64%, #f0abfc 64%, #f0abfc 65%, #818cf8 65%, #818cf8 66%, #f0abfc 66%, #f0abfc 67%, #818cf8 67%, #818cf8 68%, #f0abfc 68%, #f0abfc 69%, #818cf8 69%, #818cf8 70%, #f0abfc 70%, #f0abfc 71%, #818cf8 71%, #818cf8 72%, #f0abfc 72%, #f0abfc 73%, #818cf8 73%, #818cf8 74%, #f0abfc 74%, #f0abfc 75%, #818cf8 75%, #818cf8 76%, #f0abfc 76%, #f0abfc 77%, #818cf8 77%, #818cf8 78%, #f0abfc 78%, #f0abfc 79%, #818cf8 79%, #818cf8 80%, #f0abfc 80%, #f0abfc 81%, #818cf8 81%, #818cf8 82%, #f0abfc 82%, #f0abfc 83%, #818cf8 83%, #818cf8 84%, #f0abfc 84%, #f0abfc 85%, #818cf8 85%, #818cf8 86%, #f0abfc 86%, #f0abfc 87%, #818cf8 87%, #818cf8 88%, #f0abfc 88%, #f0abfc 89%, #818cf8 89%, #818cf8 90%, #f0abfc 90%, #f0abfc 91%, #818cf8 91%, #818cf8 92%, #f0abfc 92%, #f0abfc 93%, #818cf8 93%, #818cf8 94%, #f0abfc 94%, #f0abfc 95%, #818cf8 95%, #818cf8 96%, #f0abfc 96%, #f0abfc 97%, #818cf8 97%, #818cf8 98%, #f0abfc 98%, #f0abfc 99%, #818cf8 99%, #818cf8 100%)",
      "type": "color",
      "description": "candy_min45°"
    },
    "candy_45°": {
      "value": "linear-gradient(45deg, #f0abfc 0%, #f0abfc 1%, #818cf8 1%, #818cf8 2%, #f0abfc 2%, #f0abfc 3%, #818cf8 3%, #818cf8 4%, #f0abfc 4%, #f0abfc 5%, #818cf8 5%, #818cf8 6%, #f0abfc 6%, #f0abfc 7%, #818cf8 7%, #818cf8 8%, #f0abfc 8%, #f0abfc 9%, #818cf8 9%, #818cf8 10%, #f0abfc 10%, #f0abfc 11%, #818cf8 11%, #818cf8 12%, #f0abfc 12%, #f0abfc 13%, #818cf8 13%, #818cf8 14%, #f0abfc 14%, #f0abfc 15%, #818cf8 15%, #818cf8 16%, #f0abfc 16%, #f0abfc 17%, #818cf8 17%, #818cf8 18%, #f0abfc 18%, #f0abfc 19%, #818cf8 19%, #818cf8 20%, #f0abfc 20%, #f0abfc 21%, #818cf8 21%, #818cf8 22%, #f0abfc 22%, #f0abfc 23%, #818cf8 23%, #818cf8 24%, #f0abfc 24%, #f0abfc 25%, #818cf8 25%, #818cf8 26%, #f0abfc 26%, #f0abfc 27%, #818cf8 27%, #818cf8 28%, #f0abfc 28%, #f0abfc 29%, #818cf8 29%, #818cf8 30%, #f0abfc 30%, #f0abfc 31%, #818cf8 31%, #818cf8 32%, #f0abfc 32%, #f0abfc 33%, #818cf8 33%, #818cf8 34%, #f0abfc 34%, #f0abfc 35%, #818cf8 35%, #818cf8 36%, #f0abfc 36%, #f0abfc 37%, #818cf8 37%, #818cf8 38%, #f0abfc 38%, #f0abfc 39%, #818cf8 39%, #818cf8 40%, #f0abfc 40%, #f0abfc 41%, #818cf8 41%, #818cf8 42%, #f0abfc 42%, #f0abfc 43%, #818cf8 43%, #818cf8 44%, #f0abfc 44%, #f0abfc 45%, #818cf8 45%, #818cf8 46%, #f0abfc 46%, #f0abfc 47%, #818cf8 47%, #818cf8 48%, #f0abfc 48%, #f0abfc 49%, #818cf8 49%, #818cf8 50%, #f0abfc 50%, #f0abfc 51%, #818cf8 51%, #818cf8 52%, #f0abfc 52%, #f0abfc 53%, #818cf8 53%, #818cf8 54%, #f0abfc 54%, #f0abfc 55%, #818cf8 55%, #818cf8 56%, #f0abfc 56%, #f0abfc 57%, #818cf8 57%, #818cf8 58%, #f0abfc 58%, #f0abfc 59%, #818cf8 59%, #818cf8 60%, #f0abfc 60%, #f0abfc 61%, #818cf8 61%, #818cf8 62%, #f0abfc 62%, #f0abfc 63%, #818cf8 63%, #818cf8 64%, #f0abfc 64%, #f0abfc 65%, #818cf8 65%, #818cf8 66%, #f0abfc 66%, #f0abfc 67%, #818cf8 67%, #818cf8 68%, #f0abfc 68%, #f0abfc 69%, #818cf8 69%, #818cf8 70%, #f0abfc 70%, #f0abfc 71%, #818cf8 71%, #818cf8 72%, #f0abfc 72%, #f0abfc 73%, #818cf8 73%, #818cf8 74%, #f0abfc 74%, #f0abfc 75%, #818cf8 75%, #818cf8 76%, #f0abfc 76%, #f0abfc 77%, #818cf8 77%, #818cf8 78%, #f0abfc 78%, #f0abfc 79%, #818cf8 79%, #818cf8 80%, #f0abfc 80%, #f0abfc 81%, #818cf8 81%, #818cf8 82%, #f0abfc 82%, #f0abfc 83%, #818cf8 83%, #818cf8 84%, #f0abfc 84%, #f0abfc 85%, #818cf8 85%, #818cf8 86%, #f0abfc 86%, #f0abfc 87%, #818cf8 87%, #818cf8 88%, #f0abfc 88%, #f0abfc 89%, #818cf8 89%, #818cf8 90%, #f0abfc 90%, #f0abfc 91%, #818cf8 91%, #818cf8 92%, #f0abfc 92%, #f0abfc 93%, #818cf8 93%, #818cf8 94%, #f0abfc 94%, #f0abfc 95%, #818cf8 95%, #818cf8 96%, #f0abfc 96%, #f0abfc 97%, #818cf8 97%, #818cf8 98%, #f0abfc 98%, #f0abfc 99%, #818cf8 99%, #818cf8 100%)",
      "type": "color",
      "description": "candy_45°"
    },
    "candy_min60°": {
      "value": "linear-gradient(-60deg, #f0abfc 0%, #f0abfc 1%, #818cf8 1%, #818cf8 2%, #f0abfc 2%, #f0abfc 3%, #818cf8 3%, #818cf8 4%, #f0abfc 4%, #f0abfc 5%, #818cf8 5%, #818cf8 6%, #f0abfc 6%, #f0abfc 7%, #818cf8 7%, #818cf8 8%, #f0abfc 8%, #f0abfc 9%, #818cf8 9%, #818cf8 10%, #f0abfc 10%, #f0abfc 11%, #818cf8 11%, #818cf8 12%, #f0abfc 12%, #f0abfc 13%, #818cf8 13%, #818cf8 14%, #f0abfc 14%, #f0abfc 15%, #818cf8 15%, #818cf8 16%, #f0abfc 16%, #f0abfc 17%, #818cf8 17%, #818cf8 18%, #f0abfc 18%, #f0abfc 19%, #818cf8 19%, #818cf8 20%, #f0abfc 20%, #f0abfc 21%, #818cf8 21%, #818cf8 22%, #f0abfc 22%, #f0abfc 23%, #818cf8 23%, #818cf8 24%, #f0abfc 24%, #f0abfc 25%, #818cf8 25%, #818cf8 26%, #f0abfc 26%, #f0abfc 27%, #818cf8 27%, #818cf8 28%, #f0abfc 28%, #f0abfc 29%, #818cf8 29%, #818cf8 30%, #f0abfc 30%, #f0abfc 31%, #818cf8 31%, #818cf8 32%, #f0abfc 32%, #f0abfc 33%, #818cf8 33%, #818cf8 34%, #f0abfc 34%, #f0abfc 35%, #818cf8 35%, #818cf8 36%, #f0abfc 36%, #f0abfc 37%, #818cf8 37%, #818cf8 38%, #f0abfc 38%, #f0abfc 39%, #818cf8 39%, #818cf8 40%, #f0abfc 40%, #f0abfc 41%, #818cf8 41%, #818cf8 42%, #f0abfc 42%, #f0abfc 43%, #818cf8 43%, #818cf8 44%, #f0abfc 44%, #f0abfc 45%, #818cf8 45%, #818cf8 46%, #f0abfc 46%, #f0abfc 47%, #818cf8 47%, #818cf8 48%, #f0abfc 48%, #f0abfc 49%, #818cf8 49%, #818cf8 50%, #f0abfc 50%, #f0abfc 51%, #818cf8 51%, #818cf8 52%, #f0abfc 52%, #f0abfc 53%, #818cf8 53%, #818cf8 54%, #f0abfc 54%, #f0abfc 55%, #818cf8 55%, #818cf8 56%, #f0abfc 56%, #f0abfc 57%, #818cf8 57%, #818cf8 58%, #f0abfc 58%, #f0abfc 59%, #818cf8 59%, #818cf8 60%, #f0abfc 60%, #f0abfc 61%, #818cf8 61%, #818cf8 62%, #f0abfc 62%, #f0abfc 63%, #818cf8 63%, #818cf8 64%, #f0abfc 64%, #f0abfc 65%, #818cf8 65%, #818cf8 66%, #f0abfc 66%, #f0abfc 67%, #818cf8 67%, #818cf8 68%, #f0abfc 68%, #f0abfc 69%, #818cf8 69%, #818cf8 70%, #f0abfc 70%, #f0abfc 71%, #818cf8 71%, #818cf8 72%, #f0abfc 72%, #f0abfc 73%, #818cf8 73%, #818cf8 74%, #f0abfc 74%, #f0abfc 75%, #818cf8 75%, #818cf8 76%, #f0abfc 76%, #f0abfc 77%, #818cf8 77%, #818cf8 78%, #f0abfc 78%, #f0abfc 79%, #818cf8 79%, #818cf8 80%, #f0abfc 80%, #f0abfc 81%, #818cf8 81%, #818cf8 82%, #f0abfc 82%, #f0abfc 83%, #818cf8 83%, #818cf8 84%, #f0abfc 84%, #f0abfc 85%, #818cf8 85%, #818cf8 86%, #f0abfc 86%, #f0abfc 87%, #818cf8 87%, #818cf8 88%, #f0abfc 88%, #f0abfc 89%, #818cf8 89%, #818cf8 90%, #f0abfc 90%, #f0abfc 91%, #818cf8 91%, #818cf8 92%, #f0abfc 92%, #f0abfc 93%, #818cf8 93%, #818cf8 94%, #f0abfc 94%, #f0abfc 95%, #818cf8 95%, #818cf8 96%, #f0abfc 96%, #f0abfc 97%, #818cf8 97%, #818cf8 98%, #f0abfc 98%, #f0abfc 99%, #818cf8 99%, #818cf8 100%)",
      "type": "color",
      "description": "candy_min60°"
    },
    "candy_60°": {
      "value": "linear-gradient(60deg, #f0abfc 0%, #f0abfc 1%, #818cf8 1%, #818cf8 2%, #f0abfc 2%, #f0abfc 3%, #818cf8 3%, #818cf8 4%, #f0abfc 4%, #f0abfc 5%, #818cf8 5%, #818cf8 6%, #f0abfc 6%, #f0abfc 7%, #818cf8 7%, #818cf8 8%, #f0abfc 8%, #f0abfc 9%, #818cf8 9%, #818cf8 10%, #f0abfc 10%, #f0abfc 11%, #818cf8 11%, #818cf8 12%, #f0abfc 12%, #f0abfc 13%, #818cf8 13%, #818cf8 14%, #f0abfc 14%, #f0abfc 15%, #818cf8 15%, #818cf8 16%, #f0abfc 16%, #f0abfc 17%, #818cf8 17%, #818cf8 18%, #f0abfc 18%, #f0abfc 19%, #818cf8 19%, #818cf8 20%, #f0abfc 20%, #f0abfc 21%, #818cf8 21%, #818cf8 22%, #f0abfc 22%, #f0abfc 23%, #818cf8 23%, #818cf8 24%, #f0abfc 24%, #f0abfc 25%, #818cf8 25%, #818cf8 26%, #f0abfc 26%, #f0abfc 27%, #818cf8 27%, #818cf8 28%, #f0abfc 28%, #f0abfc 29%, #818cf8 29%, #818cf8 30%, #f0abfc 30%, #f0abfc 31%, #818cf8 31%, #818cf8 32%, #f0abfc 32%, #f0abfc 33%, #818cf8 33%, #818cf8 34%, #f0abfc 34%, #f0abfc 35%, #818cf8 35%, #818cf8 36%, #f0abfc 36%, #f0abfc 37%, #818cf8 37%, #818cf8 38%, #f0abfc 38%, #f0abfc 39%, #818cf8 39%, #818cf8 40%, #f0abfc 40%, #f0abfc 41%, #818cf8 41%, #818cf8 42%, #f0abfc 42%, #f0abfc 43%, #818cf8 43%, #818cf8 44%, #f0abfc 44%, #f0abfc 45%, #818cf8 45%, #818cf8 46%, #f0abfc 46%, #f0abfc 47%, #818cf8 47%, #818cf8 48%, #f0abfc 48%, #f0abfc 49%, #818cf8 49%, #818cf8 50%, #f0abfc 50%, #f0abfc 51%, #818cf8 51%, #818cf8 52%, #f0abfc 52%, #f0abfc 53%, #818cf8 53%, #818cf8 54%, #f0abfc 54%, #f0abfc 55%, #818cf8 55%, #818cf8 56%, #f0abfc 56%, #f0abfc 57%, #818cf8 57%, #818cf8 58%, #f0abfc 58%, #f0abfc 59%, #818cf8 59%, #818cf8 60%, #f0abfc 60%, #f0abfc 61%, #818cf8 61%, #818cf8 62%, #f0abfc 62%, #f0abfc 63%, #818cf8 63%, #818cf8 64%, #f0abfc 64%, #f0abfc 65%, #818cf8 65%, #818cf8 66%, #f0abfc 66%, #f0abfc 67%, #818cf8 67%, #818cf8 68%, #f0abfc 68%, #f0abfc 69%, #818cf8 69%, #818cf8 70%, #f0abfc 70%, #f0abfc 71%, #818cf8 71%, #818cf8 72%, #f0abfc 72%, #f0abfc 73%, #818cf8 73%, #818cf8 74%, #f0abfc 74%, #f0abfc 75%, #818cf8 75%, #818cf8 76%, #f0abfc 76%, #f0abfc 77%, #818cf8 77%, #818cf8 78%, #f0abfc 78%, #f0abfc 79%, #818cf8 79%, #818cf8 80%, #f0abfc 80%, #f0abfc 81%, #818cf8 81%, #818cf8 82%, #f0abfc 82%, #f0abfc 83%, #818cf8 83%, #818cf8 84%, #f0abfc 84%, #f0abfc 85%, #818cf8 85%, #818cf8 86%, #f0abfc 86%, #f0abfc 87%, #818cf8 87%, #818cf8 88%, #f0abfc 88%, #f0abfc 89%, #818cf8 89%, #818cf8 90%, #f0abfc 90%, #f0abfc 91%, #818cf8 91%, #818cf8 92%, #f0abfc 92%, #f0abfc 93%, #818cf8 93%, #818cf8 94%, #f0abfc 94%, #f0abfc 95%, #818cf8 95%, #818cf8 96%, #f0abfc 96%, #f0abfc 97%, #818cf8 97%, #818cf8 98%, #f0abfc 98%, #f0abfc 99%, #818cf8 99%, #818cf8 100%)",
      "type": "color",
      "description": "candy_60°"
    },
    "candy_min75°": {
      "value": "linear-gradient(-75deg, #f0abfc 0%, #f0abfc 1%, #818cf8 1%, #818cf8 2%, #f0abfc 2%, #f0abfc 3%, #818cf8 3%, #818cf8 4%, #f0abfc 4%, #f0abfc 5%, #818cf8 5%, #818cf8 6%, #f0abfc 6%, #f0abfc 7%, #818cf8 7%, #818cf8 8%, #f0abfc 8%, #f0abfc 9%, #818cf8 9%, #818cf8 10%, #f0abfc 10%, #f0abfc 11%, #818cf8 11%, #818cf8 12%, #f0abfc 12%, #f0abfc 13%, #818cf8 13%, #818cf8 14%, #f0abfc 14%, #f0abfc 15%, #818cf8 15%, #818cf8 16%, #f0abfc 16%, #f0abfc 17%, #818cf8 17%, #818cf8 18%, #f0abfc 18%, #f0abfc 19%, #818cf8 19%, #818cf8 20%, #f0abfc 20%, #f0abfc 21%, #818cf8 21%, #818cf8 22%, #f0abfc 22%, #f0abfc 23%, #818cf8 23%, #818cf8 24%, #f0abfc 24%, #f0abfc 25%, #818cf8 25%, #818cf8 26%, #f0abfc 26%, #f0abfc 27%, #818cf8 27%, #818cf8 28%, #f0abfc 28%, #f0abfc 29%, #818cf8 29%, #818cf8 30%, #f0abfc 30%, #f0abfc 31%, #818cf8 31%, #818cf8 32%, #f0abfc 32%, #f0abfc 33%, #818cf8 33%, #818cf8 34%, #f0abfc 34%, #f0abfc 35%, #818cf8 35%, #818cf8 36%, #f0abfc 36%, #f0abfc 37%, #818cf8 37%, #818cf8 38%, #f0abfc 38%, #f0abfc 39%, #818cf8 39%, #818cf8 40%, #f0abfc 40%, #f0abfc 41%, #818cf8 41%, #818cf8 42%, #f0abfc 42%, #f0abfc 43%, #818cf8 43%, #818cf8 44%, #f0abfc 44%, #f0abfc 45%, #818cf8 45%, #818cf8 46%, #f0abfc 46%, #f0abfc 47%, #818cf8 47%, #818cf8 48%, #f0abfc 48%, #f0abfc 49%, #818cf8 49%, #818cf8 50%, #f0abfc 50%, #f0abfc 51%, #818cf8 51%, #818cf8 52%, #f0abfc 52%, #f0abfc 53%, #818cf8 53%, #818cf8 54%, #f0abfc 54%, #f0abfc 55%, #818cf8 55%, #818cf8 56%, #f0abfc 56%, #f0abfc 57%, #818cf8 57%, #818cf8 58%, #f0abfc 58%, #f0abfc 59%, #818cf8 59%, #818cf8 60%, #f0abfc 60%, #f0abfc 61%, #818cf8 61%, #818cf8 62%, #f0abfc 62%, #f0abfc 63%, #818cf8 63%, #818cf8 64%, #f0abfc 64%, #f0abfc 65%, #818cf8 65%, #818cf8 66%, #f0abfc 66%, #f0abfc 67%, #818cf8 67%, #818cf8 68%, #f0abfc 68%, #f0abfc 69%, #818cf8 69%, #818cf8 70%, #f0abfc 70%, #f0abfc 71%, #818cf8 71%, #818cf8 72%, #f0abfc 72%, #f0abfc 73%, #818cf8 73%, #818cf8 74%, #f0abfc 74%, #f0abfc 75%, #818cf8 75%, #818cf8 76%, #f0abfc 76%, #f0abfc 77%, #818cf8 77%, #818cf8 78%, #f0abfc 78%, #f0abfc 79%, #818cf8 79%, #818cf8 80%, #f0abfc 80%, #f0abfc 81%, #818cf8 81%, #818cf8 82%, #f0abfc 82%, #f0abfc 83%, #818cf8 83%, #818cf8 84%, #f0abfc 84%, #f0abfc 85%, #818cf8 85%, #818cf8 86%, #f0abfc 86%, #f0abfc 87%, #818cf8 87%, #818cf8 88%, #f0abfc 88%, #f0abfc 89%, #818cf8 89%, #818cf8 90%, #f0abfc 90%, #f0abfc 91%, #818cf8 91%, #818cf8 92%, #f0abfc 92%, #f0abfc 93%, #818cf8 93%, #818cf8 94%, #f0abfc 94%, #f0abfc 95%, #818cf8 95%, #818cf8 96%, #f0abfc 96%, #f0abfc 97%, #818cf8 97%, #818cf8 98%, #f0abfc 98%, #f0abfc 99%, #818cf8 99%, #818cf8 100%)",
      "type": "color",
      "description": "candy_min75°"
    },
    "candy_75°": {
      "value": "linear-gradient(75deg, #f0abfc 0%, #f0abfc 1%, #818cf8 1%, #818cf8 2%, #f0abfc 2%, #f0abfc 3%, #818cf8 3%, #818cf8 4%, #f0abfc 4%, #f0abfc 5%, #818cf8 5%, #818cf8 6%, #f0abfc 6%, #f0abfc 7%, #818cf8 7%, #818cf8 8%, #f0abfc 8%, #f0abfc 9%, #818cf8 9%, #818cf8 10%, #f0abfc 10%, #f0abfc 11%, #818cf8 11%, #818cf8 12%, #f0abfc 12%, #f0abfc 13%, #818cf8 13%, #818cf8 14%, #f0abfc 14%, #f0abfc 15%, #818cf8 15%, #818cf8 16%, #f0abfc 16%, #f0abfc 17%, #818cf8 17%, #818cf8 18%, #f0abfc 18%, #f0abfc 19%, #818cf8 19%, #818cf8 20%, #f0abfc 20%, #f0abfc 21%, #818cf8 21%, #818cf8 22%, #f0abfc 22%, #f0abfc 23%, #818cf8 23%, #818cf8 24%, #f0abfc 24%, #f0abfc 25%, #818cf8 25%, #818cf8 26%, #f0abfc 26%, #f0abfc 27%, #818cf8 27%, #818cf8 28%, #f0abfc 28%, #f0abfc 29%, #818cf8 29%, #818cf8 30%, #f0abfc 30%, #f0abfc 31%, #818cf8 31%, #818cf8 32%, #f0abfc 32%, #f0abfc 33%, #818cf8 33%, #818cf8 34%, #f0abfc 34%, #f0abfc 35%, #818cf8 35%, #818cf8 36%, #f0abfc 36%, #f0abfc 37%, #818cf8 37%, #818cf8 38%, #f0abfc 38%, #f0abfc 39%, #818cf8 39%, #818cf8 40%, #f0abfc 40%, #f0abfc 41%, #818cf8 41%, #818cf8 42%, #f0abfc 42%, #f0abfc 43%, #818cf8 43%, #818cf8 44%, #f0abfc 44%, #f0abfc 45%, #818cf8 45%, #818cf8 46%, #f0abfc 46%, #f0abfc 47%, #818cf8 47%, #818cf8 48%, #f0abfc 48%, #f0abfc 49%, #818cf8 49%, #818cf8 50%, #f0abfc 50%, #f0abfc 51%, #818cf8 51%, #818cf8 52%, #f0abfc 52%, #f0abfc 53%, #818cf8 53%, #818cf8 54%, #f0abfc 54%, #f0abfc 55%, #818cf8 55%, #818cf8 56%, #f0abfc 56%, #f0abfc 57%, #818cf8 57%, #818cf8 58%, #f0abfc 58%, #f0abfc 59%, #818cf8 59%, #818cf8 60%, #f0abfc 60%, #f0abfc 61%, #818cf8 61%, #818cf8 62%, #f0abfc 62%, #f0abfc 63%, #818cf8 63%, #818cf8 64%, #f0abfc 64%, #f0abfc 65%, #818cf8 65%, #818cf8 66%, #f0abfc 66%, #f0abfc 67%, #818cf8 67%, #818cf8 68%, #f0abfc 68%, #f0abfc 69%, #818cf8 69%, #818cf8 70%, #f0abfc 70%, #f0abfc 71%, #818cf8 71%, #818cf8 72%, #f0abfc 72%, #f0abfc 73%, #818cf8 73%, #818cf8 74%, #f0abfc 74%, #f0abfc 75%, #818cf8 75%, #818cf8 76%, #f0abfc 76%, #f0abfc 77%, #818cf8 77%, #818cf8 78%, #f0abfc 78%, #f0abfc 79%, #818cf8 79%, #818cf8 80%, #f0abfc 80%, #f0abfc 81%, #818cf8 81%, #818cf8 82%, #f0abfc 82%, #f0abfc 83%, #818cf8 83%, #818cf8 84%, #f0abfc 84%, #f0abfc 85%, #818cf8 85%, #818cf8 86%, #f0abfc 86%, #f0abfc 87%, #818cf8 87%, #818cf8 88%, #f0abfc 88%, #f0abfc 89%, #818cf8 89%, #818cf8 90%, #f0abfc 90%, #f0abfc 91%, #818cf8 91%, #818cf8 92%, #f0abfc 92%, #f0abfc 93%, #818cf8 93%, #818cf8 94%, #f0abfc 94%, #f0abfc 95%, #818cf8 95%, #818cf8 96%, #f0abfc 96%, #f0abfc 97%, #818cf8 97%, #818cf8 98%, #f0abfc 98%, #f0abfc 99%, #818cf8 99%, #818cf8 100%)",
      "type": "color",
      "description": "candy_75°"
    },
    "candy_0°": {
      "value": "linear-gradient(0deg, #f0abfc 0%, #f0abfc 1%, #818cf8 1%, #818cf8 2%, #f0abfc 2%, #f0abfc 3%, #818cf8 3%, #818cf8 4%, #f0abfc 4%, #f0abfc 5%, #818cf8 5%, #818cf8 6%, #f0abfc 6%, #f0abfc 7%, #818cf8 7%, #818cf8 8%, #f0abfc 8%, #f0abfc 9%, #818cf8 9%, #818cf8 10%, #f0abfc 10%, #f0abfc 11%, #818cf8 11%, #818cf8 12%, #f0abfc 12%, #f0abfc 13%, #818cf8 13%, #818cf8 14%, #f0abfc 14%, #f0abfc 15%, #818cf8 15%, #818cf8 16%, #f0abfc 16%, #f0abfc 17%, #818cf8 17%, #818cf8 18%, #f0abfc 18%, #f0abfc 19%, #818cf8 19%, #818cf8 20%, #f0abfc 20%, #f0abfc 21%, #818cf8 21%, #818cf8 22%, #f0abfc 22%, #f0abfc 23%, #818cf8 23%, #818cf8 24%, #f0abfc 24%, #f0abfc 25%, #818cf8 25%, #818cf8 26%, #f0abfc 26%, #f0abfc 27%, #818cf8 27%, #818cf8 28%, #f0abfc 28%, #f0abfc 29%, #818cf8 29%, #818cf8 30%, #f0abfc 30%, #f0abfc 31%, #818cf8 31%, #818cf8 32%, #f0abfc 32%, #f0abfc 33%, #818cf8 33%, #818cf8 34%, #f0abfc 34%, #f0abfc 35%, #818cf8 35%, #818cf8 36%, #f0abfc 36%, #f0abfc 37%, #818cf8 37%, #818cf8 38%, #f0abfc 38%, #f0abfc 39%, #818cf8 39%, #818cf8 40%, #f0abfc 40%, #f0abfc 41%, #818cf8 41%, #818cf8 42%, #f0abfc 42%, #f0abfc 43%, #818cf8 43%, #818cf8 44%, #f0abfc 44%, #f0abfc 45%, #818cf8 45%, #818cf8 46%, #f0abfc 46%, #f0abfc 47%, #818cf8 47%, #818cf8 48%, #f0abfc 48%, #f0abfc 49%, #818cf8 49%, #818cf8 50%, #f0abfc 50%, #f0abfc 51%, #818cf8 51%, #818cf8 52%, #f0abfc 52%, #f0abfc 53%, #818cf8 53%, #818cf8 54%, #f0abfc 54%, #f0abfc 55%, #818cf8 55%, #818cf8 56%, #f0abfc 56%, #f0abfc 57%, #818cf8 57%, #818cf8 58%, #f0abfc 58%, #f0abfc 59%, #818cf8 59%, #818cf8 60%, #f0abfc 60%, #f0abfc 61%, #818cf8 61%, #818cf8 62%, #f0abfc 62%, #f0abfc 63%, #818cf8 63%, #818cf8 64%, #f0abfc 64%, #f0abfc 65%, #818cf8 65%, #818cf8 66%, #f0abfc 66%, #f0abfc 67%, #818cf8 67%, #818cf8 68%, #f0abfc 68%, #f0abfc 69%, #818cf8 69%, #818cf8 70%, #f0abfc 70%, #f0abfc 71%, #818cf8 71%, #818cf8 72%, #f0abfc 72%, #f0abfc 73%, #818cf8 73%, #818cf8 74%, #f0abfc 74%, #f0abfc 75%, #818cf8 75%, #818cf8 76%, #f0abfc 76%, #f0abfc 77%, #818cf8 77%, #818cf8 78%, #f0abfc 78%, #f0abfc 79%, #818cf8 79%, #818cf8 80%, #f0abfc 80%, #f0abfc 81%, #818cf8 81%, #818cf8 82%, #f0abfc 82%, #f0abfc 83%, #818cf8 83%, #818cf8 84%, #f0abfc 84%, #f0abfc 85%, #818cf8 85%, #818cf8 86%, #f0abfc 86%, #f0abfc 87%, #818cf8 87%, #818cf8 88%, #f0abfc 88%, #f0abfc 89%, #818cf8 89%, #818cf8 90%, #f0abfc 90%, #f0abfc 91%, #818cf8 91%, #818cf8 92%, #f0abfc 92%, #f0abfc 93%, #818cf8 93%, #818cf8 94%, #f0abfc 94%, #f0abfc 95%, #818cf8 95%, #818cf8 96%, #f0abfc 96%, #f0abfc 97%, #818cf8 97%, #818cf8 98%, #f0abfc 98%, #f0abfc 99%, #818cf8 99%, #818cf8 100%)",
      "type": "color",
      "description": "candy_0°"
    },
    "candy_90°": {
      "value": "linear-gradient(90deg, #f0abfc 0%, #f0abfc 1%, #818cf8 1%, #818cf8 2%, #f0abfc 2%, #f0abfc 3%, #818cf8 3%, #818cf8 4%, #f0abfc 4%, #f0abfc 5%, #818cf8 5%, #818cf8 6%, #f0abfc 6%, #f0abfc 7%, #818cf8 7%, #818cf8 8%, #f0abfc 8%, #f0abfc 9%, #818cf8 9%, #818cf8 10%, #f0abfc 10%, #f0abfc 11%, #818cf8 11%, #818cf8 12%, #f0abfc 12%, #f0abfc 13%, #818cf8 13%, #818cf8 14%, #f0abfc 14%, #f0abfc 15%, #818cf8 15%, #818cf8 16%, #f0abfc 16%, #f0abfc 17%, #818cf8 17%, #818cf8 18%, #f0abfc 18%, #f0abfc 19%, #818cf8 19%, #818cf8 20%, #f0abfc 20%, #f0abfc 21%, #818cf8 21%, #818cf8 22%, #f0abfc 22%, #f0abfc 23%, #818cf8 23%, #818cf8 24%, #f0abfc 24%, #f0abfc 25%, #818cf8 25%, #818cf8 26%, #f0abfc 26%, #f0abfc 27%, #818cf8 27%, #818cf8 28%, #f0abfc 28%, #f0abfc 29%, #818cf8 29%, #818cf8 30%, #f0abfc 30%, #f0abfc 31%, #818cf8 31%, #818cf8 32%, #f0abfc 32%, #f0abfc 33%, #818cf8 33%, #818cf8 34%, #f0abfc 34%, #f0abfc 35%, #818cf8 35%, #818cf8 36%, #f0abfc 36%, #f0abfc 37%, #818cf8 37%, #818cf8 38%, #f0abfc 38%, #f0abfc 39%, #818cf8 39%, #818cf8 40%, #f0abfc 40%, #f0abfc 41%, #818cf8 41%, #818cf8 42%, #f0abfc 42%, #f0abfc 43%, #818cf8 43%, #818cf8 44%, #f0abfc 44%, #f0abfc 45%, #818cf8 45%, #818cf8 46%, #f0abfc 46%, #f0abfc 47%, #818cf8 47%, #818cf8 48%, #f0abfc 48%, #f0abfc 49%, #818cf8 49%, #818cf8 50%, #f0abfc 50%, #f0abfc 51%, #818cf8 51%, #818cf8 52%, #f0abfc 52%, #f0abfc 53%, #818cf8 53%, #818cf8 54%, #f0abfc 54%, #f0abfc 55%, #818cf8 55%, #818cf8 56%, #f0abfc 56%, #f0abfc 57%, #818cf8 57%, #818cf8 58%, #f0abfc 58%, #f0abfc 59%, #818cf8 59%, #818cf8 60%, #f0abfc 60%, #f0abfc 61%, #818cf8 61%, #818cf8 62%, #f0abfc 62%, #f0abfc 63%, #818cf8 63%, #818cf8 64%, #f0abfc 64%, #f0abfc 65%, #818cf8 65%, #818cf8 66%, #f0abfc 66%, #f0abfc 67%, #818cf8 67%, #818cf8 68%, #f0abfc 68%, #f0abfc 69%, #818cf8 69%, #818cf8 70%, #f0abfc 70%, #f0abfc 71%, #818cf8 71%, #818cf8 72%, #f0abfc 72%, #f0abfc 73%, #818cf8 73%, #818cf8 74%, #f0abfc 74%, #f0abfc 75%, #818cf8 75%, #818cf8 76%, #f0abfc 76%, #f0abfc 77%, #818cf8 77%, #818cf8 78%, #f0abfc 78%, #f0abfc 79%, #818cf8 79%, #818cf8 80%, #f0abfc 80%, #f0abfc 81%, #818cf8 81%, #818cf8 82%, #f0abfc 82%, #f0abfc 83%, #818cf8 83%, #818cf8 84%, #f0abfc 84%, #f0abfc 85%, #818cf8 85%, #818cf8 86%, #f0abfc 86%, #f0abfc 87%, #818cf8 87%, #818cf8 88%, #f0abfc 88%, #f0abfc 89%, #818cf8 89%, #818cf8 90%, #f0abfc 90%, #f0abfc 91%, #818cf8 91%, #818cf8 92%, #f0abfc 92%, #f0abfc 93%, #818cf8 93%, #818cf8 94%, #f0abfc 94%, #f0abfc 95%, #818cf8 95%, #818cf8 96%, #f0abfc 96%, #f0abfc 97%, #818cf8 97%, #818cf8 98%, #f0abfc 98%, #f0abfc 99%, #818cf8 99%, #818cf8 100%)",
      "type": "color",
      "description": "candy_90°"
    },
    "stripe_min45°": {
      "value": "linear-gradient(-45deg, #f0abfc 0%, #f0abfc 1%, #818cf8 1%, #818cf8 5%, #f0abfc 5%, #f0abfc 6%, #818cf8 6%, #818cf8 10%, #f0abfc 10%, #f0abfc 11%, #818cf8 11%, #818cf8 15%, #f0abfc 15%, #f0abfc 16%, #818cf8 16%, #818cf8 20%, #f0abfc 20%, #f0abfc 21%, #818cf8 21%, #818cf8 25%, #f0abfc 25%, #f0abfc 26%, #818cf8 26%, #818cf8 30%, #f0abfc 30%, #f0abfc 31%, #818cf8 31%, #818cf8 35%, #f0abfc 35%, #f0abfc 36%, #818cf8 36%, #818cf8 40%, #f0abfc 40%, #f0abfc 41%, #818cf8 41%, #818cf8 45%, #f0abfc 45%, #f0abfc 46%, #818cf8 46%, #818cf8 50%, #f0abfc 50%, #f0abfc 51%, #818cf8 51%, #818cf8 55%, #f0abfc 55%, #f0abfc 56%, #818cf8 56%, #818cf8 60%, #f0abfc 60%, #f0abfc 61%, #818cf8 61%, #818cf8 65%, #f0abfc 65%, #f0abfc 66%, #818cf8 66%, #818cf8 70%, #f0abfc 70%, #f0abfc 71%, #818cf8 71%, #818cf8 75%, #f0abfc 75%, #f0abfc 76%, #818cf8 76%, #818cf8 80%, #f0abfc 80%, #f0abfc 81%, #818cf8 81%, #818cf8 85%, #f0abfc 85%, #f0abfc 86%, #818cf8 86%, #818cf8 90%, #f0abfc 90%, #f0abfc 91%, #818cf8 91%, #818cf8 95%, #f0abfc 95%, #f0abfc 96%, #818cf8 96%, #818cf8 100%)",
      "type": "color",
      "description": "stripe_min45°"
    },
    "stripe_45°": {
      "value": "linear-gradient(45deg, #f0abfc 0%, #f0abfc 1%, #818cf8 1%, #818cf8 5%, #f0abfc 5%, #f0abfc 6%, #818cf8 6%, #818cf8 10%, #f0abfc 10%, #f0abfc 11%, #818cf8 11%, #818cf8 15%, #f0abfc 15%, #f0abfc 16%, #818cf8 16%, #818cf8 20%, #f0abfc 20%, #f0abfc 21%, #818cf8 21%, #818cf8 25%, #f0abfc 25%, #f0abfc 26%, #818cf8 26%, #818cf8 30%, #f0abfc 30%, #f0abfc 31%, #818cf8 31%, #818cf8 35%, #f0abfc 35%, #f0abfc 36%, #818cf8 36%, #818cf8 40%, #f0abfc 40%, #f0abfc 41%, #818cf8 41%, #818cf8 45%, #f0abfc 45%, #f0abfc 46%, #818cf8 46%, #818cf8 50%, #f0abfc 50%, #f0abfc 51%, #818cf8 51%, #818cf8 55%, #f0abfc 55%, #f0abfc 56%, #818cf8 56%, #818cf8 60%, #f0abfc 60%, #f0abfc 61%, #818cf8 61%, #818cf8 65%, #f0abfc 65%, #f0abfc 66%, #818cf8 66%, #818cf8 70%, #f0abfc 70%, #f0abfc 71%, #818cf8 71%, #818cf8 75%, #f0abfc 75%, #f0abfc 76%, #818cf8 76%, #818cf8 80%, #f0abfc 80%, #f0abfc 81%, #818cf8 81%, #818cf8 85%, #f0abfc 85%, #f0abfc 86%, #818cf8 86%, #818cf8 90%, #f0abfc 90%, #f0abfc 91%, #818cf8 91%, #818cf8 95%, #f0abfc 95%, #f0abfc 96%, #818cf8 96%, #818cf8 100%)",
      "type": "color",
      "description": "stripe_45°"
    },
    "stripe_min60°": {
      "value": "linear-gradient(-60deg, #f0abfc 0%, #f0abfc 1%, #818cf8 1%, #818cf8 5%, #f0abfc 5%, #f0abfc 6%, #818cf8 6%, #818cf8 10%, #f0abfc 10%, #f0abfc 11%, #818cf8 11%, #818cf8 15%, #f0abfc 15%, #f0abfc 16%, #818cf8 16%, #818cf8 20%, #f0abfc 20%, #f0abfc 21%, #818cf8 21%, #818cf8 25%, #f0abfc 25%, #f0abfc 26%, #818cf8 26%, #818cf8 30%, #f0abfc 30%, #f0abfc 31%, #818cf8 31%, #818cf8 35%, #f0abfc 35%, #f0abfc 36%, #818cf8 36%, #818cf8 40%, #f0abfc 40%, #f0abfc 41%, #818cf8 41%, #818cf8 45%, #f0abfc 45%, #f0abfc 46%, #818cf8 46%, #818cf8 50%, #f0abfc 50%, #f0abfc 51%, #818cf8 51%, #818cf8 55%, #f0abfc 55%, #f0abfc 56%, #818cf8 56%, #818cf8 60%, #f0abfc 60%, #f0abfc 61%, #818cf8 61%, #818cf8 65%, #f0abfc 65%, #f0abfc 66%, #818cf8 66%, #818cf8 70%, #f0abfc 70%, #f0abfc 71%, #818cf8 71%, #818cf8 75%, #f0abfc 75%, #f0abfc 76%, #818cf8 76%, #818cf8 80%, #f0abfc 80%, #f0abfc 81%, #818cf8 81%, #818cf8 85%, #f0abfc 85%, #f0abfc 86%, #818cf8 86%, #818cf8 90%, #f0abfc 90%, #f0abfc 91%, #818cf8 91%, #818cf8 95%, #f0abfc 95%, #f0abfc 96%, #818cf8 96%, #818cf8 100%)",
      "type": "color",
      "description": "stripe_min60°"
    },
    "stripe_60°": {
      "value": "linear-gradient(60deg, #f0abfc 0%, #f0abfc 1%, #818cf8 1%, #818cf8 5%, #f0abfc 5%, #f0abfc 6%, #818cf8 6%, #818cf8 10%, #f0abfc 10%, #f0abfc 11%, #818cf8 11%, #818cf8 15%, #f0abfc 15%, #f0abfc 16%, #818cf8 16%, #818cf8 20%, #f0abfc 20%, #f0abfc 21%, #818cf8 21%, #818cf8 25%, #f0abfc 25%, #f0abfc 26%, #818cf8 26%, #818cf8 30%, #f0abfc 30%, #f0abfc 31%, #818cf8 31%, #818cf8 35%, #f0abfc 35%, #f0abfc 36%, #818cf8 36%, #818cf8 40%, #f0abfc 40%, #f0abfc 41%, #818cf8 41%, #818cf8 45%, #f0abfc 45%, #f0abfc 46%, #818cf8 46%, #818cf8 50%, #f0abfc 50%, #f0abfc 51%, #818cf8 51%, #818cf8 55%, #f0abfc 55%, #f0abfc 56%, #818cf8 56%, #818cf8 60%, #f0abfc 60%, #f0abfc 61%, #818cf8 61%, #818cf8 65%, #f0abfc 65%, #f0abfc 66%, #818cf8 66%, #818cf8 70%, #f0abfc 70%, #f0abfc 71%, #818cf8 71%, #818cf8 75%, #f0abfc 75%, #f0abfc 76%, #818cf8 76%, #818cf8 80%, #f0abfc 80%, #f0abfc 81%, #818cf8 81%, #818cf8 85%, #f0abfc 85%, #f0abfc 86%, #818cf8 86%, #818cf8 90%, #f0abfc 90%, #f0abfc 91%, #818cf8 91%, #818cf8 95%, #f0abfc 95%, #f0abfc 96%, #818cf8 96%, #818cf8 100%)",
      "type": "color",
      "description": "stripe_60°"
    },
    "stripe_min75°": {
      "value": "linear-gradient(-75deg, #f0abfc 0%, #f0abfc 1%, #818cf8 1%, #818cf8 5%, #f0abfc 5%, #f0abfc 6%, #818cf8 6%, #818cf8 10%, #f0abfc 10%, #f0abfc 11%, #818cf8 11%, #818cf8 15%, #f0abfc 15%, #f0abfc 16%, #818cf8 16%, #818cf8 20%, #f0abfc 20%, #f0abfc 21%, #818cf8 21%, #818cf8 25%, #f0abfc 25%, #f0abfc 26%, #818cf8 26%, #818cf8 30%, #f0abfc 30%, #f0abfc 31%, #818cf8 31%, #818cf8 35%, #f0abfc 35%, #f0abfc 36%, #818cf8 36%, #818cf8 40%, #f0abfc 40%, #f0abfc 41%, #818cf8 41%, #818cf8 45%, #f0abfc 45%, #f0abfc 46%, #818cf8 46%, #818cf8 50%, #f0abfc 50%, #f0abfc 51%, #818cf8 51%, #818cf8 55%, #f0abfc 55%, #f0abfc 56%, #818cf8 56%, #818cf8 60%, #f0abfc 60%, #f0abfc 61%, #818cf8 61%, #818cf8 65%, #f0abfc 65%, #f0abfc 66%, #818cf8 66%, #818cf8 70%, #f0abfc 70%, #f0abfc 71%, #818cf8 71%, #818cf8 75%, #f0abfc 75%, #f0abfc 76%, #818cf8 76%, #818cf8 80%, #f0abfc 80%, #f0abfc 81%, #818cf8 81%, #818cf8 85%, #f0abfc 85%, #f0abfc 86%, #818cf8 86%, #818cf8 90%, #f0abfc 90%, #f0abfc 91%, #818cf8 91%, #818cf8 95%, #f0abfc 95%, #f0abfc 96%, #818cf8 96%, #818cf8 100%)",
      "type": "color",
      "description": "stripe_min75°"
    },
    "stripe_75°": {
      "value": "linear-gradient(75deg, #f0abfc 0%, #f0abfc 1%, #818cf8 1%, #818cf8 5%, #f0abfc 5%, #f0abfc 6%, #818cf8 6%, #818cf8 10%, #f0abfc 10%, #f0abfc 11%, #818cf8 11%, #818cf8 15%, #f0abfc 15%, #f0abfc 16%, #818cf8 16%, #818cf8 20%, #f0abfc 20%, #f0abfc 21%, #818cf8 21%, #818cf8 25%, #f0abfc 25%, #f0abfc 26%, #818cf8 26%, #818cf8 30%, #f0abfc 30%, #f0abfc 31%, #818cf8 31%, #818cf8 35%, #f0abfc 35%, #f0abfc 36%, #818cf8 36%, #818cf8 40%, #f0abfc 40%, #f0abfc 41%, #818cf8 41%, #818cf8 45%, #f0abfc 45%, #f0abfc 46%, #818cf8 46%, #818cf8 50%, #f0abfc 50%, #f0abfc 51%, #818cf8 51%, #818cf8 55%, #f0abfc 55%, #f0abfc 56%, #818cf8 56%, #818cf8 60%, #f0abfc 60%, #f0abfc 61%, #818cf8 61%, #818cf8 65%, #f0abfc 65%, #f0abfc 66%, #818cf8 66%, #818cf8 70%, #f0abfc 70%, #f0abfc 71%, #818cf8 71%, #818cf8 75%, #f0abfc 75%, #f0abfc 76%, #818cf8 76%, #818cf8 80%, #f0abfc 80%, #f0abfc 81%, #818cf8 81%, #818cf8 85%, #f0abfc 85%, #f0abfc 86%, #818cf8 86%, #818cf8 90%, #f0abfc 90%, #f0abfc 91%, #818cf8 91%, #818cf8 95%, #f0abfc 95%, #f0abfc 96%, #818cf8 96%, #818cf8 100%)",
      "type": "color",
      "description": "stripe_75°"
    },
    "stripe_0°": {
      "value": "linear-gradient(0deg, #f0abfc 0%, #f0abfc 1%, #818cf8 1%, #818cf8 5%, #f0abfc 5%, #f0abfc 6%, #818cf8 6%, #818cf8 10%, #f0abfc 10%, #f0abfc 11%, #818cf8 11%, #818cf8 15%, #f0abfc 15%, #f0abfc 16%, #818cf8 16%, #818cf8 20%, #f0abfc 20%, #f0abfc 21%, #818cf8 21%, #818cf8 25%, #f0abfc 25%, #f0abfc 26%, #818cf8 26%, #818cf8 30%, #f0abfc 30%, #f0abfc 31%, #818cf8 31%, #818cf8 35%, #f0abfc 35%, #f0abfc 36%, #818cf8 36%, #818cf8 40%, #f0abfc 40%, #f0abfc 41%, #818cf8 41%, #818cf8 45%, #f0abfc 45%, #f0abfc 46%, #818cf8 46%, #818cf8 50%, #f0abfc 50%, #f0abfc 51%, #818cf8 51%, #818cf8 55%, #f0abfc 55%, #f0abfc 56%, #818cf8 56%, #818cf8 60%, #f0abfc 60%, #f0abfc 61%, #818cf8 61%, #818cf8 65%, #f0abfc 65%, #f0abfc 66%, #818cf8 66%, #818cf8 70%, #f0abfc 70%, #f0abfc 71%, #818cf8 71%, #818cf8 75%, #f0abfc 75%, #f0abfc 76%, #818cf8 76%, #818cf8 80%, #f0abfc 80%, #f0abfc 81%, #818cf8 81%, #818cf8 85%, #f0abfc 85%, #f0abfc 86%, #818cf8 86%, #818cf8 90%, #f0abfc 90%, #f0abfc 91%, #818cf8 91%, #818cf8 95%, #f0abfc 95%, #f0abfc 96%, #818cf8 96%, #818cf8 100%)",
      "type": "color",
      "description": "stripe_0°"
    },
    "stripe_90°": {
      "value": "linear-gradient(-90deg, #f0abfc 0%, #f0abfc 1%, #818cf8 1%, #818cf8 5%, #f0abfc 5%, #f0abfc 6%, #818cf8 6%, #818cf8 10%, #f0abfc 10%, #f0abfc 11%, #818cf8 11%, #818cf8 15%, #f0abfc 15%, #f0abfc 16%, #818cf8 16%, #818cf8 20%, #f0abfc 20%, #f0abfc 21%, #818cf8 21%, #818cf8 25%, #f0abfc 25%, #f0abfc 26%, #818cf8 26%, #818cf8 30%, #f0abfc 30%, #f0abfc 31%, #818cf8 31%, #818cf8 35%, #f0abfc 35%, #f0abfc 36%, #818cf8 36%, #818cf8 40%, #f0abfc 40%, #f0abfc 41%, #818cf8 41%, #818cf8 45%, #f0abfc 45%, #f0abfc 46%, #818cf8 46%, #818cf8 50%, #f0abfc 50%, #f0abfc 51%, #818cf8 51%, #818cf8 55%, #f0abfc 55%, #f0abfc 56%, #818cf8 56%, #818cf8 60%, #f0abfc 60%, #f0abfc 61%, #818cf8 61%, #818cf8 65%, #f0abfc 65%, #f0abfc 66%, #818cf8 66%, #818cf8 70%, #f0abfc 70%, #f0abfc 71%, #818cf8 71%, #818cf8 75%, #f0abfc 75%, #f0abfc 76%, #818cf8 76%, #818cf8 80%, #f0abfc 80%, #f0abfc 81%, #818cf8 81%, #818cf8 85%, #f0abfc 85%, #f0abfc 86%, #818cf8 86%, #818cf8 90%, #f0abfc 90%, #f0abfc 91%, #818cf8 91%, #818cf8 95%, #f0abfc 95%, #f0abfc 96%, #818cf8 96%, #818cf8 100%)",
      "type": "color",
      "description": "stripe_90°"
    }
  }
}