{
  "generationux-styles": {
    "background": {
      "value": "#5EEAD4",
      "type": "color",
      "description": "background"
    },
    "foreground": {
      "value": "#6D28D9",
      "type": "color",
      "description": "foreground"
    },
    "card": {
      "value": "#5EEAD4",
      "type": "color",
      "description": "card"
    },
    "card-foreground": {
      "value": "#4c1d95",
      "type": "color",
      "description": "card-foreground"
    },
    "popover": {
      "value": "#5EEAD4",
      "type": "color",
      "description": "popover"
    },
    "popover-foreground": {
      "value": "#4c1d95",
      "type": "color",
      "description": "popover-foreground"
    },
    "primary": {
      "value": "#6D28D9",
      "type": "color",
      "description": "primary"
    },
    "primary-foreground": {
      "value": "#5EEAD4",
      "type": "color",
      "description": "primary-foreground"
    },
    "secondary": {
      "value": "#2dd4bf",
      "type": "color",
      "description": "secondary"
    },
    "secondary-foreground": {
      "value": "#4c1d95",
      "type": "color",
      "description": "secondary-foreground"
    },
    "muted": {
      "value": "#2dd4bf",
      "type": "color",
      "description": "muted"
    },
    "muted-foreground": {
      "value": "#4c1d95",
      "type": "color",
      "description": "muted-foreground"
    },
    "accent": {
      "value": "#2dd4bf",
      "type": "color",
      "description": "accent"
    },
    "accent-foreground": {
      "value": "#4c1d95",
      "type": "color",
      "description": "accent-foreground"
    },
    "destructive": {
      "value": "linear-gradient(-75deg, #5EEAD4 0%, #5EEAD4 4%, #6D28D9 4%, #6D28D9 8%, #5EEAD4 8%, #5EEAD4 12%, #6D28D9 12%, #6D28D9 16%, #5EEAD4 16%, #5EEAD4 20%, #6D28D9 20%, #6D28D9 24%, #5EEAD4 24%, #5EEAD4 28%, #6D28D9 28%, #6D28D9 32%, #5EEAD4 32%, #5EEAD4 36%, #6D28D9 36%, #6D28D9 40%, #5EEAD4 40%, #5EEAD4 44%, #6D28D9 44%, #6D28D9 48%, #5EEAD4 48%, #5EEAD4 52%, #6D28D9 52%, #6D28D9 56%, #5EEAD4 56%, #5EEAD4 60%, #6D28D9 60%, #6D28D9 64%, #5EEAD4 64%, #5EEAD4 68%, #6D28D9 68%, #6D28D9 72%, #5EEAD4 72%, #5EEAD4 76%, #6D28D9 76%, #6D28D9 80%, #5EEAD4 80%, #5EEAD4 84%, #6D28D9 84%, #6D28D9 88%, #5EEAD4 88%, #5EEAD4 92%, #6D28D9 92%,#6D28D9 92%, #5EEAD4 96%, #5EEAD4 96%, #6D28D9 100%)",
      "type": "color",
      "description": "destructive"
    },
    "destructive-foreground": {
      "value": "#4c1d95",
      "type": "color",
      "description": "destructive-foreground"
    },
    "border": {
      "value": "#4c1d95",
      "type": "color",
      "description": "border"
    },
    "input": {
      "value": "#4c1d95",
      "type": "color",
      "description": "input"
    },
    "ring": {
      "value": "#4c1d95",
      "type": "color",
      "description": "ring"
    },
    "boxshadow": {
      "value": "#4c1d95",
      "type": "color",
      "description": "boxshadow"
    },
    "candy_min45°": {
      "value": "linear-gradient(-45deg, #5EEAD4 0%, #5EEAD4 1%, #6D28D9 1%, #6D28D9 2%, #5EEAD4 2%, #5EEAD4 3%, #6D28D9 3%, #6D28D9 4%, #5EEAD4 4%, #5EEAD4 5%, #6D28D9 5%, #6D28D9 6%, #5EEAD4 6%, #5EEAD4 7%, #6D28D9 7%, #6D28D9 8%, #5EEAD4 8%, #5EEAD4 9%, #6D28D9 9%, #6D28D9 10%, #5EEAD4 10%, #5EEAD4 11%, #6D28D9 11%, #6D28D9 12%, #5EEAD4 12%, #5EEAD4 13%, #6D28D9 13%, #6D28D9 14%, #5EEAD4 14%, #5EEAD4 15%, #6D28D9 15%, #6D28D9 16%, #5EEAD4 16%, #5EEAD4 17%, #6D28D9 17%, #6D28D9 18%, #5EEAD4 18%, #5EEAD4 19%, #6D28D9 19%, #6D28D9 20%, #5EEAD4 20%, #5EEAD4 21%, #6D28D9 21%, #6D28D9 22%, #5EEAD4 22%, #5EEAD4 23%, #6D28D9 23%, #6D28D9 24%, #5EEAD4 24%, #5EEAD4 25%, #6D28D9 25%, #6D28D9 26%, #5EEAD4 26%, #5EEAD4 27%, #6D28D9 27%, #6D28D9 28%, #5EEAD4 28%, #5EEAD4 29%, #6D28D9 29%, #6D28D9 30%, #5EEAD4 30%, #5EEAD4 31%, #6D28D9 31%, #6D28D9 32%, #5EEAD4 32%, #5EEAD4 33%, #6D28D9 33%, #6D28D9 34%, #5EEAD4 34%, #5EEAD4 35%, #6D28D9 35%, #6D28D9 36%, #5EEAD4 36%, #5EEAD4 37%, #6D28D9 37%, #6D28D9 38%, #5EEAD4 38%, #5EEAD4 39%, #6D28D9 39%, #6D28D9 40%, #5EEAD4 40%, #5EEAD4 41%, #6D28D9 41%, #6D28D9 42%, #5EEAD4 42%, #5EEAD4 43%, #6D28D9 43%, #6D28D9 44%, #5EEAD4 44%, #5EEAD4 45%, #6D28D9 45%, #6D28D9 46%, #5EEAD4 46%, #5EEAD4 47%, #6D28D9 47%, #6D28D9 48%, #5EEAD4 48%, #5EEAD4 49%, #6D28D9 49%, #6D28D9 50%, #5EEAD4 50%, #5EEAD4 51%, #6D28D9 51%, #6D28D9 52%, #5EEAD4 52%, #5EEAD4 53%, #6D28D9 53%, #6D28D9 54%, #5EEAD4 54%, #5EEAD4 55%, #6D28D9 55%, #6D28D9 56%, #5EEAD4 56%, #5EEAD4 57%, #6D28D9 57%, #6D28D9 58%, #5EEAD4 58%, #5EEAD4 59%, #6D28D9 59%, #6D28D9 60%, #5EEAD4 60%, #5EEAD4 61%, #6D28D9 61%, #6D28D9 62%, #5EEAD4 62%, #5EEAD4 63%, #6D28D9 63%, #6D28D9 64%, #5EEAD4 64%, #5EEAD4 65%, #6D28D9 65%, #6D28D9 66%, #5EEAD4 66%, #5EEAD4 67%, #6D28D9 67%, #6D28D9 68%, #5EEAD4 68%, #5EEAD4 69%, #6D28D9 69%, #6D28D9 70%, #5EEAD4 70%, #5EEAD4 71%, #6D28D9 71%, #6D28D9 72%, #5EEAD4 72%, #5EEAD4 73%, #6D28D9 73%, #6D28D9 74%, #5EEAD4 74%, #5EEAD4 75%, #6D28D9 75%, #6D28D9 76%, #5EEAD4 76%, #5EEAD4 77%, #6D28D9 77%, #6D28D9 78%, #5EEAD4 78%, #5EEAD4 79%, #6D28D9 79%, #6D28D9 80%, #5EEAD4 80%, #5EEAD4 81%, #6D28D9 81%, #6D28D9 82%, #5EEAD4 82%, #5EEAD4 83%, #6D28D9 83%, #6D28D9 84%, #5EEAD4 84%, #5EEAD4 85%, #6D28D9 85%, #6D28D9 86%, #5EEAD4 86%, #5EEAD4 87%, #6D28D9 87%, #6D28D9 88%, #5EEAD4 88%, #5EEAD4 89%, #6D28D9 89%, #6D28D9 90%, #5EEAD4 90%, #5EEAD4 91%, #6D28D9 91%, #6D28D9 92%, #5EEAD4 92%, #5EEAD4 93%, #6D28D9 93%, #6D28D9 94%, #5EEAD4 94%, #5EEAD4 95%, #6D28D9 95%, #6D28D9 96%, #5EEAD4 96%, #5EEAD4 97%, #6D28D9 97%, #6D28D9 98%, #5EEAD4 98%, #5EEAD4 99%, #6D28D9 99%, #6D28D9 100%)",
      "type": "color",
      "description": "candy_min45°"
    },
    "candy_45°": {
      "value": "linear-gradient(45deg, #5EEAD4 0%, #5EEAD4 1%, #6D28D9 1%, #6D28D9 2%, #5EEAD4 2%, #5EEAD4 3%, #6D28D9 3%, #6D28D9 4%, #5EEAD4 4%, #5EEAD4 5%, #6D28D9 5%, #6D28D9 6%, #5EEAD4 6%, #5EEAD4 7%, #6D28D9 7%, #6D28D9 8%, #5EEAD4 8%, #5EEAD4 9%, #6D28D9 9%, #6D28D9 10%, #5EEAD4 10%, #5EEAD4 11%, #6D28D9 11%, #6D28D9 12%, #5EEAD4 12%, #5EEAD4 13%, #6D28D9 13%, #6D28D9 14%, #5EEAD4 14%, #5EEAD4 15%, #6D28D9 15%, #6D28D9 16%, #5EEAD4 16%, #5EEAD4 17%, #6D28D9 17%, #6D28D9 18%, #5EEAD4 18%, #5EEAD4 19%, #6D28D9 19%, #6D28D9 20%, #5EEAD4 20%, #5EEAD4 21%, #6D28D9 21%, #6D28D9 22%, #5EEAD4 22%, #5EEAD4 23%, #6D28D9 23%, #6D28D9 24%, #5EEAD4 24%, #5EEAD4 25%, #6D28D9 25%, #6D28D9 26%, #5EEAD4 26%, #5EEAD4 27%, #6D28D9 27%, #6D28D9 28%, #5EEAD4 28%, #5EEAD4 29%, #6D28D9 29%, #6D28D9 30%, #5EEAD4 30%, #5EEAD4 31%, #6D28D9 31%, #6D28D9 32%, #5EEAD4 32%, #5EEAD4 33%, #6D28D9 33%, #6D28D9 34%, #5EEAD4 34%, #5EEAD4 35%, #6D28D9 35%, #6D28D9 36%, #5EEAD4 36%, #5EEAD4 37%, #6D28D9 37%, #6D28D9 38%, #5EEAD4 38%, #5EEAD4 39%, #6D28D9 39%, #6D28D9 40%, #5EEAD4 40%, #5EEAD4 41%, #6D28D9 41%, #6D28D9 42%, #5EEAD4 42%, #5EEAD4 43%, #6D28D9 43%, #6D28D9 44%, #5EEAD4 44%, #5EEAD4 45%, #6D28D9 45%, #6D28D9 46%, #5EEAD4 46%, #5EEAD4 47%, #6D28D9 47%, #6D28D9 48%, #5EEAD4 48%, #5EEAD4 49%, #6D28D9 49%, #6D28D9 50%, #5EEAD4 50%, #5EEAD4 51%, #6D28D9 51%, #6D28D9 52%, #5EEAD4 52%, #5EEAD4 53%, #6D28D9 53%, #6D28D9 54%, #5EEAD4 54%, #5EEAD4 55%, #6D28D9 55%, #6D28D9 56%, #5EEAD4 56%, #5EEAD4 57%, #6D28D9 57%, #6D28D9 58%, #5EEAD4 58%, #5EEAD4 59%, #6D28D9 59%, #6D28D9 60%, #5EEAD4 60%, #5EEAD4 61%, #6D28D9 61%, #6D28D9 62%, #5EEAD4 62%, #5EEAD4 63%, #6D28D9 63%, #6D28D9 64%, #5EEAD4 64%, #5EEAD4 65%, #6D28D9 65%, #6D28D9 66%, #5EEAD4 66%, #5EEAD4 67%, #6D28D9 67%, #6D28D9 68%, #5EEAD4 68%, #5EEAD4 69%, #6D28D9 69%, #6D28D9 70%, #5EEAD4 70%, #5EEAD4 71%, #6D28D9 71%, #6D28D9 72%, #5EEAD4 72%, #5EEAD4 73%, #6D28D9 73%, #6D28D9 74%, #5EEAD4 74%, #5EEAD4 75%, #6D28D9 75%, #6D28D9 76%, #5EEAD4 76%, #5EEAD4 77%, #6D28D9 77%, #6D28D9 78%, #5EEAD4 78%, #5EEAD4 79%, #6D28D9 79%, #6D28D9 80%, #5EEAD4 80%, #5EEAD4 81%, #6D28D9 81%, #6D28D9 82%, #5EEAD4 82%, #5EEAD4 83%, #6D28D9 83%, #6D28D9 84%, #5EEAD4 84%, #5EEAD4 85%, #6D28D9 85%, #6D28D9 86%, #5EEAD4 86%, #5EEAD4 87%, #6D28D9 87%, #6D28D9 88%, #5EEAD4 88%, #5EEAD4 89%, #6D28D9 89%, #6D28D9 90%, #5EEAD4 90%, #5EEAD4 91%, #6D28D9 91%, #6D28D9 92%, #5EEAD4 92%, #5EEAD4 93%, #6D28D9 93%, #6D28D9 94%, #5EEAD4 94%, #5EEAD4 95%, #6D28D9 95%, #6D28D9 96%, #5EEAD4 96%, #5EEAD4 97%, #6D28D9 97%, #6D28D9 98%, #5EEAD4 98%, #5EEAD4 99%, #6D28D9 99%, #6D28D9 100%)",
      "type": "color",
      "description": "candy_45°"
    },
    "candy_min60°": {
      "value": "linear-gradient(-60deg, #5EEAD4 0%, #5EEAD4 1%, #6D28D9 1%, #6D28D9 2%, #5EEAD4 2%, #5EEAD4 3%, #6D28D9 3%, #6D28D9 4%, #5EEAD4 4%, #5EEAD4 5%, #6D28D9 5%, #6D28D9 6%, #5EEAD4 6%, #5EEAD4 7%, #6D28D9 7%, #6D28D9 8%, #5EEAD4 8%, #5EEAD4 9%, #6D28D9 9%, #6D28D9 10%, #5EEAD4 10%, #5EEAD4 11%, #6D28D9 11%, #6D28D9 12%, #5EEAD4 12%, #5EEAD4 13%, #6D28D9 13%, #6D28D9 14%, #5EEAD4 14%, #5EEAD4 15%, #6D28D9 15%, #6D28D9 16%, #5EEAD4 16%, #5EEAD4 17%, #6D28D9 17%, #6D28D9 18%, #5EEAD4 18%, #5EEAD4 19%, #6D28D9 19%, #6D28D9 20%, #5EEAD4 20%, #5EEAD4 21%, #6D28D9 21%, #6D28D9 22%, #5EEAD4 22%, #5EEAD4 23%, #6D28D9 23%, #6D28D9 24%, #5EEAD4 24%, #5EEAD4 25%, #6D28D9 25%, #6D28D9 26%, #5EEAD4 26%, #5EEAD4 27%, #6D28D9 27%, #6D28D9 28%, #5EEAD4 28%, #5EEAD4 29%, #6D28D9 29%, #6D28D9 30%, #5EEAD4 30%, #5EEAD4 31%, #6D28D9 31%, #6D28D9 32%, #5EEAD4 32%, #5EEAD4 33%, #6D28D9 33%, #6D28D9 34%, #5EEAD4 34%, #5EEAD4 35%, #6D28D9 35%, #6D28D9 36%, #5EEAD4 36%, #5EEAD4 37%, #6D28D9 37%, #6D28D9 38%, #5EEAD4 38%, #5EEAD4 39%, #6D28D9 39%, #6D28D9 40%, #5EEAD4 40%, #5EEAD4 41%, #6D28D9 41%, #6D28D9 42%, #5EEAD4 42%, #5EEAD4 43%, #6D28D9 43%, #6D28D9 44%, #5EEAD4 44%, #5EEAD4 45%, #6D28D9 45%, #6D28D9 46%, #5EEAD4 46%, #5EEAD4 47%, #6D28D9 47%, #6D28D9 48%, #5EEAD4 48%, #5EEAD4 49%, #6D28D9 49%, #6D28D9 50%, #5EEAD4 50%, #5EEAD4 51%, #6D28D9 51%, #6D28D9 52%, #5EEAD4 52%, #5EEAD4 53%, #6D28D9 53%, #6D28D9 54%, #5EEAD4 54%, #5EEAD4 55%, #6D28D9 55%, #6D28D9 56%, #5EEAD4 56%, #5EEAD4 57%, #6D28D9 57%, #6D28D9 58%, #5EEAD4 58%, #5EEAD4 59%, #6D28D9 59%, #6D28D9 60%, #5EEAD4 60%, #5EEAD4 61%, #6D28D9 61%, #6D28D9 62%, #5EEAD4 62%, #5EEAD4 63%, #6D28D9 63%, #6D28D9 64%, #5EEAD4 64%, #5EEAD4 65%, #6D28D9 65%, #6D28D9 66%, #5EEAD4 66%, #5EEAD4 67%, #6D28D9 67%, #6D28D9 68%, #5EEAD4 68%, #5EEAD4 69%, #6D28D9 69%, #6D28D9 70%, #5EEAD4 70%, #5EEAD4 71%, #6D28D9 71%, #6D28D9 72%, #5EEAD4 72%, #5EEAD4 73%, #6D28D9 73%, #6D28D9 74%, #5EEAD4 74%, #5EEAD4 75%, #6D28D9 75%, #6D28D9 76%, #5EEAD4 76%, #5EEAD4 77%, #6D28D9 77%, #6D28D9 78%, #5EEAD4 78%, #5EEAD4 79%, #6D28D9 79%, #6D28D9 80%, #5EEAD4 80%, #5EEAD4 81%, #6D28D9 81%, #6D28D9 82%, #5EEAD4 82%, #5EEAD4 83%, #6D28D9 83%, #6D28D9 84%, #5EEAD4 84%, #5EEAD4 85%, #6D28D9 85%, #6D28D9 86%, #5EEAD4 86%, #5EEAD4 87%, #6D28D9 87%, #6D28D9 88%, #5EEAD4 88%, #5EEAD4 89%, #6D28D9 89%, #6D28D9 90%, #5EEAD4 90%, #5EEAD4 91%, #6D28D9 91%, #6D28D9 92%, #5EEAD4 92%, #5EEAD4 93%, #6D28D9 93%, #6D28D9 94%, #5EEAD4 94%, #5EEAD4 95%, #6D28D9 95%, #6D28D9 96%, #5EEAD4 96%, #5EEAD4 97%, #6D28D9 97%, #6D28D9 98%, #5EEAD4 98%, #5EEAD4 99%, #6D28D9 99%, #6D28D9 100%)",
      "type": "color",
      "description": "candy_min60°"
    },
    "candy_60°": {
      "value": "linear-gradient(60deg, #5EEAD4 0%, #5EEAD4 1%, #6D28D9 1%, #6D28D9 2%, #5EEAD4 2%, #5EEAD4 3%, #6D28D9 3%, #6D28D9 4%, #5EEAD4 4%, #5EEAD4 5%, #6D28D9 5%, #6D28D9 6%, #5EEAD4 6%, #5EEAD4 7%, #6D28D9 7%, #6D28D9 8%, #5EEAD4 8%, #5EEAD4 9%, #6D28D9 9%, #6D28D9 10%, #5EEAD4 10%, #5EEAD4 11%, #6D28D9 11%, #6D28D9 12%, #5EEAD4 12%, #5EEAD4 13%, #6D28D9 13%, #6D28D9 14%, #5EEAD4 14%, #5EEAD4 15%, #6D28D9 15%, #6D28D9 16%, #5EEAD4 16%, #5EEAD4 17%, #6D28D9 17%, #6D28D9 18%, #5EEAD4 18%, #5EEAD4 19%, #6D28D9 19%, #6D28D9 20%, #5EEAD4 20%, #5EEAD4 21%, #6D28D9 21%, #6D28D9 22%, #5EEAD4 22%, #5EEAD4 23%, #6D28D9 23%, #6D28D9 24%, #5EEAD4 24%, #5EEAD4 25%, #6D28D9 25%, #6D28D9 26%, #5EEAD4 26%, #5EEAD4 27%, #6D28D9 27%, #6D28D9 28%, #5EEAD4 28%, #5EEAD4 29%, #6D28D9 29%, #6D28D9 30%, #5EEAD4 30%, #5EEAD4 31%, #6D28D9 31%, #6D28D9 32%, #5EEAD4 32%, #5EEAD4 33%, #6D28D9 33%, #6D28D9 34%, #5EEAD4 34%, #5EEAD4 35%, #6D28D9 35%, #6D28D9 36%, #5EEAD4 36%, #5EEAD4 37%, #6D28D9 37%, #6D28D9 38%, #5EEAD4 38%, #5EEAD4 39%, #6D28D9 39%, #6D28D9 40%, #5EEAD4 40%, #5EEAD4 41%, #6D28D9 41%, #6D28D9 42%, #5EEAD4 42%, #5EEAD4 43%, #6D28D9 43%, #6D28D9 44%, #5EEAD4 44%, #5EEAD4 45%, #6D28D9 45%, #6D28D9 46%, #5EEAD4 46%, #5EEAD4 47%, #6D28D9 47%, #6D28D9 48%, #5EEAD4 48%, #5EEAD4 49%, #6D28D9 49%, #6D28D9 50%, #5EEAD4 50%, #5EEAD4 51%, #6D28D9 51%, #6D28D9 52%, #5EEAD4 52%, #5EEAD4 53%, #6D28D9 53%, #6D28D9 54%, #5EEAD4 54%, #5EEAD4 55%, #6D28D9 55%, #6D28D9 56%, #5EEAD4 56%, #5EEAD4 57%, #6D28D9 57%, #6D28D9 58%, #5EEAD4 58%, #5EEAD4 59%, #6D28D9 59%, #6D28D9 60%, #5EEAD4 60%, #5EEAD4 61%, #6D28D9 61%, #6D28D9 62%, #5EEAD4 62%, #5EEAD4 63%, #6D28D9 63%, #6D28D9 64%, #5EEAD4 64%, #5EEAD4 65%, #6D28D9 65%, #6D28D9 66%, #5EEAD4 66%, #5EEAD4 67%, #6D28D9 67%, #6D28D9 68%, #5EEAD4 68%, #5EEAD4 69%, #6D28D9 69%, #6D28D9 70%, #5EEAD4 70%, #5EEAD4 71%, #6D28D9 71%, #6D28D9 72%, #5EEAD4 72%, #5EEAD4 73%, #6D28D9 73%, #6D28D9 74%, #5EEAD4 74%, #5EEAD4 75%, #6D28D9 75%, #6D28D9 76%, #5EEAD4 76%, #5EEAD4 77%, #6D28D9 77%, #6D28D9 78%, #5EEAD4 78%, #5EEAD4 79%, #6D28D9 79%, #6D28D9 80%, #5EEAD4 80%, #5EEAD4 81%, #6D28D9 81%, #6D28D9 82%, #5EEAD4 82%, #5EEAD4 83%, #6D28D9 83%, #6D28D9 84%, #5EEAD4 84%, #5EEAD4 85%, #6D28D9 85%, #6D28D9 86%, #5EEAD4 86%, #5EEAD4 87%, #6D28D9 87%, #6D28D9 88%, #5EEAD4 88%, #5EEAD4 89%, #6D28D9 89%, #6D28D9 90%, #5EEAD4 90%, #5EEAD4 91%, #6D28D9 91%, #6D28D9 92%, #5EEAD4 92%, #5EEAD4 93%, #6D28D9 93%, #6D28D9 94%, #5EEAD4 94%, #5EEAD4 95%, #6D28D9 95%, #6D28D9 96%, #5EEAD4 96%, #5EEAD4 97%, #6D28D9 97%, #6D28D9 98%, #5EEAD4 98%, #5EEAD4 99%, #6D28D9 99%, #6D28D9 100%)",
      "type": "color",
      "description": "candy_60°"
    },
    "candy_min75°": {
      "value": "linear-gradient(-75deg, #5EEAD4 0%, #5EEAD4 1%, #6D28D9 1%, #6D28D9 2%, #5EEAD4 2%, #5EEAD4 3%, #6D28D9 3%, #6D28D9 4%, #5EEAD4 4%, #5EEAD4 5%, #6D28D9 5%, #6D28D9 6%, #5EEAD4 6%, #5EEAD4 7%, #6D28D9 7%, #6D28D9 8%, #5EEAD4 8%, #5EEAD4 9%, #6D28D9 9%, #6D28D9 10%, #5EEAD4 10%, #5EEAD4 11%, #6D28D9 11%, #6D28D9 12%, #5EEAD4 12%, #5EEAD4 13%, #6D28D9 13%, #6D28D9 14%, #5EEAD4 14%, #5EEAD4 15%, #6D28D9 15%, #6D28D9 16%, #5EEAD4 16%, #5EEAD4 17%, #6D28D9 17%, #6D28D9 18%, #5EEAD4 18%, #5EEAD4 19%, #6D28D9 19%, #6D28D9 20%, #5EEAD4 20%, #5EEAD4 21%, #6D28D9 21%, #6D28D9 22%, #5EEAD4 22%, #5EEAD4 23%, #6D28D9 23%, #6D28D9 24%, #5EEAD4 24%, #5EEAD4 25%, #6D28D9 25%, #6D28D9 26%, #5EEAD4 26%, #5EEAD4 27%, #6D28D9 27%, #6D28D9 28%, #5EEAD4 28%, #5EEAD4 29%, #6D28D9 29%, #6D28D9 30%, #5EEAD4 30%, #5EEAD4 31%, #6D28D9 31%, #6D28D9 32%, #5EEAD4 32%, #5EEAD4 33%, #6D28D9 33%, #6D28D9 34%, #5EEAD4 34%, #5EEAD4 35%, #6D28D9 35%, #6D28D9 36%, #5EEAD4 36%, #5EEAD4 37%, #6D28D9 37%, #6D28D9 38%, #5EEAD4 38%, #5EEAD4 39%, #6D28D9 39%, #6D28D9 40%, #5EEAD4 40%, #5EEAD4 41%, #6D28D9 41%, #6D28D9 42%, #5EEAD4 42%, #5EEAD4 43%, #6D28D9 43%, #6D28D9 44%, #5EEAD4 44%, #5EEAD4 45%, #6D28D9 45%, #6D28D9 46%, #5EEAD4 46%, #5EEAD4 47%, #6D28D9 47%, #6D28D9 48%, #5EEAD4 48%, #5EEAD4 49%, #6D28D9 49%, #6D28D9 50%, #5EEAD4 50%, #5EEAD4 51%, #6D28D9 51%, #6D28D9 52%, #5EEAD4 52%, #5EEAD4 53%, #6D28D9 53%, #6D28D9 54%, #5EEAD4 54%, #5EEAD4 55%, #6D28D9 55%, #6D28D9 56%, #5EEAD4 56%, #5EEAD4 57%, #6D28D9 57%, #6D28D9 58%, #5EEAD4 58%, #5EEAD4 59%, #6D28D9 59%, #6D28D9 60%, #5EEAD4 60%, #5EEAD4 61%, #6D28D9 61%, #6D28D9 62%, #5EEAD4 62%, #5EEAD4 63%, #6D28D9 63%, #6D28D9 64%, #5EEAD4 64%, #5EEAD4 65%, #6D28D9 65%, #6D28D9 66%, #5EEAD4 66%, #5EEAD4 67%, #6D28D9 67%, #6D28D9 68%, #5EEAD4 68%, #5EEAD4 69%, #6D28D9 69%, #6D28D9 70%, #5EEAD4 70%, #5EEAD4 71%, #6D28D9 71%, #6D28D9 72%, #5EEAD4 72%, #5EEAD4 73%, #6D28D9 73%, #6D28D9 74%, #5EEAD4 74%, #5EEAD4 75%, #6D28D9 75%, #6D28D9 76%, #5EEAD4 76%, #5EEAD4 77%, #6D28D9 77%, #6D28D9 78%, #5EEAD4 78%, #5EEAD4 79%, #6D28D9 79%, #6D28D9 80%, #5EEAD4 80%, #5EEAD4 81%, #6D28D9 81%, #6D28D9 82%, #5EEAD4 82%, #5EEAD4 83%, #6D28D9 83%, #6D28D9 84%, #5EEAD4 84%, #5EEAD4 85%, #6D28D9 85%, #6D28D9 86%, #5EEAD4 86%, #5EEAD4 87%, #6D28D9 87%, #6D28D9 88%, #5EEAD4 88%, #5EEAD4 89%, #6D28D9 89%, #6D28D9 90%, #5EEAD4 90%, #5EEAD4 91%, #6D28D9 91%, #6D28D9 92%, #5EEAD4 92%, #5EEAD4 93%, #6D28D9 93%, #6D28D9 94%, #5EEAD4 94%, #5EEAD4 95%, #6D28D9 95%, #6D28D9 96%, #5EEAD4 96%, #5EEAD4 97%, #6D28D9 97%, #6D28D9 98%, #5EEAD4 98%, #5EEAD4 99%, #6D28D9 99%, #6D28D9 100%)",
      "type": "color",
      "description": "candy_min75°"
    },
    "candy_75°": {
      "value": "linear-gradient(75deg, #5EEAD4 0%, #5EEAD4 1%, #6D28D9 1%, #6D28D9 2%, #5EEAD4 2%, #5EEAD4 3%, #6D28D9 3%, #6D28D9 4%, #5EEAD4 4%, #5EEAD4 5%, #6D28D9 5%, #6D28D9 6%, #5EEAD4 6%, #5EEAD4 7%, #6D28D9 7%, #6D28D9 8%, #5EEAD4 8%, #5EEAD4 9%, #6D28D9 9%, #6D28D9 10%, #5EEAD4 10%, #5EEAD4 11%, #6D28D9 11%, #6D28D9 12%, #5EEAD4 12%, #5EEAD4 13%, #6D28D9 13%, #6D28D9 14%, #5EEAD4 14%, #5EEAD4 15%, #6D28D9 15%, #6D28D9 16%, #5EEAD4 16%, #5EEAD4 17%, #6D28D9 17%, #6D28D9 18%, #5EEAD4 18%, #5EEAD4 19%, #6D28D9 19%, #6D28D9 20%, #5EEAD4 20%, #5EEAD4 21%, #6D28D9 21%, #6D28D9 22%, #5EEAD4 22%, #5EEAD4 23%, #6D28D9 23%, #6D28D9 24%, #5EEAD4 24%, #5EEAD4 25%, #6D28D9 25%, #6D28D9 26%, #5EEAD4 26%, #5EEAD4 27%, #6D28D9 27%, #6D28D9 28%, #5EEAD4 28%, #5EEAD4 29%, #6D28D9 29%, #6D28D9 30%, #5EEAD4 30%, #5EEAD4 31%, #6D28D9 31%, #6D28D9 32%, #5EEAD4 32%, #5EEAD4 33%, #6D28D9 33%, #6D28D9 34%, #5EEAD4 34%, #5EEAD4 35%, #6D28D9 35%, #6D28D9 36%, #5EEAD4 36%, #5EEAD4 37%, #6D28D9 37%, #6D28D9 38%, #5EEAD4 38%, #5EEAD4 39%, #6D28D9 39%, #6D28D9 40%, #5EEAD4 40%, #5EEAD4 41%, #6D28D9 41%, #6D28D9 42%, #5EEAD4 42%, #5EEAD4 43%, #6D28D9 43%, #6D28D9 44%, #5EEAD4 44%, #5EEAD4 45%, #6D28D9 45%, #6D28D9 46%, #5EEAD4 46%, #5EEAD4 47%, #6D28D9 47%, #6D28D9 48%, #5EEAD4 48%, #5EEAD4 49%, #6D28D9 49%, #6D28D9 50%, #5EEAD4 50%, #5EEAD4 51%, #6D28D9 51%, #6D28D9 52%, #5EEAD4 52%, #5EEAD4 53%, #6D28D9 53%, #6D28D9 54%, #5EEAD4 54%, #5EEAD4 55%, #6D28D9 55%, #6D28D9 56%, #5EEAD4 56%, #5EEAD4 57%, #6D28D9 57%, #6D28D9 58%, #5EEAD4 58%, #5EEAD4 59%, #6D28D9 59%, #6D28D9 60%, #5EEAD4 60%, #5EEAD4 61%, #6D28D9 61%, #6D28D9 62%, #5EEAD4 62%, #5EEAD4 63%, #6D28D9 63%, #6D28D9 64%, #5EEAD4 64%, #5EEAD4 65%, #6D28D9 65%, #6D28D9 66%, #5EEAD4 66%, #5EEAD4 67%, #6D28D9 67%, #6D28D9 68%, #5EEAD4 68%, #5EEAD4 69%, #6D28D9 69%, #6D28D9 70%, #5EEAD4 70%, #5EEAD4 71%, #6D28D9 71%, #6D28D9 72%, #5EEAD4 72%, #5EEAD4 73%, #6D28D9 73%, #6D28D9 74%, #5EEAD4 74%, #5EEAD4 75%, #6D28D9 75%, #6D28D9 76%, #5EEAD4 76%, #5EEAD4 77%, #6D28D9 77%, #6D28D9 78%, #5EEAD4 78%, #5EEAD4 79%, #6D28D9 79%, #6D28D9 80%, #5EEAD4 80%, #5EEAD4 81%, #6D28D9 81%, #6D28D9 82%, #5EEAD4 82%, #5EEAD4 83%, #6D28D9 83%, #6D28D9 84%, #5EEAD4 84%, #5EEAD4 85%, #6D28D9 85%, #6D28D9 86%, #5EEAD4 86%, #5EEAD4 87%, #6D28D9 87%, #6D28D9 88%, #5EEAD4 88%, #5EEAD4 89%, #6D28D9 89%, #6D28D9 90%, #5EEAD4 90%, #5EEAD4 91%, #6D28D9 91%, #6D28D9 92%, #5EEAD4 92%, #5EEAD4 93%, #6D28D9 93%, #6D28D9 94%, #5EEAD4 94%, #5EEAD4 95%, #6D28D9 95%, #6D28D9 96%, #5EEAD4 96%, #5EEAD4 97%, #6D28D9 97%, #6D28D9 98%, #5EEAD4 98%, #5EEAD4 99%, #6D28D9 99%, #6D28D9 100%)",
      "type": "color",
      "description": "candy_75°"
    },
    "candy_0°": {
      "value": "linear-gradient(0deg, #5EEAD4 0%, #5EEAD4 1%, #6D28D9 1%, #6D28D9 2%, #5EEAD4 2%, #5EEAD4 3%, #6D28D9 3%, #6D28D9 4%, #5EEAD4 4%, #5EEAD4 5%, #6D28D9 5%, #6D28D9 6%, #5EEAD4 6%, #5EEAD4 7%, #6D28D9 7%, #6D28D9 8%, #5EEAD4 8%, #5EEAD4 9%, #6D28D9 9%, #6D28D9 10%, #5EEAD4 10%, #5EEAD4 11%, #6D28D9 11%, #6D28D9 12%, #5EEAD4 12%, #5EEAD4 13%, #6D28D9 13%, #6D28D9 14%, #5EEAD4 14%, #5EEAD4 15%, #6D28D9 15%, #6D28D9 16%, #5EEAD4 16%, #5EEAD4 17%, #6D28D9 17%, #6D28D9 18%, #5EEAD4 18%, #5EEAD4 19%, #6D28D9 19%, #6D28D9 20%, #5EEAD4 20%, #5EEAD4 21%, #6D28D9 21%, #6D28D9 22%, #5EEAD4 22%, #5EEAD4 23%, #6D28D9 23%, #6D28D9 24%, #5EEAD4 24%, #5EEAD4 25%, #6D28D9 25%, #6D28D9 26%, #5EEAD4 26%, #5EEAD4 27%, #6D28D9 27%, #6D28D9 28%, #5EEAD4 28%, #5EEAD4 29%, #6D28D9 29%, #6D28D9 30%, #5EEAD4 30%, #5EEAD4 31%, #6D28D9 31%, #6D28D9 32%, #5EEAD4 32%, #5EEAD4 33%, #6D28D9 33%, #6D28D9 34%, #5EEAD4 34%, #5EEAD4 35%, #6D28D9 35%, #6D28D9 36%, #5EEAD4 36%, #5EEAD4 37%, #6D28D9 37%, #6D28D9 38%, #5EEAD4 38%, #5EEAD4 39%, #6D28D9 39%, #6D28D9 40%, #5EEAD4 40%, #5EEAD4 41%, #6D28D9 41%, #6D28D9 42%, #5EEAD4 42%, #5EEAD4 43%, #6D28D9 43%, #6D28D9 44%, #5EEAD4 44%, #5EEAD4 45%, #6D28D9 45%, #6D28D9 46%, #5EEAD4 46%, #5EEAD4 47%, #6D28D9 47%, #6D28D9 48%, #5EEAD4 48%, #5EEAD4 49%, #6D28D9 49%, #6D28D9 50%, #5EEAD4 50%, #5EEAD4 51%, #6D28D9 51%, #6D28D9 52%, #5EEAD4 52%, #5EEAD4 53%, #6D28D9 53%, #6D28D9 54%, #5EEAD4 54%, #5EEAD4 55%, #6D28D9 55%, #6D28D9 56%, #5EEAD4 56%, #5EEAD4 57%, #6D28D9 57%, #6D28D9 58%, #5EEAD4 58%, #5EEAD4 59%, #6D28D9 59%, #6D28D9 60%, #5EEAD4 60%, #5EEAD4 61%, #6D28D9 61%, #6D28D9 62%, #5EEAD4 62%, #5EEAD4 63%, #6D28D9 63%, #6D28D9 64%, #5EEAD4 64%, #5EEAD4 65%, #6D28D9 65%, #6D28D9 66%, #5EEAD4 66%, #5EEAD4 67%, #6D28D9 67%, #6D28D9 68%, #5EEAD4 68%, #5EEAD4 69%, #6D28D9 69%, #6D28D9 70%, #5EEAD4 70%, #5EEAD4 71%, #6D28D9 71%, #6D28D9 72%, #5EEAD4 72%, #5EEAD4 73%, #6D28D9 73%, #6D28D9 74%, #5EEAD4 74%, #5EEAD4 75%, #6D28D9 75%, #6D28D9 76%, #5EEAD4 76%, #5EEAD4 77%, #6D28D9 77%, #6D28D9 78%, #5EEAD4 78%, #5EEAD4 79%, #6D28D9 79%, #6D28D9 80%, #5EEAD4 80%, #5EEAD4 81%, #6D28D9 81%, #6D28D9 82%, #5EEAD4 82%, #5EEAD4 83%, #6D28D9 83%, #6D28D9 84%, #5EEAD4 84%, #5EEAD4 85%, #6D28D9 85%, #6D28D9 86%, #5EEAD4 86%, #5EEAD4 87%, #6D28D9 87%, #6D28D9 88%, #5EEAD4 88%, #5EEAD4 89%, #6D28D9 89%, #6D28D9 90%, #5EEAD4 90%, #5EEAD4 91%, #6D28D9 91%, #6D28D9 92%, #5EEAD4 92%, #5EEAD4 93%, #6D28D9 93%, #6D28D9 94%, #5EEAD4 94%, #5EEAD4 95%, #6D28D9 95%, #6D28D9 96%, #5EEAD4 96%, #5EEAD4 97%, #6D28D9 97%, #6D28D9 98%, #5EEAD4 98%, #5EEAD4 99%, #6D28D9 99%, #6D28D9 100%)",
      "type": "color",
      "description": "candy_0°"
    },
    "candy_90°": {
      "value": "linear-gradient(90deg, #5EEAD4 0%, #5EEAD4 1%, #6D28D9 1%, #6D28D9 2%, #5EEAD4 2%, #5EEAD4 3%, #6D28D9 3%, #6D28D9 4%, #5EEAD4 4%, #5EEAD4 5%, #6D28D9 5%, #6D28D9 6%, #5EEAD4 6%, #5EEAD4 7%, #6D28D9 7%, #6D28D9 8%, #5EEAD4 8%, #5EEAD4 9%, #6D28D9 9%, #6D28D9 10%, #5EEAD4 10%, #5EEAD4 11%, #6D28D9 11%, #6D28D9 12%, #5EEAD4 12%, #5EEAD4 13%, #6D28D9 13%, #6D28D9 14%, #5EEAD4 14%, #5EEAD4 15%, #6D28D9 15%, #6D28D9 16%, #5EEAD4 16%, #5EEAD4 17%, #6D28D9 17%, #6D28D9 18%, #5EEAD4 18%, #5EEAD4 19%, #6D28D9 19%, #6D28D9 20%, #5EEAD4 20%, #5EEAD4 21%, #6D28D9 21%, #6D28D9 22%, #5EEAD4 22%, #5EEAD4 23%, #6D28D9 23%, #6D28D9 24%, #5EEAD4 24%, #5EEAD4 25%, #6D28D9 25%, #6D28D9 26%, #5EEAD4 26%, #5EEAD4 27%, #6D28D9 27%, #6D28D9 28%, #5EEAD4 28%, #5EEAD4 29%, #6D28D9 29%, #6D28D9 30%, #5EEAD4 30%, #5EEAD4 31%, #6D28D9 31%, #6D28D9 32%, #5EEAD4 32%, #5EEAD4 33%, #6D28D9 33%, #6D28D9 34%, #5EEAD4 34%, #5EEAD4 35%, #6D28D9 35%, #6D28D9 36%, #5EEAD4 36%, #5EEAD4 37%, #6D28D9 37%, #6D28D9 38%, #5EEAD4 38%, #5EEAD4 39%, #6D28D9 39%, #6D28D9 40%, #5EEAD4 40%, #5EEAD4 41%, #6D28D9 41%, #6D28D9 42%, #5EEAD4 42%, #5EEAD4 43%, #6D28D9 43%, #6D28D9 44%, #5EEAD4 44%, #5EEAD4 45%, #6D28D9 45%, #6D28D9 46%, #5EEAD4 46%, #5EEAD4 47%, #6D28D9 47%, #6D28D9 48%, #5EEAD4 48%, #5EEAD4 49%, #6D28D9 49%, #6D28D9 50%, #5EEAD4 50%, #5EEAD4 51%, #6D28D9 51%, #6D28D9 52%, #5EEAD4 52%, #5EEAD4 53%, #6D28D9 53%, #6D28D9 54%, #5EEAD4 54%, #5EEAD4 55%, #6D28D9 55%, #6D28D9 56%, #5EEAD4 56%, #5EEAD4 57%, #6D28D9 57%, #6D28D9 58%, #5EEAD4 58%, #5EEAD4 59%, #6D28D9 59%, #6D28D9 60%, #5EEAD4 60%, #5EEAD4 61%, #6D28D9 61%, #6D28D9 62%, #5EEAD4 62%, #5EEAD4 63%, #6D28D9 63%, #6D28D9 64%, #5EEAD4 64%, #5EEAD4 65%, #6D28D9 65%, #6D28D9 66%, #5EEAD4 66%, #5EEAD4 67%, #6D28D9 67%, #6D28D9 68%, #5EEAD4 68%, #5EEAD4 69%, #6D28D9 69%, #6D28D9 70%, #5EEAD4 70%, #5EEAD4 71%, #6D28D9 71%, #6D28D9 72%, #5EEAD4 72%, #5EEAD4 73%, #6D28D9 73%, #6D28D9 74%, #5EEAD4 74%, #5EEAD4 75%, #6D28D9 75%, #6D28D9 76%, #5EEAD4 76%, #5EEAD4 77%, #6D28D9 77%, #6D28D9 78%, #5EEAD4 78%, #5EEAD4 79%, #6D28D9 79%, #6D28D9 80%, #5EEAD4 80%, #5EEAD4 81%, #6D28D9 81%, #6D28D9 82%, #5EEAD4 82%, #5EEAD4 83%, #6D28D9 83%, #6D28D9 84%, #5EEAD4 84%, #5EEAD4 85%, #6D28D9 85%, #6D28D9 86%, #5EEAD4 86%, #5EEAD4 87%, #6D28D9 87%, #6D28D9 88%, #5EEAD4 88%, #5EEAD4 89%, #6D28D9 89%, #6D28D9 90%, #5EEAD4 90%, #5EEAD4 91%, #6D28D9 91%, #6D28D9 92%, #5EEAD4 92%, #5EEAD4 93%, #6D28D9 93%, #6D28D9 94%, #5EEAD4 94%, #5EEAD4 95%, #6D28D9 95%, #6D28D9 96%, #5EEAD4 96%, #5EEAD4 97%, #6D28D9 97%, #6D28D9 98%, #5EEAD4 98%, #5EEAD4 99%, #6D28D9 99%, #6D28D9 100%)",
      "type": "color",
      "description": "candy_90°"
    },
    "stripe_min45°": {
      "value": "linear-gradient(-45deg, #5EEAD4 0%, #5EEAD4 1%, #6D28D9 1%, #6D28D9 5%, #5EEAD4 5%, #5EEAD4 6%, #6D28D9 6%, #6D28D9 10%, #5EEAD4 10%, #5EEAD4 11%, #6D28D9 11%, #6D28D9 15%, #5EEAD4 15%, #5EEAD4 16%, #6D28D9 16%, #6D28D9 20%, #5EEAD4 20%, #5EEAD4 21%, #6D28D9 21%, #6D28D9 25%, #5EEAD4 25%, #5EEAD4 26%, #6D28D9 26%, #6D28D9 30%, #5EEAD4 30%, #5EEAD4 31%, #6D28D9 31%, #6D28D9 35%, #5EEAD4 35%, #5EEAD4 36%, #6D28D9 36%, #6D28D9 40%, #5EEAD4 40%, #5EEAD4 41%, #6D28D9 41%, #6D28D9 45%, #5EEAD4 45%, #5EEAD4 46%, #6D28D9 46%, #6D28D9 50%, #5EEAD4 50%, #5EEAD4 51%, #6D28D9 51%, #6D28D9 55%, #5EEAD4 55%, #5EEAD4 56%, #6D28D9 56%, #6D28D9 60%, #5EEAD4 60%, #5EEAD4 61%, #6D28D9 61%, #6D28D9 65%, #5EEAD4 65%, #5EEAD4 66%, #6D28D9 66%, #6D28D9 70%, #5EEAD4 70%, #5EEAD4 71%, #6D28D9 71%, #6D28D9 75%, #5EEAD4 75%, #5EEAD4 76%, #6D28D9 76%, #6D28D9 80%, #5EEAD4 80%, #5EEAD4 81%, #6D28D9 81%, #6D28D9 85%, #5EEAD4 85%, #5EEAD4 86%, #6D28D9 86%, #6D28D9 90%, #5EEAD4 90%, #5EEAD4 91%, #6D28D9 91%, #6D28D9 95%, #5EEAD4 95%, #5EEAD4 96%, #6D28D9 96%, #6D28D9 100%)",
      "type": "color",
      "description": "stripe_min45°"
    },
    "stripe_45°": {
      "value": "linear-gradient(45deg, #5EEAD4 0%, #5EEAD4 1%, #6D28D9 1%, #6D28D9 5%, #5EEAD4 5%, #5EEAD4 6%, #6D28D9 6%, #6D28D9 10%, #5EEAD4 10%, #5EEAD4 11%, #6D28D9 11%, #6D28D9 15%, #5EEAD4 15%, #5EEAD4 16%, #6D28D9 16%, #6D28D9 20%, #5EEAD4 20%, #5EEAD4 21%, #6D28D9 21%, #6D28D9 25%, #5EEAD4 25%, #5EEAD4 26%, #6D28D9 26%, #6D28D9 30%, #5EEAD4 30%, #5EEAD4 31%, #6D28D9 31%, #6D28D9 35%, #5EEAD4 35%, #5EEAD4 36%, #6D28D9 36%, #6D28D9 40%, #5EEAD4 40%, #5EEAD4 41%, #6D28D9 41%, #6D28D9 45%, #5EEAD4 45%, #5EEAD4 46%, #6D28D9 46%, #6D28D9 50%, #5EEAD4 50%, #5EEAD4 51%, #6D28D9 51%, #6D28D9 55%, #5EEAD4 55%, #5EEAD4 56%, #6D28D9 56%, #6D28D9 60%, #5EEAD4 60%, #5EEAD4 61%, #6D28D9 61%, #6D28D9 65%, #5EEAD4 65%, #5EEAD4 66%, #6D28D9 66%, #6D28D9 70%, #5EEAD4 70%, #5EEAD4 71%, #6D28D9 71%, #6D28D9 75%, #5EEAD4 75%, #5EEAD4 76%, #6D28D9 76%, #6D28D9 80%, #5EEAD4 80%, #5EEAD4 81%, #6D28D9 81%, #6D28D9 85%, #5EEAD4 85%, #5EEAD4 86%, #6D28D9 86%, #6D28D9 90%, #5EEAD4 90%, #5EEAD4 91%, #6D28D9 91%, #6D28D9 95%, #5EEAD4 95%, #5EEAD4 96%, #6D28D9 96%, #6D28D9 100%)",
      "type": "color",
      "description": "stripe_45°"
    },
    "stripe_min60°": {
      "value": "linear-gradient(-60deg, #5EEAD4 0%, #5EEAD4 1%, #6D28D9 1%, #6D28D9 5%, #5EEAD4 5%, #5EEAD4 6%, #6D28D9 6%, #6D28D9 10%, #5EEAD4 10%, #5EEAD4 11%, #6D28D9 11%, #6D28D9 15%, #5EEAD4 15%, #5EEAD4 16%, #6D28D9 16%, #6D28D9 20%, #5EEAD4 20%, #5EEAD4 21%, #6D28D9 21%, #6D28D9 25%, #5EEAD4 25%, #5EEAD4 26%, #6D28D9 26%, #6D28D9 30%, #5EEAD4 30%, #5EEAD4 31%, #6D28D9 31%, #6D28D9 35%, #5EEAD4 35%, #5EEAD4 36%, #6D28D9 36%, #6D28D9 40%, #5EEAD4 40%, #5EEAD4 41%, #6D28D9 41%, #6D28D9 45%, #5EEAD4 45%, #5EEAD4 46%, #6D28D9 46%, #6D28D9 50%, #5EEAD4 50%, #5EEAD4 51%, #6D28D9 51%, #6D28D9 55%, #5EEAD4 55%, #5EEAD4 56%, #6D28D9 56%, #6D28D9 60%, #5EEAD4 60%, #5EEAD4 61%, #6D28D9 61%, #6D28D9 65%, #5EEAD4 65%, #5EEAD4 66%, #6D28D9 66%, #6D28D9 70%, #5EEAD4 70%, #5EEAD4 71%, #6D28D9 71%, #6D28D9 75%, #5EEAD4 75%, #5EEAD4 76%, #6D28D9 76%, #6D28D9 80%, #5EEAD4 80%, #5EEAD4 81%, #6D28D9 81%, #6D28D9 85%, #5EEAD4 85%, #5EEAD4 86%, #6D28D9 86%, #6D28D9 90%, #5EEAD4 90%, #5EEAD4 91%, #6D28D9 91%, #6D28D9 95%, #5EEAD4 95%, #5EEAD4 96%, #6D28D9 96%, #6D28D9 100%)",
      "type": "color",
      "description": "stripe_min60°"
    },
    "stripe_60°": {
      "value": "linear-gradient(60deg, #5EEAD4 0%, #5EEAD4 1%, #6D28D9 1%, #6D28D9 5%, #5EEAD4 5%, #5EEAD4 6%, #6D28D9 6%, #6D28D9 10%, #5EEAD4 10%, #5EEAD4 11%, #6D28D9 11%, #6D28D9 15%, #5EEAD4 15%, #5EEAD4 16%, #6D28D9 16%, #6D28D9 20%, #5EEAD4 20%, #5EEAD4 21%, #6D28D9 21%, #6D28D9 25%, #5EEAD4 25%, #5EEAD4 26%, #6D28D9 26%, #6D28D9 30%, #5EEAD4 30%, #5EEAD4 31%, #6D28D9 31%, #6D28D9 35%, #5EEAD4 35%, #5EEAD4 36%, #6D28D9 36%, #6D28D9 40%, #5EEAD4 40%, #5EEAD4 41%, #6D28D9 41%, #6D28D9 45%, #5EEAD4 45%, #5EEAD4 46%, #6D28D9 46%, #6D28D9 50%, #5EEAD4 50%, #5EEAD4 51%, #6D28D9 51%, #6D28D9 55%, #5EEAD4 55%, #5EEAD4 56%, #6D28D9 56%, #6D28D9 60%, #5EEAD4 60%, #5EEAD4 61%, #6D28D9 61%, #6D28D9 65%, #5EEAD4 65%, #5EEAD4 66%, #6D28D9 66%, #6D28D9 70%, #5EEAD4 70%, #5EEAD4 71%, #6D28D9 71%, #6D28D9 75%, #5EEAD4 75%, #5EEAD4 76%, #6D28D9 76%, #6D28D9 80%, #5EEAD4 80%, #5EEAD4 81%, #6D28D9 81%, #6D28D9 85%, #5EEAD4 85%, #5EEAD4 86%, #6D28D9 86%, #6D28D9 90%, #5EEAD4 90%, #5EEAD4 91%, #6D28D9 91%, #6D28D9 95%, #5EEAD4 95%, #5EEAD4 96%, #6D28D9 96%, #6D28D9 100%)",
      "type": "color",
      "description": "stripe_60°"
    },
    "stripe_min75°": {
      "value": "linear-gradient(-75deg, #5EEAD4 0%, #5EEAD4 1%, #6D28D9 1%, #6D28D9 5%, #5EEAD4 5%, #5EEAD4 6%, #6D28D9 6%, #6D28D9 10%, #5EEAD4 10%, #5EEAD4 11%, #6D28D9 11%, #6D28D9 15%, #5EEAD4 15%, #5EEAD4 16%, #6D28D9 16%, #6D28D9 20%, #5EEAD4 20%, #5EEAD4 21%, #6D28D9 21%, #6D28D9 25%, #5EEAD4 25%, #5EEAD4 26%, #6D28D9 26%, #6D28D9 30%, #5EEAD4 30%, #5EEAD4 31%, #6D28D9 31%, #6D28D9 35%, #5EEAD4 35%, #5EEAD4 36%, #6D28D9 36%, #6D28D9 40%, #5EEAD4 40%, #5EEAD4 41%, #6D28D9 41%, #6D28D9 45%, #5EEAD4 45%, #5EEAD4 46%, #6D28D9 46%, #6D28D9 50%, #5EEAD4 50%, #5EEAD4 51%, #6D28D9 51%, #6D28D9 55%, #5EEAD4 55%, #5EEAD4 56%, #6D28D9 56%, #6D28D9 60%, #5EEAD4 60%, #5EEAD4 61%, #6D28D9 61%, #6D28D9 65%, #5EEAD4 65%, #5EEAD4 66%, #6D28D9 66%, #6D28D9 70%, #5EEAD4 70%, #5EEAD4 71%, #6D28D9 71%, #6D28D9 75%, #5EEAD4 75%, #5EEAD4 76%, #6D28D9 76%, #6D28D9 80%, #5EEAD4 80%, #5EEAD4 81%, #6D28D9 81%, #6D28D9 85%, #5EEAD4 85%, #5EEAD4 86%, #6D28D9 86%, #6D28D9 90%, #5EEAD4 90%, #5EEAD4 91%, #6D28D9 91%, #6D28D9 95%, #5EEAD4 95%, #5EEAD4 96%, #6D28D9 96%, #6D28D9 100%)",
      "type": "color",
      "description": "stripe_min75°"
    },
    "stripe_75°": {
      "value": "linear-gradient(75deg, #5EEAD4 0%, #5EEAD4 1%, #6D28D9 1%, #6D28D9 5%, #5EEAD4 5%, #5EEAD4 6%, #6D28D9 6%, #6D28D9 10%, #5EEAD4 10%, #5EEAD4 11%, #6D28D9 11%, #6D28D9 15%, #5EEAD4 15%, #5EEAD4 16%, #6D28D9 16%, #6D28D9 20%, #5EEAD4 20%, #5EEAD4 21%, #6D28D9 21%, #6D28D9 25%, #5EEAD4 25%, #5EEAD4 26%, #6D28D9 26%, #6D28D9 30%, #5EEAD4 30%, #5EEAD4 31%, #6D28D9 31%, #6D28D9 35%, #5EEAD4 35%, #5EEAD4 36%, #6D28D9 36%, #6D28D9 40%, #5EEAD4 40%, #5EEAD4 41%, #6D28D9 41%, #6D28D9 45%, #5EEAD4 45%, #5EEAD4 46%, #6D28D9 46%, #6D28D9 50%, #5EEAD4 50%, #5EEAD4 51%, #6D28D9 51%, #6D28D9 55%, #5EEAD4 55%, #5EEAD4 56%, #6D28D9 56%, #6D28D9 60%, #5EEAD4 60%, #5EEAD4 61%, #6D28D9 61%, #6D28D9 65%, #5EEAD4 65%, #5EEAD4 66%, #6D28D9 66%, #6D28D9 70%, #5EEAD4 70%, #5EEAD4 71%, #6D28D9 71%, #6D28D9 75%, #5EEAD4 75%, #5EEAD4 76%, #6D28D9 76%, #6D28D9 80%, #5EEAD4 80%, #5EEAD4 81%, #6D28D9 81%, #6D28D9 85%, #5EEAD4 85%, #5EEAD4 86%, #6D28D9 86%, #6D28D9 90%, #5EEAD4 90%, #5EEAD4 91%, #6D28D9 91%, #6D28D9 95%, #5EEAD4 95%, #5EEAD4 96%, #6D28D9 96%, #6D28D9 100%)",
      "type": "color",
      "description": "stripe_75°"
    },
    "stripe_0°": {
      "value": "linear-gradient(0deg, #5EEAD4 0%, #5EEAD4 1%, #6D28D9 1%, #6D28D9 5%, #5EEAD4 5%, #5EEAD4 6%, #6D28D9 6%, #6D28D9 10%, #5EEAD4 10%, #5EEAD4 11%, #6D28D9 11%, #6D28D9 15%, #5EEAD4 15%, #5EEAD4 16%, #6D28D9 16%, #6D28D9 20%, #5EEAD4 20%, #5EEAD4 21%, #6D28D9 21%, #6D28D9 25%, #5EEAD4 25%, #5EEAD4 26%, #6D28D9 26%, #6D28D9 30%, #5EEAD4 30%, #5EEAD4 31%, #6D28D9 31%, #6D28D9 35%, #5EEAD4 35%, #5EEAD4 36%, #6D28D9 36%, #6D28D9 40%, #5EEAD4 40%, #5EEAD4 41%, #6D28D9 41%, #6D28D9 45%, #5EEAD4 45%, #5EEAD4 46%, #6D28D9 46%, #6D28D9 50%, #5EEAD4 50%, #5EEAD4 51%, #6D28D9 51%, #6D28D9 55%, #5EEAD4 55%, #5EEAD4 56%, #6D28D9 56%, #6D28D9 60%, #5EEAD4 60%, #5EEAD4 61%, #6D28D9 61%, #6D28D9 65%, #5EEAD4 65%, #5EEAD4 66%, #6D28D9 66%, #6D28D9 70%, #5EEAD4 70%, #5EEAD4 71%, #6D28D9 71%, #6D28D9 75%, #5EEAD4 75%, #5EEAD4 76%, #6D28D9 76%, #6D28D9 80%, #5EEAD4 80%, #5EEAD4 81%, #6D28D9 81%, #6D28D9 85%, #5EEAD4 85%, #5EEAD4 86%, #6D28D9 86%, #6D28D9 90%, #5EEAD4 90%, #5EEAD4 91%, #6D28D9 91%, #6D28D9 95%, #5EEAD4 95%, #5EEAD4 96%, #6D28D9 96%, #6D28D9 100%)",
      "type": "color",
      "description": "stripe_0°"
    },
    "stripe_90°": {
      "value": "linear-gradient(-90deg, #5EEAD4 0%, #5EEAD4 1%, #6D28D9 1%, #6D28D9 5%, #5EEAD4 5%, #5EEAD4 6%, #6D28D9 6%, #6D28D9 10%, #5EEAD4 10%, #5EEAD4 11%, #6D28D9 11%, #6D28D9 15%, #5EEAD4 15%, #5EEAD4 16%, #6D28D9 16%, #6D28D9 20%, #5EEAD4 20%, #5EEAD4 21%, #6D28D9 21%, #6D28D9 25%, #5EEAD4 25%, #5EEAD4 26%, #6D28D9 26%, #6D28D9 30%, #5EEAD4 30%, #5EEAD4 31%, #6D28D9 31%, #6D28D9 35%, #5EEAD4 35%, #5EEAD4 36%, #6D28D9 36%, #6D28D9 40%, #5EEAD4 40%, #5EEAD4 41%, #6D28D9 41%, #6D28D9 45%, #5EEAD4 45%, #5EEAD4 46%, #6D28D9 46%, #6D28D9 50%, #5EEAD4 50%, #5EEAD4 51%, #6D28D9 51%, #6D28D9 55%, #5EEAD4 55%, #5EEAD4 56%, #6D28D9 56%, #6D28D9 60%, #5EEAD4 60%, #5EEAD4 61%, #6D28D9 61%, #6D28D9 65%, #5EEAD4 65%, #5EEAD4 66%, #6D28D9 66%, #6D28D9 70%, #5EEAD4 70%, #5EEAD4 71%, #6D28D9 71%, #6D28D9 75%, #5EEAD4 75%, #5EEAD4 76%, #6D28D9 76%, #6D28D9 80%, #5EEAD4 80%, #5EEAD4 81%, #6D28D9 81%, #6D28D9 85%, #5EEAD4 85%, #5EEAD4 86%, #6D28D9 86%, #6D28D9 90%, #5EEAD4 90%, #5EEAD4 91%, #6D28D9 91%, #6D28D9 95%, #5EEAD4 95%, #5EEAD4 96%, #6D28D9 96%, #6D28D9 100%)",
      "type": "color",
      "description": "stripe_90°"
    }
  }
}